Workbook

Sheet BWT
A1: MODELO | B1: ANO | C1: PLACA | D1: ROTA | E1: MOTORISTA | F1: KM CARREGADO | G1: KM VAZIO | H1: HODÔMETRO | I1: FATURAMENTO | J1: VOLUME TRANSPORTADO | K1: CUSTO FIXO (SEM DEPREC.) | L1: CUSTO VARIÁVEL | M1: EBITDA ESTIMADO | N1: EBITDA ATINGIDO | O1: RESULTADO | P1: MARGEM | Q1: FATURAMENTO POR KM | R1: MÉDIA KM/L | S1: LITROS CONSUMIDOS | T1: Coluna1 | U1: 6 | V1: EBITDA BWT | W1: =Tabela1[[#Totals],[RESULTADO]] -> 202319.24 | Z1: Dia | AA1: =DAY(TODAY()) -> 13 | AB1: CUSTO FIXO 7 EIXOS | AC1: DEPREC. 7 EIXOS | AD1: CUSTO FIXO 7 EIXOS SEM DEPREC. | AF1: CUSTO FIXO 9 EIXOS | AG1: DEPREC. 9 EIXOS | AH1: CUSTO FIXO 9 EIXOS SEM DEPREC.
A2: VOLVO/FH 540 6X4T | B2: 2020 | C2: BDQ4E21 | D2: ISOTANK | E2: =IFERROR(_xlfn.XLOOKUP(Tabela1[[#This Row],[PLACA]],'Telemetria Sighra'!F:F,'Telemetria Sighra'!T:T),"NÃO EMBARCADO") -> MARCELO DE JESUS ARAUJO - 118 | F2: {=SUMPRODUCT((ISNUMBER(FIND(C2,Faturamento!$F$2:$F$1014)))*(Faturamento!$AA$2:$AA$1014))} -> 0 | G2: =Tabela1[[#This Row],[HODÔMETRO]]-Tabela1[[#This Row],[KM CARREGADO]] -> 5156.51 | H2: =_xlfn.XLOOKUP(C2,'Telemetria Sighra'!F:F,'Telemetria Sighra'!R:R,0) -> 5156.51 | I2: =SUMIF(Faturamento!AC:AC,C2,Faturamento!T:T) -> 0 | J2: {=SUMPRODUCT((ISNUMBER(FIND(C2,Faturamento!$F$2:$F$1014)))*(Faturamento!$R$2:$R$1014))} -> 0 | K2: =$AH$2/30*$AA$1 -> 9479.7957 | L2: 4.4694 | M2: 40000 | N2: =Tabela1[[#This Row],[RESULTADO]]/Tabela1[[#This Row],[EBITDA ESTIMADO]] -> -0.81315754 | O2: =Tabela1[[#This Row],[FATURAMENTO]]-Tabela1[[#This Row],[CUSTO FIXO (SEM DEPREC.)]]-(Tabela1[[#This Row],[CUSTO VARIÁVEL]]*Tabela1[[#This Row],[HODÔMETRO]])+IF(COUNTIFS('ROTAS REALIZADAS'!A:A,Tabela1[[#This Row],[PLACA]],'ROTAS REALIZADAS'!A:A,"SANTOS/PAULINIA")>0,$AA$1*1233.33,0) -> -32526.302 | P2: =IFERROR(Tabela1[[#This Row],[RESULTADO]]/Tabela1[[#This Row],[FATURAMENTO]],"-") -> - | Q2: =IFERROR(I2/H2,"-") -> 0 | R2: =_xlfn.XLOOKUP(C2,'Telemetria Sighra'!F:F,'Telemetria Sighra'!S:S,0) -> 1.8454744 | S2: =_xlfn.XLOOKUP(Tabela1[[#This Row],[PLACA]],'Telemetria Sighra'!F:F,'Telemetria Sighra'!I:I,0) -> 2794.23 | T2: =IFERROR((Tabela1[[#This Row],[LITROS CONSUMIDOS]]*$U$1)/Tabela1[[#This Row],[HODÔMETRO]],"-") -> 3.2513037 | V2: EBITDA SUBCONTRATADO | W2: =SUMIF(Faturamento!AB:AB,"SUBCONTRATADO",Faturamento!T:T)*0.3 -> 38271.891 | AB2: 37311.23 | AC2: =230183.45/12 -> 19181.954 | AD2: =AB2-AC2 -> 18129.276 | AF2: 45740.36 | AG2: =286366.9/12 -> 23863.908 | AH2: =AF2-AG2 -> 21876.452
A3: DAF/XF FTT 530 | B3: 2021 | C3: RHG5D76 | D3: SANTOS X PAULINIA | E3: =IFERROR(_xlfn.XLOOKUP(Tabela1[[#This Row],[PLACA]],'Telemetria Sighra'!F:F,'Telemetria Sighra'!T:T),"NÃO EMBARCADO") -> JEFFERSON APARECIDO DE LIMA - 10857 | F3: {=SUMPRODUCT((ISNUMBER(FIND(C3,Faturamento!$F$2:$F$1014)))*(Faturamento!$AA$2:$AA$1014))} -> 0 | G3: =Tabela1[[#This Row],[HODÔMETRO]]-Tabela1[[#This Row],[KM CARREGADO]] -> 1342.87 | H3: =_xlfn.XLOOKUP(C3,'Telemetria Sighra'!F:F,'Telemetria Sighra'!R:R,0) -> 1342.87 | I3: =SUMIF(Faturamento!AC:AC,C3,Faturamento!T:T) -> 0 | J3: {=SUMPRODUCT((ISNUMBER(FIND(C3,Faturamento!$F$2:$F$1014)))*(Faturamento!$R$2:$R$1014))} -> 0 | K3: =$AH$2/30*$AA$1 -> 9479.7957 | L3: 4.4694 | M3: 39990 | N3: =Tabela1[[#This Row],[RESULTADO]]/Tabela1[[#This Row],[EBITDA ESTIMADO]] -> -0.38713726 | O3: =Tabela1[[#This Row],[FATURAMENTO]]-Tabela1[[#This Row],[CUSTO FIXO (SEM DEPREC.)]]-(Tabela1[[#This Row],[CUSTO VARIÁVEL]]*Tabela1[[#This Row],[HODÔMETRO]])+IF(COUNTIFS('ROTAS REALIZADAS'!A:A,Tabela1[[#This Row],[PLACA]],'ROTAS REALIZADAS'!A:A,"SANTOS/PAULINIA")>0,$AA$1*1233.33,0) -> -15481.619 | P3: =IFERROR(Tabela1[[#This Row],[RESULTADO]]/Tabela1[[#This Row],[FATURAMENTO]],"-") -> - | Q3: =IFERROR(I3/H3,"-") -> 0 | R3: =_xlfn.XLOOKUP(C3,'Telemetria Sighra'!F:F,'Telemetria Sighra'!S:S,0) -> 1.7216831 | S3: =_xlfn.XLOOKUP(Tabela1[[#This Row],[PLACA]],'Telemetria Sighra'!F:F,'Telemetria Sighra'!I:I,0) -> 780.01 | T3: =IFERROR((Tabela1[[#This Row],[LITROS CONSUMIDOS]]*$U$1)/Tabela1[[#This Row],[HODÔMETRO]],"-") -> 3.4851177 | V3: RESULTADO | W3: =W1+W2 -> 240591.13
A4: DAF/XF FTT 530 | B4: 2024 | C4: SEX2C71 | D4: SANTOS X PAULINIA | E4: =IFERROR(_xlfn.XLOOKUP(Tabela1[[#This Row],[PLACA]],'Telemetria Sighra'!F:F,'Telemetria Sighra'!T:T),"NÃO EMBARCADO") -> ORVITO ANDERLE - 217 | F4: {=SUMPRODUCT((ISNUMBER(FIND(C4,Faturamento!$F$2:$F$1014)))*(Faturamento!$AA$2:$AA$1014))} -> 0 | G4: =Tabela1[[#This Row],[HODÔMETRO]]-Tabela1[[#This Row],[KM CARREGADO]] -> 1018.19 | H4: =_xlfn.XLOOKUP(C4,'Telemetria Sighra'!F:F,'Telemetria Sighra'!R:R,0) -> 1018.19 | I4: =SUMIF(Faturamento!AC:AC,C4,Faturamento!T:T) -> 0 | J4: {=SUMPRODUCT((ISNUMBER(FIND(C4,Faturamento!$F$2:$F$1014)))*(Faturamento!$R$2:$R$1014))} -> 0 | K4: =$AH$2/30*$AA$1 -> 9479.7957 | L4: 4.4694 | M4: 39990 | N4: =Tabela1[[#This Row],[RESULTADO]]/Tabela1[[#This Row],[EBITDA ESTIMADO]] -> -0.35085007 | O4: =Tabela1[[#This Row],[FATURAMENTO]]-Tabela1[[#This Row],[CUSTO FIXO (SEM DEPREC.)]]-(Tabela1[[#This Row],[CUSTO VARIÁVEL]]*Tabela1[[#This Row],[HODÔMETRO]])+IF(COUNTIFS('ROTAS REALIZADAS'!A:A,Tabela1[[#This Row],[PLACA]],'ROTAS REALIZADAS'!A:A,"SANTOS/PAULINIA")>0,$AA$1*1233.33,0) -> -14030.494 | P4: =IFERROR(Tabela1[[#This Row],[RESULTADO]]/Tabela1[[#This Row],[FATURAMENTO]],"-") -> - | Q4: =IFERROR(I4/H4,"-") -> 0 | R4: =_xlfn.XLOOKUP(C4,'Telemetria Sighra'!F:F,'Telemetria Sighra'!S:S,0) -> 1.592123 | S4: =_xlfn.XLOOKUP(Tabela1[[#This Row],[PLACA]],'Telemetria Sighra'!F:F,'Telemetria Sighra'!I:I,0) -> 639.58 | T4: =IFERROR((Tabela1[[#This Row],[LITROS CONSUMIDOS]]*$U$1)/Tabela1[[#This Row],[HODÔMETRO]],"-") -> 3.7689233
A5: DAF/XF FTT 530 | B5: 2024 | C5: SFA7F70 | D5: VIBRA | E5: =IFERROR(_xlfn.XLOOKUP(Tabela1[[#This Row],[PLACA]],'Telemetria Sighra'!F:F,'Telemetria Sighra'!T:T),"NÃO EMBARCADO") -> PAULO ROBERTO EVANGELISTA SOARES - 255 | F5: {=SUMPRODUCT((ISNUMBER(FIND(C5,Faturamento!$F$2:$F$1014)))*(Faturamento!$AA$2:$AA$1014))} -> 430 | G5: =Tabela1[[#This Row],[HODÔMETRO]]-Tabela1[[#This Row],[KM CARREGADO]] -> 1702.44 | H5: =_xlfn.XLOOKUP(C5,'Telemetria Sighra'!F:F,'Telemetria Sighra'!R:R,0) -> 2132.44 | I5: =SUMIF(Faturamento!AC:AC,C5,Faturamento!T:T) -> 6300.07 | J5: {=SUMPRODUCT((ISNUMBER(FIND(C5,Faturamento!$F$2:$F$1014)))*(Faturamento!$R$2:$R$1014))} -> 124316 | K5: =$AH$2/30*$AA$1 -> 9479.7957 | L5: 4.4694 | M5: 69761 | N5: =Tabela1[[#This Row],[RESULTADO]]/Tabela1[[#This Row],[EBITDA ESTIMADO]] -> -0.18219998 | O5: =Tabela1[[#This Row],[FATURAMENTO]]-Tabela1[[#This Row],[CUSTO FIXO (SEM DEPREC.)]]-(Tabela1[[#This Row],[CUSTO VARIÁVEL]]*Tabela1[[#This Row],[HODÔMETRO]])+IF(COUNTIFS('ROTAS REALIZADAS'!A:A,Tabela1[[#This Row],[PLACA]],'ROTAS REALIZADAS'!A:A,"SANTOS/PAULINIA")>0,$AA$1*1233.33,0) -> -12710.453 | P5: =IFERROR(Tabela1[[#This Row],[RESULTADO]]/Tabela1[[#This Row],[FATURAMENTO]],"-") -> -2.0175098 | Q5: =IFERROR(I5/H5,"-") -> 2.954395 | R5: =_xlfn.XLOOKUP(C5,'Telemetria Sighra'!F:F,'Telemetria Sighra'!S:S,0) -> 2.1289231 | S5: =_xlfn.XLOOKUP(Tabela1[[#This Row],[PLACA]],'Telemetria Sighra'!F:F,'Telemetria Sighra'!I:I,0) -> 1001.76 | T5: =IFERROR((Tabela1[[#This Row],[LITROS CONSUMIDOS]]*$U$1)/Tabela1[[#This Row],[HODÔMETRO]],"-") -> 2.8186303
A6: SCANIA/R 480 A6X4 | B6: 2016 | C6: BAY4H67 | D6: PGUA X LAPA | E6: =IFERROR(_xlfn.XLOOKUP(Tabela1[[#This Row],[PLACA]],'Telemetria Sighra'!F:F,'Telemetria Sighra'!T:T),"NÃO EMBARCADO") -> LUIZ TOME DOS SANTOS FILHO - 10844 | F6: {=SUMPRODUCT((ISNUMBER(FIND(C6,Faturamento!$F$2:$F$1014)))*(Faturamento!$AA$2:$AA$1014))} -> 0 | G6: =Tabela1[[#This Row],[HODÔMETRO]]-Tabela1[[#This Row],[KM CARREGADO]] -> 1108.95 | H6: =_xlfn.XLOOKUP(C6,'Telemetria Sighra'!F:F,'Telemetria Sighra'!R:R,0) -> 1108.95 | I6: =SUMIF(Faturamento!AC:AC,C6,Faturamento!T:T) -> 0 | J6: {=SUMPRODUCT((ISNUMBER(FIND(C6,Faturamento!$F$2:$F$1014)))*(Faturamento!$R$2:$R$1014))} -> 0 | K6: =$AD$2/30*$AA$1 -> 7856.0195 | L6: 3.55 | M6: 36051 | N6: =Tabela1[[#This Row],[RESULTADO]]/Tabela1[[#This Row],[EBITDA ESTIMADO]] -> -0.32711414 | O6: =Tabela1[[#This Row],[FATURAMENTO]]-Tabela1[[#This Row],[CUSTO FIXO (SEM DEPREC.)]]-(Tabela1[[#This Row],[CUSTO VARIÁVEL]]*Tabela1[[#This Row],[HODÔMETRO]])+IF(COUNTIFS('ROTAS REALIZADAS'!A:A,Tabela1[[#This Row],[PLACA]],'ROTAS REALIZADAS'!A:A,"SANTOS/PAULINIA")>0,$AA$1*1233.33,0) -> -11792.792 | P6: =IFERROR(Tabela1[[#This Row],[RESULTADO]]/Tabela1[[#This Row],[FATURAMENTO]],"-") -> - | Q6: =IFERROR(I6/H6,"-") -> 0 | R6: =_xlfn.XLOOKUP(C6,'Telemetria Sighra'!F:F,'Telemetria Sighra'!S:S,0) -> 2.1881301 | S6: =_xlfn.XLOOKUP(Tabela1[[#This Row],[PLACA]],'Telemetria Sighra'!F:F,'Telemetria Sighra'!I:I,0) -> 506.83 | T6: =IFERROR((Tabela1[[#This Row],[LITROS CONSUMIDOS]]*$U$1)/Tabela1[[#This Row],[HODÔMETRO]],"-") -> 2.7422156
A7: SCANIA/R 480 A6X4 | B7: 2016 | C7: BAQ0D27 | D7: METANOL | E7: =IFERROR(_xlfn.XLOOKUP(Tabela1[[#This Row],[PLACA]],'Telemetria Sighra'!F:F,'Telemetria Sighra'!T:T),"NÃO EMBARCADO") -> CLODOALDO SANTIAGO - 10247 | F7: {=SUMPRODUCT((ISNUMBER(FIND(C7,Faturamento!$F$2:$F$1014)))*(Faturamento!$AA$2:$AA$1014))} -> 0 | G7: =Tabela1[[#This Row],[HODÔMETRO]]-Tabela1[[#This Row],[KM CARREGADO]] -> 553.76 | H7: =_xlfn.XLOOKUP(C7,'Telemetria Sighra'!F:F,'Telemetria Sighra'!R:R,0) -> 553.76 | I7: =SUMIF(Faturamento!AC:AC,C7,Faturamento!T:T) -> 0 | J7: {=SUMPRODUCT((ISNUMBER(FIND(C7,Faturamento!$F$2:$F$1014)))*(Faturamento!$R$2:$R$1014))} -> 0 | K7: =$AD$2/30*$AA$1 -> 7856.0195 | L7: 3.55 | M7: 47896 | N7: =Tabela1[[#This Row],[RESULTADO]]/Tabela1[[#This Row],[EBITDA ESTIMADO]] -> -0.20506655 | O7: =Tabela1[[#This Row],[FATURAMENTO]]-Tabela1[[#This Row],[CUSTO FIXO (SEM DEPREC.)]]-(Tabela1[[#This Row],[CUSTO VARIÁVEL]]*Tabela1[[#This Row],[HODÔMETRO]])+IF(COUNTIFS('ROTAS REALIZADAS'!A:A,Tabela1[[#This Row],[PLACA]],'ROTAS REALIZADAS'!A:A,"SANTOS/PAULINIA")>0,$AA$1*1233.33,0) -> -9821.8675 | P7: =IFERROR(Tabela1[[#This Row],[RESULTADO]]/Tabela1[[#This Row],[FATURAMENTO]],"-") -> - | Q7: =IFERROR(I7/H7,"-") -> 0 | R7: =_xlfn.XLOOKUP(C7,'Telemetria Sighra'!F:F,'Telemetria Sighra'!S:S,0) -> 2.6425231 | S7: =_xlfn.XLOOKUP(Tabela1[[#This Row],[PLACA]],'Telemetria Sighra'!F:F,'Telemetria Sighra'!I:I,0) -> 209.58 | T7: =IFERROR((Tabela1[[#This Row],[LITROS CONSUMIDOS]]*$U$1)/Tabela1[[#This Row],[HODÔMETRO]],"-") -> 2.2708032
A8: DAF/XF FTT 530 | B8: 2023 | C8: SEE2J88 | D8: SANTOS X PAULINIA | E8: =IFERROR(_xlfn.XLOOKUP(Tabela1[[#This Row],[PLACA]],'Telemetria Sighra'!F:F,'Telemetria Sighra'!T:T),"NÃO EMBARCADO") -> MARCOS AURELIO NOGUEIRA - 235 | F8: {=SUMPRODUCT((ISNUMBER(FIND(C8,Faturamento!$F$2:$F$1014)))*(Faturamento!$AA$2:$AA$1014))} -> 494 | G8: =Tabela1[[#This Row],[HODÔMETRO]]-Tabela1[[#This Row],[KM CARREGADO]] -> 1448.6 | H8: =_xlfn.XLOOKUP(C8,'Telemetria Sighra'!F:F,'Telemetria Sighra'!R:R,0) -> 1942.6 | I8: =SUMIF(Faturamento!AC:AC,C8,Faturamento!T:T) -> 8477.29 | J8: {=SUMPRODUCT((ISNUMBER(FIND(C8,Faturamento!$F$2:$F$1014)))*(Faturamento!$R$2:$R$1014))} -> 121889 | K8: =$AH$2/30*$AA$1 -> 9479.7957 | L8: 4.4694 | M8: 39990 | N8: =Tabela1[[#This Row],[RESULTADO]]/Tabela1[[#This Row],[EBITDA ESTIMADO]] -> -0.2421796 | O8: =Tabela1[[#This Row],[FATURAMENTO]]-Tabela1[[#This Row],[CUSTO FIXO (SEM DEPREC.)]]-(Tabela1[[#This Row],[CUSTO VARIÁVEL]]*Tabela1[[#This Row],[HODÔMETRO]])+IF(COUNTIFS('ROTAS REALIZADAS'!A:A,Tabela1[[#This Row],[PLACA]],'ROTAS REALIZADAS'!A:A,"SANTOS/PAULINIA")>0,$AA$1*1233.33,0) -> -9684.7622 | P8: =IFERROR(Tabela1[[#This Row],[RESULTADO]]/Tabela1[[#This Row],[FATURAMENTO]],"-") -> -1.1424361 | Q8: =IFERROR(I8/H8,"-") -> 4.3638886 | R8: =_xlfn.XLOOKUP(C8,'Telemetria Sighra'!F:F,'Telemetria Sighra'!S:S,0) -> 1.5095532 | S8: =_xlfn.XLOOKUP(Tabela1[[#This Row],[PLACA]],'Telemetria Sighra'!F:F,'Telemetria Sighra'!I:I,0) -> 1287.01 | T8: =IFERROR((Tabela1[[#This Row],[LITROS CONSUMIDOS]]*$U$1)/Tabela1[[#This Row],[HODÔMETRO]],"-") -> 3.9751158
A9: VOLVO/FH 500 6X4T S BIO | B9: 2025 | C9: TAW2A67 | D9: VIBRA | E9: =IFERROR(_xlfn.XLOOKUP(Tabela1[[#This Row],[PLACA]],'Telemetria Sighra'!F:F,'Telemetria Sighra'!T:T),"NÃO EMBARCADO") -> LUIZ ALEX DOS SANTOS - 167 | F9: {=SUMPRODUCT((ISNUMBER(FIND(C9,Faturamento!$F$2:$F$1014)))*(Faturamento!$AA$2:$AA$1014))} -> 20 | G9: =Tabela1[[#This Row],[HODÔMETRO]]-Tabela1[[#This Row],[KM CARREGADO]] -> 351.2 | H9: =_xlfn.XLOOKUP(C9,'Telemetria Sighra'!F:F,'Telemetria Sighra'!R:R,0) -> 371.2 | I9: =SUMIF(Faturamento!AC:AC,C9,Faturamento!T:T) -> 1618.07 | J9: {=SUMPRODUCT((ISNUMBER(FIND(C9,Faturamento!$F$2:$F$1014)))*(Faturamento!$R$2:$R$1014))} -> 60062 | K9: =$AH$2/30*$AA$1 -> 9479.7957 | L9: 4.4694 | M9: 69761 | N9: =Tabela1[[#This Row],[RESULTADO]]/Tabela1[[#This Row],[EBITDA ESTIMADO]] -> -0.13647693 | O9: =Tabela1[[#This Row],[FATURAMENTO]]-Tabela1[[#This Row],[CUSTO FIXO (SEM DEPREC.)]]-(Tabela1[[#This Row],[CUSTO VARIÁVEL]]*Tabela1[[#This Row],[HODÔMETRO]])+IF(COUNTIFS('ROTAS REALIZADAS'!A:A,Tabela1[[#This Row],[PLACA]],'ROTAS REALIZADAS'!A:A,"SANTOS/PAULINIA")>0,$AA$1*1233.33,0) -> -9520.767 | P9: =IFERROR(Tabela1[[#This Row],[RESULTADO]]/Tabela1[[#This Row],[FATURAMENTO]],"-") -> -5.8840267 | Q9: =IFERROR(I9/H9,"-") -> 4.3590248 | R9: =_xlfn.XLOOKUP(C9,'Telemetria Sighra'!F:F,'Telemetria Sighra'!S:S,0) -> 2.0648462 | S9: =_xlfn.XLOOKUP(Tabela1[[#This Row],[PLACA]],'Telemetria Sighra'!F:F,'Telemetria Sighra'!I:I,0) -> 179.81 | T9: =IFERROR((Tabela1[[#This Row],[LITROS CONSUMIDOS]]*$U$1)/Tabela1[[#This Row],[HODÔMETRO]],"-") -> 2.9064116
A10: DAF/XF FTT 530 | B10: 2021 | C10: RHI3D91 | D10: ISOTANK | E10: =IFERROR(_xlfn.XLOOKUP(Tabela1[[#This Row],[PLACA]],'Telemetria Sighra'!F:F,'Telemetria Sighra'!T:T),"NÃO EMBARCADO") -> NÃO EMBARCADO | F10: {=SUMPRODUCT((ISNUMBER(FIND(C10,Faturamento!$F$2:$F$1014)))*(Faturamento!$AA$2:$AA$1014))} -> 0 | G10: =Tabela1[[#This Row],[HODÔMETRO]]-Tabela1[[#This Row],[KM CARREGADO]] -> 0 | H10: =_xlfn.XLOOKUP(C10,'Telemetria Sighra'!F:F,'Telemetria Sighra'!R:R,0) -> 0 | I10: =SUMIF(Faturamento!AC:AC,C10,Faturamento!T:T) -> 0 | J10: {=SUMPRODUCT((ISNUMBER(FIND(C10,Faturamento!$F$2:$F$1014)))*(Faturamento!$R$2:$R$1014))} -> 0 | K10: =$AH$2/30*$AA$1 -> 9479.7957 | L10: 4.4694 | M10: 40000 | N10: =Tabela1[[#This Row],[RESULTADO]]/Tabela1[[#This Row],[EBITDA ESTIMADO]] -> -0.23699489 | O10: =Tabela1[[#This Row],[FATURAMENTO]]-Tabela1[[#This Row],[CUSTO FIXO (SEM DEPREC.)]]-(Tabela1[[#This Row],[CUSTO VARIÁVEL]]*Tabela1[[#This Row],[HODÔMETRO]])+IF(COUNTIFS('ROTAS REALIZADAS'!A:A,Tabela1[[#This Row],[PLACA]],'ROTAS REALIZADAS'!A:A,"SANTOS/PAULINIA")>0,$AA$1*1233.33,0) -> -9479.7957 | P10: =IFERROR(Tabela1[[#This Row],[RESULTADO]]/Tabela1[[#This Row],[FATURAMENTO]],"-") -> - | Q10: =IFERROR(I10/H10,"-") -> - | R10: =_xlfn.XLOOKUP(C10,'Telemetria Sighra'!F:F,'Telemetria Sighra'!S:S,0) -> 0 | S10: =_xlfn.XLOOKUP(Tabela1[[#This Row],[PLACA]],'Telemetria Sighra'!F:F,'Telemetria Sighra'!I:I,0) -> 0 | T10: =IFERROR((Tabela1[[#This Row],[LITROS CONSUMIDOS]]*$U$1)/Tabela1[[#This Row],[HODÔMETRO]],"-") -> -
A11: VOLVO/FH 540 6X4T | B11: 2020 | C11: BDQ4E34 | D11: Spot melhor tarifa | E11: =IFERROR(_xlfn.XLOOKUP(Tabela1[[#This Row],[PLACA]],'Telemetria Sighra'!F:F,'Telemetria Sighra'!T:T),"NÃO EMBARCADO") -> NÃO EMBARCADO | F11: {=SUMPRODUCT((ISNUMBER(FIND(C11,Faturamento!$F$2:$F$1014)))*(Faturamento!$AA$2:$AA$1014))} -> 0 | G11: =Tabela1[[#This Row],[HODÔMETRO]]-Tabela1[[#This Row],[KM CARREGADO]] -> 0 | H11: =_xlfn.XLOOKUP(C11,'Telemetria Sighra'!F:F,'Telemetria Sighra'!R:R,0) -> 0 | I11: =SUMIF(Faturamento!AC:AC,C11,Faturamento!T:T) -> 0 | J11: {=SUMPRODUCT((ISNUMBER(FIND(C11,Faturamento!$F$2:$F$1014)))*(Faturamento!$R$2:$R$1014))} -> 0 | K11: =$AH$2/30*$AA$1 -> 9479.7957 | L11: 4.4694 | M11: 40000 | N11: =Tabela1[[#This Row],[RESULTADO]]/Tabela1[[#This Row],[EBITDA ESTIMADO]] -> -0.23699489 | O11: =Tabela1[[#This Row],[FATURAMENTO]]-Tabela1[[#This Row],[CUSTO FIXO (SEM DEPREC.)]]-(Tabela1[[#This Row],[CUSTO VARIÁVEL]]*Tabela1[[#This Row],[HODÔMETRO]])+IF(COUNTIFS('ROTAS REALIZADAS'!A:A,Tabela1[[#This Row],[PLACA]],'ROTAS REALIZADAS'!A:A,"SANTOS/PAULINIA")>0,$AA$1*1233.33,0) -> -9479.7957 | P11: =IFERROR(Tabela1[[#This Row],[RESULTADO]]/Tabela1[[#This Row],[FATURAMENTO]],"-") -> - | Q11: =IFERROR(I11/H11,"-") -> - | R11: =_xlfn.XLOOKUP(C11,'Telemetria Sighra'!F:F,'Telemetria Sighra'!S:S,0) -> 0 | S11: =_xlfn.XLOOKUP(Tabela1[[#This Row],[PLACA]],'Telemetria Sighra'!F:F,'Telemetria Sighra'!I:I,0) -> 0 | T11: =IFERROR((Tabela1[[#This Row],[LITROS CONSUMIDOS]]*$U$1)/Tabela1[[#This Row],[HODÔMETRO]],"-") -> -
A12: DAF/XF FTT 530 | B12: 2024 | C12: SFC5F45 | D12: ISOTANK | E12: =IFERROR(_xlfn.XLOOKUP(Tabela1[[#This Row],[PLACA]],'Telemetria Sighra'!F:F,'Telemetria Sighra'!T:T),"NÃO EMBARCADO") -> EMERSON MENON CUNHA - 128 | F12: {=SUMPRODUCT((ISNUMBER(FIND(C12,Faturamento!$F$2:$F$1014)))*(Faturamento!$AA$2:$AA$1014))} -> 645 | G12: =Tabela1[[#This Row],[HODÔMETRO]]-Tabela1[[#This Row],[KM CARREGADO]] -> 1268.85 | H12: =_xlfn.XLOOKUP(C12,'Telemetria Sighra'!F:F,'Telemetria Sighra'!R:R,0) -> 1913.85 | I12: =SUMIF(Faturamento!AC:AC,C12,Faturamento!T:T) -> 8660.51 | J12: {=SUMPRODUCT((ISNUMBER(FIND(C12,Faturamento!$F$2:$F$1014)))*(Faturamento!$R$2:$R$1014))} -> 145601 | K12: =$AH$2/30*$AA$1 -> 9479.7957 | L12: 4.4694 | M12: 40000 | N12: =Tabela1[[#This Row],[RESULTADO]]/Tabela1[[#This Row],[EBITDA ESTIMADO]] -> -0.23432617 | O12: =Tabela1[[#This Row],[FATURAMENTO]]-Tabela1[[#This Row],[CUSTO FIXO (SEM DEPREC.)]]-(Tabela1[[#This Row],[CUSTO VARIÁVEL]]*Tabela1[[#This Row],[HODÔMETRO]])+IF(COUNTIFS('ROTAS REALIZADAS'!A:A,Tabela1[[#This Row],[PLACA]],'ROTAS REALIZADAS'!A:A,"SANTOS/PAULINIA")>0,$AA$1*1233.33,0) -> -9373.0469 | P12: =IFERROR(Tabela1[[#This Row],[RESULTADO]]/Tabela1[[#This Row],[FATURAMENTO]],"-") -> -1.0822742 | Q12: =IFERROR(I12/H12,"-") -> 4.525177 | R12: =_xlfn.XLOOKUP(C12,'Telemetria Sighra'!F:F,'Telemetria Sighra'!S:S,0) -> 2.5586643 | S12: =_xlfn.XLOOKUP(Tabela1[[#This Row],[PLACA]],'Telemetria Sighra'!F:F,'Telemetria Sighra'!I:I,0) -> 748.07 | T12: =IFERROR((Tabela1[[#This Row],[LITROS CONSUMIDOS]]*$U$1)/Tabela1[[#This Row],[HODÔMETRO]],"-") -> 2.3452308
A13: DAF/XF FTT 530 | B13: 2024 | C13: SEX2C73 | D13: METANOL | E13: =IFERROR(_xlfn.XLOOKUP(Tabela1[[#This Row],[PLACA]],'Telemetria Sighra'!F:F,'Telemetria Sighra'!T:T),"NÃO EMBARCADO") -> MARIOVANY QUIRINO GOMES - 200 | F13: {=SUMPRODUCT((ISNUMBER(FIND(C13,Faturamento!$F$2:$F$1014)))*(Faturamento!$AA$2:$AA$1014))} -> 860 | G13: =Tabela1[[#This Row],[HODÔMETRO]]-Tabela1[[#This Row],[KM CARREGADO]] -> 1821.91 | H13: =_xlfn.XLOOKUP(C13,'Telemetria Sighra'!F:F,'Telemetria Sighra'!R:R,0) -> 2681.91 | I13: =SUMIF(Faturamento!AC:AC,C13,Faturamento!T:T) -> 12919.55 | J13: {=SUMPRODUCT((ISNUMBER(FIND(C13,Faturamento!$F$2:$F$1014)))*(Faturamento!$R$2:$R$1014))} -> 247926 | K13: =$AH$2/30*$AA$1 -> 9479.7957 | L13: 4.4694 | M13: 47896 | N13: =Tabela1[[#This Row],[RESULTADO]]/Tabela1[[#This Row],[EBITDA ESTIMADO]] -> -0.17844443 | O13: =Tabela1[[#This Row],[FATURAMENTO]]-Tabela1[[#This Row],[CUSTO FIXO (SEM DEPREC.)]]-(Tabela1[[#This Row],[CUSTO VARIÁVEL]]*Tabela1[[#This Row],[HODÔMETRO]])+IF(COUNTIFS('ROTAS REALIZADAS'!A:A,Tabela1[[#This Row],[PLACA]],'ROTAS REALIZADAS'!A:A,"SANTOS/PAULINIA")>0,$AA$1*1233.33,0) -> -8546.7743 | P13: =IFERROR(Tabela1[[#This Row],[RESULTADO]]/Tabela1[[#This Row],[FATURAMENTO]],"-") -> -0.66153808 | Q13: =IFERROR(I13/H13,"-") -> 4.8172944 | R13: =_xlfn.XLOOKUP(C13,'Telemetria Sighra'!F:F,'Telemetria Sighra'!S:S,0) -> 1.9951277 | S13: =_xlfn.XLOOKUP(Tabela1[[#This Row],[PLACA]],'Telemetria Sighra'!F:F,'Telemetria Sighra'!I:I,0) -> 1344.33 | T13: =IFERROR((Tabela1[[#This Row],[LITROS CONSUMIDOS]]*$U$1)/Tabela1[[#This Row],[HODÔMETRO]],"-") -> 3.0075506
A14: DAF/XF FTT 530 | B14: 2023 | C14: SEE2J92 | D14: VIBRA | E14: =IFERROR(_xlfn.XLOOKUP(Tabela1[[#This Row],[PLACA]],'Telemetria Sighra'!F:F,'Telemetria Sighra'!T:T),"NÃO EMBARCADO") -> SILAS DE LIMA - 225 | F14: {=SUMPRODUCT((ISNUMBER(FIND(C14,Faturamento!$F$2:$F$1014)))*(Faturamento!$AA$2:$AA$1014))} -> 860 | G14: =Tabela1[[#This Row],[HODÔMETRO]]-Tabela1[[#This Row],[KM CARREGADO]] -> 1524.76 | H14: =_xlfn.XLOOKUP(C14,'Telemetria Sighra'!F:F,'Telemetria Sighra'!R:R,0) -> 2384.76 | I14: =SUMIF(Faturamento!AC:AC,C14,Faturamento!T:T) -> 12599.78 | J14: {=SUMPRODUCT((ISNUMBER(FIND(C14,Faturamento!$F$2:$F$1014)))*(Faturamento!$R$2:$R$1014))} -> 246833 | K14: =$AH$2/30*$AA$1 -> 9479.7957 | L14: 4.4694 | M14: 69761 | N14: =Tabela1[[#This Row],[RESULTADO]]/Tabela1[[#This Row],[EBITDA ESTIMADO]] -> -0.10806127 | O14: =Tabela1[[#This Row],[FATURAMENTO]]-Tabela1[[#This Row],[CUSTO FIXO (SEM DEPREC.)]]-(Tabela1[[#This Row],[CUSTO VARIÁVEL]]*Tabela1[[#This Row],[HODÔMETRO]])+IF(COUNTIFS('ROTAS REALIZADAS'!A:A,Tabela1[[#This Row],[PLACA]],'ROTAS REALIZADAS'!A:A,"SANTOS/PAULINIA")>0,$AA$1*1233.33,0) -> -7538.4621 | P14: =IFERROR(Tabela1[[#This Row],[RESULTADO]]/Tabela1[[#This Row],[FATURAMENTO]],"-") -> -0.59830109 | Q14: =IFERROR(I14/H14,"-") -> 5.2834583 | R14: =_xlfn.XLOOKUP(C14,'Telemetria Sighra'!F:F,'Telemetria Sighra'!S:S,0) -> 2.1322695 | S14: =_xlfn.XLOOKUP(Tabela1[[#This Row],[PLACA]],'Telemetria Sighra'!F:F,'Telemetria Sighra'!I:I,0) -> 1118.55 | T14: =IFERROR((Tabela1[[#This Row],[LITROS CONSUMIDOS]]*$U$1)/Tabela1[[#This Row],[HODÔMETRO]],"-") -> 2.8142455
A15: DAF/XF FTT 530 | B15: 2023 | C15: SEE2J86 | D15: SANTOS X PAULINIA | E15: =IFERROR(_xlfn.XLOOKUP(Tabela1[[#This Row],[PLACA]],'Telemetria Sighra'!F:F,'Telemetria Sighra'!T:T),"NÃO EMBARCADO") -> SAMUEL CRUZ TORRES DE BRITO - 189 | F15: {=SUMPRODUCT((ISNUMBER(FIND(C15,Faturamento!$F$2:$F$1014)))*(Faturamento!$AA$2:$AA$1014))} -> 860 | G15: =Tabela1[[#This Row],[HODÔMETRO]]-Tabela1[[#This Row],[KM CARREGADO]] -> 1138.54 | H15: =_xlfn.XLOOKUP(C15,'Telemetria Sighra'!F:F,'Telemetria Sighra'!R:R,0) -> 1998.54 | I15: =SUMIF(Faturamento!AC:AC,C15,Faturamento!T:T) -> 12600.12 | J15: {=SUMPRODUCT((ISNUMBER(FIND(C15,Faturamento!$F$2:$F$1014)))*(Faturamento!$R$2:$R$1014))} -> 247201 | K15: =$AH$2/30*$AA$1 -> 9479.7957 | L15: 4.4694 | M15: 39990 | N15: =Tabela1[[#This Row],[RESULTADO]]/Tabela1[[#This Row],[EBITDA ESTIMADO]] -> -0.14533509 | O15: =Tabela1[[#This Row],[FATURAMENTO]]-Tabela1[[#This Row],[CUSTO FIXO (SEM DEPREC.)]]-(Tabela1[[#This Row],[CUSTO VARIÁVEL]]*Tabela1[[#This Row],[HODÔMETRO]])+IF(COUNTIFS('ROTAS REALIZADAS'!A:A,Tabela1[[#This Row],[PLACA]],'ROTAS REALIZADAS'!A:A,"SANTOS/PAULINIA")>0,$AA$1*1233.33,0) -> -5811.9504 | P15: =IFERROR(Tabela1[[#This Row],[RESULTADO]]/Tabela1[[#This Row],[FATURAMENTO]],"-") -> -0.46126151 | Q15: =IFERROR(I15/H15,"-") -> 6.3046624 | R15: =_xlfn.XLOOKUP(C15,'Telemetria Sighra'!F:F,'Telemetria Sighra'!S:S,0) -> 2.0687367 | S15: =_xlfn.XLOOKUP(Tabela1[[#This Row],[PLACA]],'Telemetria Sighra'!F:F,'Telemetria Sighra'!I:I,0) -> 966.15 | T15: =IFERROR((Tabela1[[#This Row],[LITROS CONSUMIDOS]]*$U$1)/Tabela1[[#This Row],[HODÔMETRO]],"-") -> 2.9005674
A16: DAF/XF FTT 530 | B16: 2023 | C16: SEE0H97 | D16: CAMERA | E16: =IFERROR(_xlfn.XLOOKUP(Tabela1[[#This Row],[PLACA]],'Telemetria Sighra'!F:F,'Telemetria Sighra'!T:T),"NÃO EMBARCADO") -> JOSE CLAUDIO DA CRUZ - 201 | F16: {=SUMPRODUCT((ISNUMBER(FIND(C16,Faturamento!$F$2:$F$1014)))*(Faturamento!$AA$2:$AA$1014))} -> 580 | G16: =Tabela1[[#This Row],[HODÔMETRO]]-Tabela1[[#This Row],[KM CARREGADO]] -> 186.37 | H16: =_xlfn.XLOOKUP(C16,'Telemetria Sighra'!F:F,'Telemetria Sighra'!R:R,0) -> 766.37 | I16: =SUMIF(Faturamento!AC:AC,C16,Faturamento!T:T) -> 8338.09 | J16: {=SUMPRODUCT((ISNUMBER(FIND(C16,Faturamento!$F$2:$F$1014)))*(Faturamento!$R$2:$R$1014))} -> 59250 | K16: =$AH$2/30*$AA$1 -> 9479.7957 | L16: 4.4694 | M16: 53428 | N16: =Tabela1[[#This Row],[RESULTADO]]/Tabela1[[#This Row],[EBITDA ESTIMADO]] -> -0.085478023 | O16: =Tabela1[[#This Row],[FATURAMENTO]]-Tabela1[[#This Row],[CUSTO FIXO (SEM DEPREC.)]]-(Tabela1[[#This Row],[CUSTO VARIÁVEL]]*Tabela1[[#This Row],[HODÔMETRO]])+IF(COUNTIFS('ROTAS REALIZADAS'!A:A,Tabela1[[#This Row],[PLACA]],'ROTAS REALIZADAS'!A:A,"SANTOS/PAULINIA")>0,$AA$1*1233.33,0) -> -4566.9198 | P16: =IFERROR(Tabela1[[#This Row],[RESULTADO]]/Tabela1[[#This Row],[FATURAMENTO]],"-") -> -0.54771774 | Q16: =IFERROR(I16/H16,"-") -> 10.87998 | R16: =_xlfn.XLOOKUP(C16,'Telemetria Sighra'!F:F,'Telemetria Sighra'!S:S,0) -> 1.2623518 | S16: =_xlfn.XLOOKUP(Tabela1[[#This Row],[PLACA]],'Telemetria Sighra'!F:F,'Telemetria Sighra'!I:I,0) -> 607.2 | T16: =IFERROR((Tabela1[[#This Row],[LITROS CONSUMIDOS]]*$U$1)/Tabela1[[#This Row],[HODÔMETRO]],"-") -> 4.7538395
A17: VOLVO/FH 540 6X4T | B17: 2020 | C17: BDQ4E19 | D17: SANTOS X PAULINIA | E17: =IFERROR(_xlfn.XLOOKUP(Tabela1[[#This Row],[PLACA]],'Telemetria Sighra'!F:F,'Telemetria Sighra'!T:T),"NÃO EMBARCADO") -> ADRIANO DAGNON - 247 | F17: {=SUMPRODUCT((ISNUMBER(FIND(C17,Faturamento!$F$2:$F$1014)))*(Faturamento!$AA$2:$AA$1014))} -> 1076 | G17: =Tabela1[[#This Row],[HODÔMETRO]]-Tabela1[[#This Row],[KM CARREGADO]] -> 1945.86 | H17: =_xlfn.XLOOKUP(C17,'Telemetria Sighra'!F:F,'Telemetria Sighra'!R:R,0) -> 3021.86 | I17: =SUMIF(Faturamento!AC:AC,C17,Faturamento!T:T) -> 18675.3 | J17: {=SUMPRODUCT((ISNUMBER(FIND(C17,Faturamento!$F$2:$F$1014)))*(Faturamento!$R$2:$R$1014))} -> 105728 | K17: =$AH$2/30*$AA$1 -> 9479.7957 | L17: 4.4694 | M17: 39990 | N17: =Tabela1[[#This Row],[RESULTADO]]/Tabela1[[#This Row],[EBITDA ESTIMADO]] -> -0.10778687 | O17: =Tabela1[[#This Row],[FATURAMENTO]]-Tabela1[[#This Row],[CUSTO FIXO (SEM DEPREC.)]]-(Tabela1[[#This Row],[CUSTO VARIÁVEL]]*Tabela1[[#This Row],[HODÔMETRO]])+IF(COUNTIFS('ROTAS REALIZADAS'!A:A,Tabela1[[#This Row],[PLACA]],'ROTAS REALIZADAS'!A:A,"SANTOS/PAULINIA")>0,$AA$1*1233.33,0) -> -4310.3968 | P17: =IFERROR(Tabela1[[#This Row],[RESULTADO]]/Tabela1[[#This Row],[FATURAMENTO]],"-") -> -0.23080737 | Q17: =IFERROR(I17/H17,"-") -> 6.1800679 | R17: =_xlfn.XLOOKUP(C17,'Telemetria Sighra'!F:F,'Telemetria Sighra'!S:S,0) -> 1.578471 | S17: =_xlfn.XLOOKUP(Tabela1[[#This Row],[PLACA]],'Telemetria Sighra'!F:F,'Telemetria Sighra'!I:I,0) -> 1914.53 | T17: =IFERROR((Tabela1[[#This Row],[LITROS CONSUMIDOS]]*$U$1)/Tabela1[[#This Row],[HODÔMETRO]],"-") -> 3.8013608
A18: DAF/XF FTT 530 | B18: 2023 | C18: SEE0I16 | D18: ISOTANK | E18: =IFERROR(_xlfn.XLOOKUP(Tabela1[[#This Row],[PLACA]],'Telemetria Sighra'!F:F,'Telemetria Sighra'!T:T),"NÃO EMBARCADO") -> LEANDRO CESAR VIEIRA DE OLIVEIRA - 1 | F18: {=SUMPRODUCT((ISNUMBER(FIND(C18,Faturamento!$F$2:$F$1014)))*(Faturamento!$AA$2:$AA$1014))} -> 2055 | G18: =Tabela1[[#This Row],[HODÔMETRO]]-Tabela1[[#This Row],[KM CARREGADO]] -> 602.47 | H18: =_xlfn.XLOOKUP(C18,'Telemetria Sighra'!F:F,'Telemetria Sighra'!R:R,0) -> 2657.47 | I18: =SUMIF(Faturamento!AC:AC,C18,Faturamento!T:T) -> 17096.65 | J18: {=SUMPRODUCT((ISNUMBER(FIND(C18,Faturamento!$F$2:$F$1014)))*(Faturamento!$R$2:$R$1014))} -> 152090 | K18: =$AH$2/30*$AA$1 -> 9479.7957 | L18: 4.4694 | M18: 40000 | N18: =Tabela1[[#This Row],[RESULTADO]]/Tabela1[[#This Row],[EBITDA ESTIMADO]] -> -0.10651105 | O18: =Tabela1[[#This Row],[FATURAMENTO]]-Tabela1[[#This Row],[CUSTO FIXO (SEM DEPREC.)]]-(Tabela1[[#This Row],[CUSTO VARIÁVEL]]*Tabela1[[#This Row],[HODÔMETRO]])+IF(COUNTIFS('ROTAS REALIZADAS'!A:A,Tabela1[[#This Row],[PLACA]],'ROTAS REALIZADAS'!A:A,"SANTOS/PAULINIA")>0,$AA$1*1233.33,0) -> -4260.4421 | P18: =IFERROR(Tabela1[[#This Row],[RESULTADO]]/Tabela1[[#This Row],[FATURAMENTO]],"-") -> -0.24919748 | Q18: =IFERROR(I18/H18,"-") -> 6.433431 | R18: =_xlfn.XLOOKUP(C18,'Telemetria Sighra'!F:F,'Telemetria Sighra'!S:S,0) -> 1.9377415 | S18: =_xlfn.XLOOKUP(Tabela1[[#This Row],[PLACA]],'Telemetria Sighra'!F:F,'Telemetria Sighra'!I:I,0) -> 1371.54 | T18: =IFERROR((Tabela1[[#This Row],[LITROS CONSUMIDOS]]*$U$1)/Tabela1[[#This Row],[HODÔMETRO]],"-") -> 3.0966446
A19: DAF/XF FTT 530 | B19: 2021 | C19: RHG5D75 | D19: ISOTANK | E19: =IFERROR(_xlfn.XLOOKUP(Tabela1[[#This Row],[PLACA]],'Telemetria Sighra'!F:F,'Telemetria Sighra'!T:T),"NÃO EMBARCADO") -> VILSO DE OLIVEIRA COSTA - 78 | F19: {=SUMPRODUCT((ISNUMBER(FIND(C19,Faturamento!$F$2:$F$1014)))*(Faturamento!$AA$2:$AA$1014))} -> 1860 | G19: =Tabela1[[#This Row],[HODÔMETRO]]-Tabela1[[#This Row],[KM CARREGADO]] -> -793.74 | H19: =_xlfn.XLOOKUP(C19,'Telemetria Sighra'!F:F,'Telemetria Sighra'!R:R,0) -> 1066.26 | I19: =SUMIF(Faturamento!AC:AC,C19,Faturamento!T:T) -> 10600 | J19: {=SUMPRODUCT((ISNUMBER(FIND(C19,Faturamento!$F$2:$F$1014)))*(Faturamento!$R$2:$R$1014))} -> 107140 | K19: =$AH$2/30*$AA$1 -> 9479.7957 | L19: 4.4694 | M19: 40000 | N19: =Tabela1[[#This Row],[RESULTADO]]/Tabela1[[#This Row],[EBITDA ESTIMADO]] -> -0.091133454 | O19: =Tabela1[[#This Row],[FATURAMENTO]]-Tabela1[[#This Row],[CUSTO FIXO (SEM DEPREC.)]]-(Tabela1[[#This Row],[CUSTO VARIÁVEL]]*Tabela1[[#This Row],[HODÔMETRO]])+IF(COUNTIFS('ROTAS REALIZADAS'!A:A,Tabela1[[#This Row],[PLACA]],'ROTAS REALIZADAS'!A:A,"SANTOS/PAULINIA")>0,$AA$1*1233.33,0) -> -3645.3382 | P19: =IFERROR(Tabela1[[#This Row],[RESULTADO]]/Tabela1[[#This Row],[FATURAMENTO]],"-") -> -0.34389983 | Q19: =IFERROR(I19/H19,"-") -> 9.9412901 | R19: =_xlfn.XLOOKUP(C19,'Telemetria Sighra'!F:F,'Telemetria Sighra'!S:S,0) -> 2.0141832 | S19: =_xlfn.XLOOKUP(Tabela1[[#This Row],[PLACA]],'Telemetria Sighra'!F:F,'Telemetria Sighra'!I:I,0) -> 529.5 | T19: =IFERROR((Tabela1[[#This Row],[LITROS CONSUMIDOS]]*$U$1)/Tabela1[[#This Row],[HODÔMETRO]],"-") -> 2.9795735
... A24: DAF/XF FTT 530 | B24: 2021 | C24: BEZ9A98 | D24: ISOTANK | E24: =IFERROR(_xlfn.XLOOKUP(Tabela1[[#This Row],[PLACA]],'Telemetria Sighra'!F:F,'Telemetria Sighra'!T:T),"NÃO EMBARCADO") -> ISACC SANTOS GUEDES - 172 | F24: {=SUMPRODUCT((ISNUMBER(FIND(C24,Faturamento!$F$2:$F$1014)))*(Faturamento!$AA$2:$AA$1014))} -> 2055 | G24: =Tabela1[[#This Row],[HODÔMETRO]]-Tabela1[[#This Row],[KM CARREGADO]] -> 286.38 | H24: =_xlfn.XLOOKUP(C24,'Telemetria Sighra'!F:F,'Telemetria Sighra'!R:R,0) -> 2341.38 | I24: =SUMIF(Faturamento!AC:AC,C24,Faturamento!T:T) -> 17140.1 | J24: {=SUMPRODUCT((ISNUMBER(FIND(C24,Faturamento!$F$2:$F$1014)))*(Faturamento!$R$2:$R$1014))} -> 151820 | K24: =$AH$2/30*$AA$1 -> 9479.7957 | L24: 4.4694 | M24: 40000 | N24: =Tabela1[[#This Row],[RESULTADO]]/Tabela1[[#This Row],[EBITDA ESTIMADO]] -> -0.070106487 | O24: =Tabela1[[#This Row],[FATURAMENTO]]-Tabela1[[#This Row],[CUSTO FIXO (SEM DEPREC.)]]-(Tabela1[[#This Row],[CUSTO VARIÁVEL]]*Tabela1[[#This Row],[HODÔMETRO]])+IF(COUNTIFS('ROTAS REALIZADAS'!A:A,Tabela1[[#This Row],[PLACA]],'ROTAS REALIZADAS'!A:A,"SANTOS/PAULINIA")>0,$AA$1*1233.33,0) -> -2804.2595 | P24: =IFERROR(Tabela1[[#This Row],[RESULTADO]]/Tabela1[[#This Row],[FATURAMENTO]],"-") -> -0.16360812 | Q24: =IFERROR(I24/H24,"-") -> 7.3205118 | R24: =_xlfn.XLOOKUP(C24,'Telemetria Sighra'!F:F,'Telemetria Sighra'!S:S,0) -> 1.6041996 | S24: =_xlfn.XLOOKUP(Tabela1[[#This Row],[PLACA]],'Telemetria Sighra'!F:F,'Telemetria Sighra'!I:I,0) -> 1459.65 | T24: =IFERROR((Tabela1[[#This Row],[LITROS CONSUMIDOS]]*$U$1)/Tabela1[[#This Row],[HODÔMETRO]],"-") -> 3.7404864
A25: SCANIA/R 480 A6X4 | B25: 2017 | C25: BBM5I45 | D25: METANOL | E25: =IFERROR(_xlfn.XLOOKUP(Tabela1[[#This Row],[PLACA]],'Telemetria Sighra'!F:F,'Telemetria Sighra'!T:T),"NÃO EMBARCADO") -> VLADEMIR JORGE SANTOS - 208 | F25: {=SUMPRODUCT((ISNUMBER(FIND(C25,Faturamento!$F$2:$F$1014)))*(Faturamento!$AA$2:$AA$1014))} -> 1003 | G25: =Tabela1[[#This Row],[HODÔMETRO]]-Tabela1[[#This Row],[KM CARREGADO]] -> 1521.67 | H25: =_xlfn.XLOOKUP(C25,'Telemetria Sighra'!F:F,'Telemetria Sighra'!R:R,0) -> 2524.67 | I25: =SUMIF(Faturamento!AC:AC,C25,Faturamento!T:T) -> 14527.51 | J25: {=SUMPRODUCT((ISNUMBER(FIND(C25,Faturamento!$F$2:$F$1014)))*(Faturamento!$R$2:$R$1014))} -> 128653 | K25: =$AD$2/30*$AA$1 -> 7856.0195 | L25: 3.55 | M25: 47896 | N25: =Tabela1[[#This Row],[RESULTADO]]/Tabela1[[#This Row],[EBITDA ESTIMADO]] -> -0.047834642 | O25: =Tabela1[[#This Row],[FATURAMENTO]]-Tabela1[[#This Row],[CUSTO FIXO (SEM DEPREC.)]]-(Tabela1[[#This Row],[CUSTO VARIÁVEL]]*Tabela1[[#This Row],[HODÔMETRO]])+IF(COUNTIFS('ROTAS REALIZADAS'!A:A,Tabela1[[#This Row],[PLACA]],'ROTAS REALIZADAS'!A:A,"SANTOS/PAULINIA")>0,$AA$1*1233.33,0) -> -2291.088 | P25: =IFERROR(Tabela1[[#This Row],[RESULTADO]]/Tabela1[[#This Row],[FATURAMENTO]],"-") -> -0.15770686 | Q25: =IFERROR(I25/H25,"-") -> 5.7542213 | R25: =_xlfn.XLOOKUP(C25,'Telemetria Sighra'!F:F,'Telemetria Sighra'!S:S,0) -> 2.3209877 | S25: =_xlfn.XLOOKUP(Tabela1[[#This Row],[PLACA]],'Telemetria Sighra'!F:F,'Telemetria Sighra'!I:I,0) -> 1087.83 | T25: =IFERROR((Tabela1[[#This Row],[LITROS CONSUMIDOS]]*$U$1)/Tabela1[[#This Row],[HODÔMETRO]],"-") -> 2.5852805
A26: DAF/XF FTT 530 | B26: 2023 | C26: SEE2J87 | D26: SANTOS X PAULINIA | E26: =IFERROR(_xlfn.XLOOKUP(Tabela1[[#This Row],[PLACA]],'Telemetria Sighra'!F:F,'Telemetria Sighra'!T:T),"NÃO EMBARCADO") -> LUIZ CEZAR KELCZESKI - 50073 | F26: {=SUMPRODUCT((ISNUMBER(FIND(C26,Faturamento!$F$2:$F$1014)))*(Faturamento!$AA$2:$AA$1014))} -> 1212 | G26: =Tabela1[[#This Row],[HODÔMETRO]]-Tabela1[[#This Row],[KM CARREGADO]] -> 892.04 | H26: =_xlfn.XLOOKUP(C26,'Telemetria Sighra'!F:F,'Telemetria Sighra'!R:R,0) -> 2104.04 | I26: =SUMIF(Faturamento!AC:AC,C26,Faturamento!T:T) -> 17284.1 | J26: {=SUMPRODUCT((ISNUMBER(FIND(C26,Faturamento!$F$2:$F$1014)))*(Faturamento!$R$2:$R$1014))} -> 57345 | K26: =$AH$2/30*$AA$1 -> 9479.7957 | L26: 4.4694 | M26: 39990 | N26: =Tabela1[[#This Row],[RESULTADO]]/Tabela1[[#This Row],[EBITDA ESTIMADO]] -> -0.039997302 | O26: =Tabela1[[#This Row],[FATURAMENTO]]-Tabela1[[#This Row],[CUSTO FIXO (SEM DEPREC.)]]-(Tabela1[[#This Row],[CUSTO VARIÁVEL]]*Tabela1[[#This Row],[HODÔMETRO]])+IF(COUNTIFS('ROTAS REALIZADAS'!A:A,Tabela1[[#This Row],[PLACA]],'ROTAS REALIZADAS'!A:A,"SANTOS/PAULINIA")>0,$AA$1*1233.33,0) -> -1599.4921 | P26: =IFERROR(Tabela1[[#This Row],[RESULTADO]]/Tabela1[[#This Row],[FATURAMENTO]],"-") -> -0.092541243 | Q26: =IFERROR(I26/H26,"-") -> 8.2147203 | R26: =_xlfn.XLOOKUP(C26,'Telemetria Sighra'!F:F,'Telemetria Sighra'!S:S,0) -> 1.0146153 | S26: =_xlfn.XLOOKUP(Tabela1[[#This Row],[PLACA]],'Telemetria Sighra'!F:F,'Telemetria Sighra'!I:I,0) -> 2073.85 | T26: =IFERROR((Tabela1[[#This Row],[LITROS CONSUMIDOS]]*$U$1)/Tabela1[[#This Row],[HODÔMETRO]],"-") -> 5.9139085
A27: DAF/XF FTT 530 | B27: 2024 | C27: SEX2C75 | D27: SANTOS X PAULINIA | E27: =IFERROR(_xlfn.XLOOKUP(Tabela1[[#This Row],[PLACA]],'Telemetria Sighra'!F:F,'Telemetria Sighra'!T:T),"NÃO EMBARCADO") -> FRANCISCO JOSE ESTEVES - 162 | F27: {=SUMPRODUCT((ISNUMBER(FIND(C27,Faturamento!$F$2:$F$1014)))*(Faturamento!$AA$2:$AA$1014))} -> 1346 | G27: =Tabela1[[#This Row],[HODÔMETRO]]-Tabela1[[#This Row],[KM CARREGADO]] -> 1413.25 | H27: =_xlfn.XLOOKUP(C27,'Telemetria Sighra'!F:F,'Telemetria Sighra'!R:R,0) -> 2759.25 | I27: =SUMIF(Faturamento!AC:AC,C27,Faturamento!T:T) -> 20288.44 | J27: {=SUMPRODUCT((ISNUMBER(FIND(C27,Faturamento!$F$2:$F$1014)))*(Faturamento!$R$2:$R$1014))} -> 245307 | K27: =$AH$2/30*$AA$1 -> 9479.7957 | L27: 4.4694 | M27: 39990 | N27: =Tabela1[[#This Row],[RESULTADO]]/Tabela1[[#This Row],[EBITDA ESTIMADO]] -> -0.038098216 | O27: =Tabela1[[#This Row],[FATURAMENTO]]-Tabela1[[#This Row],[CUSTO FIXO (SEM DEPREC.)]]-(Tabela1[[#This Row],[CUSTO VARIÁVEL]]*Tabela1[[#This Row],[HODÔMETRO]])+IF(COUNTIFS('ROTAS REALIZADAS'!A:A,Tabela1[[#This Row],[PLACA]],'ROTAS REALIZADAS'!A:A,"SANTOS/PAULINIA")>0,$AA$1*1233.33,0) -> -1523.5477 | P27: =IFERROR(Tabela1[[#This Row],[RESULTADO]]/Tabela1[[#This Row],[FATURAMENTO]],"-") -> -0.075094373 | Q27: =IFERROR(I27/H27,"-") -> 7.3528821 | R27: =_xlfn.XLOOKUP(C27,'Telemetria Sighra'!F:F,'Telemetria Sighra'!S:S,0) -> 1.8247753 | S27: =_xlfn.XLOOKUP(Tabela1[[#This Row],[PLACA]],'Telemetria Sighra'!F:F,'Telemetria Sighra'!I:I,0) -> 1512.23 | T27: =IFERROR((Tabela1[[#This Row],[LITROS CONSUMIDOS]]*$U$1)/Tabela1[[#This Row],[HODÔMETRO]],"-") -> 3.2883501
A28: VOLVO/FH 540 6X4T | B28: 2020 | C28: BDQ4E18 | D28: SANTOS X PAULINIA | E28: =IFERROR(_xlfn.XLOOKUP(Tabela1[[#This Row],[PLACA]],'Telemetria Sighra'!F:F,'Telemetria Sighra'!T:T),"NÃO EMBARCADO") -> DANIEL EUFRAZIO - 245 | F28: {=SUMPRODUCT((ISNUMBER(FIND(C28,Faturamento!$F$2:$F$1014)))*(Faturamento!$AA$2:$AA$1014))} -> 1138 | G28: =Tabela1[[#This Row],[HODÔMETRO]]-Tabela1[[#This Row],[KM CARREGADO]] -> 533 | H28: =_xlfn.XLOOKUP(C28,'Telemetria Sighra'!F:F,'Telemetria Sighra'!R:R,0) -> 1671 | I28: =SUMIF(Faturamento!AC:AC,C28,Faturamento!T:T) -> 15955.98 | J28: {=SUMPRODUCT((ISNUMBER(FIND(C28,Faturamento!$F$2:$F$1014)))*(Faturamento!$R$2:$R$1014))} -> 117574 | K28: =$AH$2/30*$AA$1 -> 9479.7957 | L28: 4.4694 | M28: 39990 | N28: =Tabela1[[#This Row],[RESULTADO]]/Tabela1[[#This Row],[EBITDA ESTIMADO]] -> -0.024810781 | O28: =Tabela1[[#This Row],[FATURAMENTO]]-Tabela1[[#This Row],[CUSTO FIXO (SEM DEPREC.)]]-(Tabela1[[#This Row],[CUSTO VARIÁVEL]]*Tabela1[[#This Row],[HODÔMETRO]])+IF(COUNTIFS('ROTAS REALIZADAS'!A:A,Tabela1[[#This Row],[PLACA]],'ROTAS REALIZADAS'!A:A,"SANTOS/PAULINIA")>0,$AA$1*1233.33,0) -> -992.18312 | P28: =IFERROR(Tabela1[[#This Row],[RESULTADO]]/Tabela1[[#This Row],[FATURAMENTO]],"-") -> -0.062182525 | Q28: =IFERROR(I28/H28,"-") -> 9.5487612 | R28: =_xlfn.XLOOKUP(C28,'Telemetria Sighra'!F:F,'Telemetria Sighra'!S:S,0) -> 1.2932705 | S28: =_xlfn.XLOOKUP(Tabela1[[#This Row],[PLACA]],'Telemetria Sighra'!F:F,'Telemetria Sighra'!I:I,0) -> 1292.22 | T28: =IFERROR((Tabela1[[#This Row],[LITROS CONSUMIDOS]]*$U$1)/Tabela1[[#This Row],[HODÔMETRO]],"-") -> 4.6399282
A29: DAF/XF FTT 530 | B29: 2023 | C29: SEE0I13 | D29: Spot melhor tarifa | E29: =IFERROR(_xlfn.XLOOKUP(Tabela1[[#This Row],[PLACA]],'Telemetria Sighra'!F:F,'Telemetria Sighra'!T:T),"NÃO EMBARCADO") -> ALAOR BATISTA DE FREITAS - 193 | F29: {=SUMPRODUCT((ISNUMBER(FIND(C29,Faturamento!$F$2:$F$1014)))*(Faturamento!$AA$2:$AA$1014))} -> 1286 | G29: =Tabela1[[#This Row],[HODÔMETRO]]-Tabela1[[#This Row],[KM CARREGADO]] -> 1576.74 | H29: =_xlfn.XLOOKUP(C29,'Telemetria Sighra'!F:F,'Telemetria Sighra'!R:R,0) -> 2862.74 | I29: =SUMIF(Faturamento!AC:AC,C29,Faturamento!T:T) -> 21626.84 | J29: {=SUMPRODUCT((ISNUMBER(FIND(C29,Faturamento!$F$2:$F$1014)))*(Faturamento!$R$2:$R$1014))} -> 245397 | K29: =$AH$2/30*$AA$1 -> 9479.7957 | L29: 4.4694 | M29: 40000 | N29: =Tabela1[[#This Row],[RESULTADO]]/Tabela1[[#This Row],[EBITDA ESTIMADO]] -> -0.016192147 | O29: =Tabela1[[#This Row],[FATURAMENTO]]-Tabela1[[#This Row],[CUSTO FIXO (SEM DEPREC.)]]-(Tabela1[[#This Row],[CUSTO VARIÁVEL]]*Tabela1[[#This Row],[HODÔMETRO]])+IF(COUNTIFS('ROTAS REALIZADAS'!A:A,Tabela1[[#This Row],[PLACA]],'ROTAS REALIZADAS'!A:A,"SANTOS/PAULINIA")>0,$AA$1*1233.33,0) -> -647.68588 | P29: =IFERROR(Tabela1[[#This Row],[RESULTADO]]/Tabela1[[#This Row],[FATURAMENTO]],"-") -> -0.029948244 | Q29: =IFERROR(I29/H29,"-") -> 7.5545945 | R29: =_xlfn.XLOOKUP(C29,'Telemetria Sighra'!F:F,'Telemetria Sighra'!S:S,0) -> 1.2487201 | S29: =_xlfn.XLOOKUP(Tabela1[[#This Row],[PLACA]],'Telemetria Sighra'!F:F,'Telemetria Sighra'!I:I,0) -> 1511.78 | T29: =IFERROR((Tabela1[[#This Row],[LITROS CONSUMIDOS]]*$U$1)/Tabela1[[#This Row],[HODÔMETRO]],"-") -> 3.1685308
A30: DAF/XF FTT 530 | B30: 2023 | C30: SEE2J90 | D30: Spot melhor tarifa | E30: =IFERROR(_xlfn.XLOOKUP(Tabela1[[#This Row],[PLACA]],'Telemetria Sighra'!F:F,'Telemetria Sighra'!T:T),"NÃO EMBARCADO") -> ANDRIELIA APARECIDA GOMES - 238 | F30: {=SUMPRODUCT((ISNUMBER(FIND(C30,Faturamento!$F$2:$F$1014)))*(Faturamento!$AA$2:$AA$1014))} -> 1346 | G30: =Tabela1[[#This Row],[HODÔMETRO]]-Tabela1[[#This Row],[KM CARREGADO]] -> 1136.62 | H30: =_xlfn.XLOOKUP(C30,'Telemetria Sighra'!F:F,'Telemetria Sighra'!R:R,0) -> 2482.62 | I30: =SUMIF(Faturamento!AC:AC,C30,Faturamento!T:T) -> 20289.85 | J30: {=SUMPRODUCT((ISNUMBER(FIND(C30,Faturamento!$F$2:$F$1014)))*(Faturamento!$R$2:$R$1014))} -> 243351 | K30: =$AH$2/30*$AA$1 -> 9479.7957 | L30: 4.4694 | M30: 40000 | N30: =Tabela1[[#This Row],[RESULTADO]]/Tabela1[[#This Row],[EBITDA ESTIMADO]] -> -0.0071441888 | O30: =Tabela1[[#This Row],[FATURAMENTO]]-Tabela1[[#This Row],[CUSTO FIXO (SEM DEPREC.)]]-(Tabela1[[#This Row],[CUSTO VARIÁVEL]]*Tabela1[[#This Row],[HODÔMETRO]])+IF(COUNTIFS('ROTAS REALIZADAS'!A:A,Tabela1[[#This Row],[PLACA]],'ROTAS REALIZADAS'!A:A,"SANTOS/PAULINIA")>0,$AA$1*1233.33,0) -> -285.76755 | P30: =IFERROR(Tabela1[[#This Row],[RESULTADO]]/Tabela1[[#This Row],[FATURAMENTO]],"-") -> -0.014084261 | Q30: =IFERROR(I30/H30,"-") -> 8.172757 | R30: =_xlfn.XLOOKUP(C30,'Telemetria Sighra'!F:F,'Telemetria Sighra'!S:S,0) -> 1.7649405 | S30: =_xlfn.XLOOKUP(Tabela1[[#This Row],[PLACA]],'Telemetria Sighra'!F:F,'Telemetria Sighra'!I:I,0) -> 1406.75 | T30: =IFERROR((Tabela1[[#This Row],[LITROS CONSUMIDOS]]*$U$1)/Tabela1[[#This Row],[HODÔMETRO]],"-") -> 3.3998357
A31: DAF/XF FTT 530 | B31: 2021 | C31: RHH5D97 | D31: SANTOS X PAULINIA | E31: =IFERROR(_xlfn.XLOOKUP(Tabela1[[#This Row],[PLACA]],'Telemetria Sighra'!F:F,'Telemetria Sighra'!T:T),"NÃO EMBARCADO") -> MARIO SERGIO DOS SANTOS ANDREOLA - 50101 | F31: {=SUMPRODUCT((ISNUMBER(FIND(C31,Faturamento!$F$2:$F$1014)))*(Faturamento!$AA$2:$AA$1014))} -> 1034 | G31: =Tabela1[[#This Row],[HODÔMETRO]]-Tabela1[[#This Row],[KM CARREGADO]] -> 589.47 | H31: =_xlfn.XLOOKUP(C31,'Telemetria Sighra'!F:F,'Telemetria Sighra'!R:R,0) -> 1623.47 | I31: =SUMIF(Faturamento!AC:AC,C31,Faturamento!T:T) -> 17166.08 | J31: {=SUMPRODUCT((ISNUMBER(FIND(C31,Faturamento!$F$2:$F$1014)))*(Faturamento!$R$2:$R$1014))} -> 59598 | K31: =$AH$2/30*$AA$1 -> 9479.7957 | L31: 4.4694 | M31: 39990 | N31: =Tabela1[[#This Row],[RESULTADO]]/Tabela1[[#This Row],[EBITDA ESTIMADO]] -> 0.010761377 | O31: =Tabela1[[#This Row],[FATURAMENTO]]-Tabela1[[#This Row],[CUSTO FIXO (SEM DEPREC.)]]-(Tabela1[[#This Row],[CUSTO VARIÁVEL]]*Tabela1[[#This Row],[HODÔMETRO]])+IF(COUNTIFS('ROTAS REALIZADAS'!A:A,Tabela1[[#This Row],[PLACA]],'ROTAS REALIZADAS'!A:A,"SANTOS/PAULINIA")>0,$AA$1*1233.33,0) -> 430.34746 | P31: =IFERROR(Tabela1[[#This Row],[RESULTADO]]/Tabela1[[#This Row],[FATURAMENTO]],"-") -> 0.025069641 | Q31: =IFERROR(I31/H31,"-") -> 10.573697 | R31: =_xlfn.XLOOKUP(C31,'Telemetria Sighra'!F:F,'Telemetria Sighra'!S:S,0) -> 1.3322584 | S31: =_xlfn.XLOOKUP(Tabela1[[#This Row],[PLACA]],'Telemetria Sighra'!F:F,'Telemetria Sighra'!I:I,0) -> 1218.66 | T31: =IFERROR((Tabela1[[#This Row],[LITROS CONSUMIDOS]]*$U$1)/Tabela1[[#This Row],[HODÔMETRO]],"-") -> 4.5039083
A32: SCANIA/R 480 A6X4 | B32: 2016 | C32: BAX9A94 | D32: PGUA X LAPA | E32: =IFERROR(_xlfn.XLOOKUP(Tabela1[[#This Row],[PLACA]],'Telemetria Sighra'!F:F,'Telemetria Sighra'!T:T),"NÃO EMBARCADO") -> FRANCISCO ADEMIR MORO JUNIOR - 216 | F32: {=SUMPRODUCT((ISNUMBER(FIND(C32,Faturamento!$F$2:$F$1014)))*(Faturamento!$AA$2:$AA$1014))} -> 1346 | G32: =Tabela1[[#This Row],[HODÔMETRO]]-Tabela1[[#This Row],[KM CARREGADO]] -> 1326.63 | H32: =_xlfn.XLOOKUP(C32,'Telemetria Sighra'!F:F,'Telemetria Sighra'!R:R,0) -> 2672.63 | I32: =SUMIF(Faturamento!AC:AC,C32,Faturamento!T:T) -> 17938.65 | J32: {=SUMPRODUCT((ISNUMBER(FIND(C32,Faturamento!$F$2:$F$1014)))*(Faturamento!$R$2:$R$1014))} -> 189190 | K32: =$AD$2/30*$AA$1 -> 7856.0195 | L32: 3.55 | M32: 63000 | N32: =Tabela1[[#This Row],[RESULTADO]]/Tabela1[[#This Row],[EBITDA ESTIMADO]] -> 0.0094411742 | O32: =Tabela1[[#This Row],[FATURAMENTO]]-Tabela1[[#This Row],[CUSTO FIXO (SEM DEPREC.)]]-(Tabela1[[#This Row],[CUSTO VARIÁVEL]]*Tabela1[[#This Row],[HODÔMETRO]])+IF(COUNTIFS('ROTAS REALIZADAS'!A:A,Tabela1[[#This Row],[PLACA]],'ROTAS REALIZADAS'!A:A,"SANTOS/PAULINIA")>0,$AA$1*1233.33,0) -> 594.79397 | P32: =IFERROR(Tabela1[[#This Row],[RESULTADO]]/Tabela1[[#This Row],[FATURAMENTO]],"-") -> 0.03315712 | Q32: =IFERROR(I32/H32,"-") -> 6.7119841 | R32: =_xlfn.XLOOKUP(C32,'Telemetria Sighra'!F:F,'Telemetria Sighra'!S:S,0) -> 2.2072471 | S32: =_xlfn.XLOOKUP(Tabela1[[#This Row],[PLACA]],'Telemetria Sighra'!F:F,'Telemetria Sighra'!I:I,0) -> 1210.97 | T32: =IFERROR((Tabela1[[#This Row],[LITROS CONSUMIDOS]]*$U$1)/Tabela1[[#This Row],[HODÔMETRO]],"-") -> 2.718603
A33: VOLVO/FH 500 6X4T S BIO | B33: 2025 | C33: TAW8B84 | D33: VIBRA | E33: =IFERROR(_xlfn.XLOOKUP(Tabela1[[#This Row],[PLACA]],'Telemetria Sighra'!F:F,'Telemetria Sighra'!T:T),"NÃO EMBARCADO") -> EDENIR MALOSTI PEREIRA - 72 | F33: {=SUMPRODUCT((ISNUMBER(FIND(C33,Faturamento!$F$2:$F$1014)))*(Faturamento!$AA$2:$AA$1014))} -> 1506 | G33: =Tabela1[[#This Row],[HODÔMETRO]]-Tabela1[[#This Row],[KM CARREGADO]] -> 1777.4 | H33: =_xlfn.XLOOKUP(C33,'Telemetria Sighra'!F:F,'Telemetria Sighra'!R:R,0) -> 3283.4 | I33: =SUMIF(Faturamento!AC:AC,C33,Faturamento!T:T) -> 25037.32 | J33: {=SUMPRODUCT((ISNUMBER(FIND(C33,Faturamento!$F$2:$F$1014)))*(Faturamento!$R$2:$R$1014))} -> 234308 | K33: =$AH$2/30*$AA$1 -> 9479.7957 | L33: 4.4694 | M33: 69761 | N33: =Tabela1[[#This Row],[RESULTADO]]/Tabela1[[#This Row],[EBITDA ESTIMADO]] -> 0.012653149 | O33: =Tabela1[[#This Row],[FATURAMENTO]]-Tabela1[[#This Row],[CUSTO FIXO (SEM DEPREC.)]]-(Tabela1[[#This Row],[CUSTO VARIÁVEL]]*Tabela1[[#This Row],[HODÔMETRO]])+IF(COUNTIFS('ROTAS REALIZADAS'!A:A,Tabela1[[#This Row],[PLACA]],'ROTAS REALIZADAS'!A:A,"SANTOS/PAULINIA")>0,$AA$1*1233.33,0) -> 882.69632 | P33: =IFERROR(Tabela1[[#This Row],[RESULTADO]]/Tabela1[[#This Row],[FATURAMENTO]],"-") -> 0.035255224 | Q33: =IFERROR(I33/H33,"-") -> 7.6254249 | R33: =_xlfn.XLOOKUP(C33,'Telemetria Sighra'!F:F,'Telemetria Sighra'!S:S,0) -> 1.869535 | S33: =_xlfn.XLOOKUP(Tabela1[[#This Row],[PLACA]],'Telemetria Sighra'!F:F,'Telemetria Sighra'!I:I,0) -> 1756.41 | T33: =IFERROR((Tabela1[[#This Row],[LITROS CONSUMIDOS]]*$U$1)/Tabela1[[#This Row],[HODÔMETRO]],"-") -> 3.2096181
A34: VOLVO/FH 500 6X4T S BIO | B34: 2025 | C34: TAW8C01 | D34: VIBRA | E34: =IFERROR(_xlfn.XLOOKUP(Tabela1[[#This Row],[PLACA]],'Telemetria Sighra'!F:F,'Telemetria Sighra'!T:T),"NÃO EMBARCADO") -> ROBERTO RIVELINO CABRAL - 234 | F34: {=SUMPRODUCT((ISNUMBER(FIND(C34,Faturamento!$F$2:$F$1014)))*(Faturamento!$AA$2:$AA$1014))} -> 1346 | G34: =Tabela1[[#This Row],[HODÔMETRO]]-Tabela1[[#This Row],[KM CARREGADO]] -> 849.84 | H34: =_xlfn.XLOOKUP(C34,'Telemetria Sighra'!F:F,'Telemetria Sighra'!R:R,0) -> 2195.84 | I34: =SUMIF(Faturamento!AC:AC,C34,Faturamento!T:T) -> 20291.69 | J34: {=SUMPRODUCT((ISNUMBER(FIND(C34,Faturamento!$F$2:$F$1014)))*(Faturamento!$R$2:$R$1014))} -> 247351 | K34: =$AH$2/30*$AA$1 -> 9479.7957 | L34: 4.4694 | M34: 69761 | N34: =Tabela1[[#This Row],[RESULTADO]]/Tabela1[[#This Row],[EBITDA ESTIMADO]] -> 0.014303221 | O34: =Tabela1[[#This Row],[FATURAMENTO]]-Tabela1[[#This Row],[CUSTO FIXO (SEM DEPREC.)]]-(Tabela1[[#This Row],[CUSTO VARIÁVEL]]*Tabela1[[#This Row],[HODÔMETRO]])+IF(COUNTIFS('ROTAS REALIZADAS'!A:A,Tabela1[[#This Row],[PLACA]],'ROTAS REALIZADAS'!A:A,"SANTOS/PAULINIA")>0,$AA$1*1233.33,0) -> 997.80698 | P34: =IFERROR(Tabela1[[#This Row],[RESULTADO]]/Tabela1[[#This Row],[FATURAMENTO]],"-") -> 0.049173183 | Q34: =IFERROR(I34/H34,"-") -> 9.2409693 | R34: =_xlfn.XLOOKUP(C34,'Telemetria Sighra'!F:F,'Telemetria Sighra'!S:S,0) -> 1.8177898 | S34: =_xlfn.XLOOKUP(Tabela1[[#This Row],[PLACA]],'Telemetria Sighra'!F:F,'Telemetria Sighra'!I:I,0) -> 1208.11 | T34: =IFERROR((Tabela1[[#This Row],[LITROS CONSUMIDOS]]*$U$1)/Tabela1[[#This Row],[HODÔMETRO]],"-") -> 3.3010875
A35: VOLVO/FH 500 6X4T S BIO | B35: 2025 | C35: TAW2A65 | D35: VIBRA | E35: =IFERROR(_xlfn.XLOOKUP(Tabela1[[#This Row],[PLACA]],'Telemetria Sighra'!F:F,'Telemetria Sighra'!T:T),"NÃO EMBARCADO") -> JOSE ARIMATEIA DA SILVA - 63 | F35: {=SUMPRODUCT((ISNUMBER(FIND(C35,Faturamento!$F$2:$F$1014)))*(Faturamento!$AA$2:$AA$1014))} -> 856 | G35: =Tabela1[[#This Row],[HODÔMETRO]]-Tabela1[[#This Row],[KM CARREGADO]] -> 65.51 | H35: =_xlfn.XLOOKUP(C35,'Telemetria Sighra'!F:F,'Telemetria Sighra'!R:R,0) -> 921.51 | I35: =SUMIF(Faturamento!AC:AC,C35,Faturamento!T:T) -> 14702.75 | J35: {=SUMPRODUCT((ISNUMBER(FIND(C35,Faturamento!$F$2:$F$1014)))*(Faturamento!$R$2:$R$1014))} -> 116817 | K35: =$AH$2/30*$AA$1 -> 9479.7957 | L35: 4.4694 | M35: 69761 | N35: =Tabela1[[#This Row],[RESULTADO]]/Tabela1[[#This Row],[EBITDA ESTIMADO]] -> 0.015830586 | O35: =Tabela1[[#This Row],[FATURAMENTO]]-Tabela1[[#This Row],[CUSTO FIXO (SEM DEPREC.)]]-(Tabela1[[#This Row],[CUSTO VARIÁVEL]]*Tabela1[[#This Row],[HODÔMETRO]])+IF(COUNTIFS('ROTAS REALIZADAS'!A:A,Tabela1[[#This Row],[PLACA]],'ROTAS REALIZADAS'!A:A,"SANTOS/PAULINIA")>0,$AA$1*1233.33,0) -> 1104.3575 | P35: =IFERROR(Tabela1[[#This Row],[RESULTADO]]/Tabela1[[#This Row],[FATURAMENTO]],"-") -> 0.075112308 | Q35: =IFERROR(I35/H35,"-") -> 15.955063 | R35: =_xlfn.XLOOKUP(C35,'Telemetria Sighra'!F:F,'Telemetria Sighra'!S:S,0) -> 1.8194255 | S35: =_xlfn.XLOOKUP(Tabela1[[#This Row],[PLACA]],'Telemetria Sighra'!F:F,'Telemetria Sighra'!I:I,0) -> 506.55 | T35: =IFERROR((Tabela1[[#This Row],[LITROS CONSUMIDOS]]*$U$1)/Tabela1[[#This Row],[HODÔMETRO]],"-") -> 3.2981736
A36: DAF/XF FTT 530 | B36: 2023 | C36: SEE0I05 | D36: CAMERA | E36: =IFERROR(_xlfn.XLOOKUP(Tabela1[[#This Row],[PLACA]],'Telemetria Sighra'!F:F,'Telemetria Sighra'!T:T),"NÃO EMBARCADO") -> RODRIGO DOS SANTOS ALVES - 250 | F36: {=SUMPRODUCT((ISNUMBER(FIND(C36,Faturamento!$F$2:$F$1014)))*(Faturamento!$AA$2:$AA$1014))} -> 1071 | G36: =Tabela1[[#This Row],[HODÔMETRO]]-Tabela1[[#This Row],[KM CARREGADO]] -> 940.69 | H36: =_xlfn.XLOOKUP(C36,'Telemetria Sighra'!F:F,'Telemetria Sighra'!R:R,0) -> 2011.69 | I36: =SUMIF(Faturamento!AC:AC,C36,Faturamento!T:T) -> 19742.8 | J36: {=SUMPRODUCT((ISNUMBER(FIND(C36,Faturamento!$F$2:$F$1014)))*(Faturamento!$R$2:$R$1014))} -> 177211 | K36: =$AH$2/30*$AA$1 -> 9479.7957 | L36: 4.4694 | M36: 53428 | N36: =Tabela1[[#This Row],[RESULTADO]]/Tabela1[[#This Row],[EBITDA ESTIMADO]] -> 0.023806936 | O36: =Tabela1[[#This Row],[FATURAMENTO]]-Tabela1[[#This Row],[CUSTO FIXO (SEM DEPREC.)]]-(Tabela1[[#This Row],[CUSTO VARIÁVEL]]*Tabela1[[#This Row],[HODÔMETRO]])+IF(COUNTIFS('ROTAS REALIZADAS'!A:A,Tabela1[[#This Row],[PLACA]],'ROTAS REALIZADAS'!A:A,"SANTOS/PAULINIA")>0,$AA$1*1233.33,0) -> 1271.957 | P36: =IFERROR(Tabela1[[#This Row],[RESULTADO]]/Tabela1[[#This Row],[FATURAMENTO]],"-") -> 0.064426373 | Q36: =IFERROR(I36/H36,"-") -> 9.814037 | R36: =_xlfn.XLOOKUP(C36,'Telemetria Sighra'!F:F,'Telemetria Sighra'!S:S,0) -> 1.8929556 | S36: =_xlfn.XLOOKUP(Tabela1[[#This Row],[PLACA]],'Telemetria Sighra'!F:F,'Telemetria Sighra'!I:I,0) -> 1062.83 | T36: =IFERROR((Tabela1[[#This Row],[LITROS CONSUMIDOS]]*$U$1)/Tabela1[[#This Row],[HODÔMETRO]],"-") -> 3.1699616
A37: VOLVO/FH 500 6X4T S BIO | B37: 2025 | C37: TAW8C09 | D37: ARAUCARIA X CASCAVEL | E37: =IFERROR(_xlfn.XLOOKUP(Tabela1[[#This Row],[PLACA]],'Telemetria Sighra'!F:F,'Telemetria Sighra'!T:T),"NÃO EMBARCADO") -> CLAIR SONAI - 67 | F37: {=SUMPRODUCT((ISNUMBER(FIND(C37,Faturamento!$F$2:$F$1014)))*(Faturamento!$AA$2:$AA$1014))} -> 1286 | G37: =Tabela1[[#This Row],[HODÔMETRO]]-Tabela1[[#This Row],[KM CARREGADO]] -> 998.22 | H37: =_xlfn.XLOOKUP(C37,'Telemetria Sighra'!F:F,'Telemetria Sighra'!R:R,0) -> 2284.22 | I37: =SUMIF(Faturamento!AC:AC,C37,Faturamento!T:T) -> 22714.9 | J37: {=SUMPRODUCT((ISNUMBER(FIND(C37,Faturamento!$F$2:$F$1014)))*(Faturamento!$R$2:$R$1014))} -> 239819 | K37: =$AH$2/30*$AA$1 -> 9479.7957 | L37: 4.4694 | M37: 34268 | N37: =Tabela1[[#This Row],[RESULTADO]]/Tabela1[[#This Row],[EBITDA ESTIMADO]] -> 0.08830429 | O37: =Tabela1[[#This Row],[FATURAMENTO]]-Tabela1[[#This Row],[CUSTO FIXO (SEM DEPREC.)]]-(Tabela1[[#This Row],[CUSTO VARIÁVEL]]*Tabela1[[#This Row],[HODÔMETRO]])+IF(COUNTIFS('ROTAS REALIZADAS'!A:A,Tabela1[[#This Row],[PLACA]],'ROTAS REALIZADAS'!A:A,"SANTOS/PAULINIA")>0,$AA$1*1233.33,0) -> 3026.0114 | P37: =IFERROR(Tabela1[[#This Row],[RESULTADO]]/Tabela1[[#This Row],[FATURAMENTO]],"-") -> 0.13321703 | Q37: =IFERROR(I37/H37,"-") -> 9.9442698 | R37: =_xlfn.XLOOKUP(C37,'Telemetria Sighra'!F:F,'Telemetria Sighra'!S:S,0) -> 1.85428 | S37: =_xlfn.XLOOKUP(Tabela1[[#This Row],[PLACA]],'Telemetria Sighra'!F:F,'Telemetria Sighra'!I:I,0) -> 1232.02 | T37: =IFERROR((Tabela1[[#This Row],[LITROS CONSUMIDOS]]*$U$1)/Tabela1[[#This Row],[HODÔMETRO]],"-") -> 3.2361681
A38: DAF/XF FTT 530 | B38: 2021 | C38: RHH5C92 | D38: SANTOS X PAULINIA | E38: =IFERROR(_xlfn.XLOOKUP(Tabela1[[#This Row],[PLACA]],'Telemetria Sighra'!F:F,'Telemetria Sighra'!T:T),"NÃO EMBARCADO") -> CLAUDEMIR SOARES - 252 | F38: {=SUMPRODUCT((ISNUMBER(FIND(C38,Faturamento!$F$2:$F$1014)))*(Faturamento!$AA$2:$AA$1014))} -> 1727 | G38: =Tabela1[[#This Row],[HODÔMETRO]]-Tabela1[[#This Row],[KM CARREGADO]] -> 554.52 | H38: =_xlfn.XLOOKUP(C38,'Telemetria Sighra'!F:F,'Telemetria Sighra'!R:R,0) -> 2281.52 | I38: =SUMIF(Faturamento!AC:AC,C38,Faturamento!T:T) -> 23075.99 | J38: {=SUMPRODUCT((ISNUMBER(FIND(C38,Faturamento!$F$2:$F$1014)))*(Faturamento!$R$2:$R$1014))} -> 117433 | K38: =$AH$2/30*$AA$1 -> 9479.7957 | L38: 4.4694 | M38: 39990 | N38: =Tabela1[[#This Row],[RESULTADO]]/Tabela1[[#This Row],[EBITDA ESTIMADO]] -> 0.08500047 | O38: =Tabela1[[#This Row],[FATURAMENTO]]-Tabela1[[#This Row],[CUSTO FIXO (SEM DEPREC.)]]-(Tabela1[[#This Row],[CUSTO VARIÁVEL]]*Tabela1[[#This Row],[HODÔMETRO]])+IF(COUNTIFS('ROTAS REALIZADAS'!A:A,Tabela1[[#This Row],[PLACA]],'ROTAS REALIZADAS'!A:A,"SANTOS/PAULINIA")>0,$AA$1*1233.33,0) -> 3399.1688 | P38: =IFERROR(Tabela1[[#This Row],[RESULTADO]]/Tabela1[[#This Row],[FATURAMENTO]],"-") -> 0.14730327 | Q38: =IFERROR(I38/H38,"-") -> 10.114305 | R38: =_xlfn.XLOOKUP(C38,'Telemetria Sighra'!F:F,'Telemetria Sighra'!S:S,0) -> 1.5780198 | S38: =_xlfn.XLOOKUP(Tabela1[[#This Row],[PLACA]],'Telemetria Sighra'!F:F,'Telemetria Sighra'!I:I,0) -> 1445.85 | T38: =IFERROR((Tabela1[[#This Row],[LITROS CONSUMIDOS]]*$U$1)/Tabela1[[#This Row],[HODÔMETRO]],"-") -> 3.8023335
A39: SCANIA/R 480 A6X4 | B39: 2017 | C39: BBM8G62 | D39: METANOL | E39: =IFERROR(_xlfn.XLOOKUP(Tabela1[[#This Row],[PLACA]],'Telemetria Sighra'!F:F,'Telemetria Sighra'!T:T),"NÃO EMBARCADO") -> LUIZ GERVASIO STROPARO - 10759 | F39: {=SUMPRODUCT((ISNUMBER(FIND(C39,Faturamento!$F$2:$F$1014)))*(Faturamento!$AA$2:$AA$1014))} -> 660 | G39: =Tabela1[[#This Row],[HODÔMETRO]]-Tabela1[[#This Row],[KM CARREGADO]] -> 537.52 | H39: =_xlfn.XLOOKUP(C39,'Telemetria Sighra'!F:F,'Telemetria Sighra'!R:R,0) -> 1197.52 | I39: =SUMIF(Faturamento!AC:AC,C39,Faturamento!T:T) -> 17105.81 | J39: {=SUMPRODUCT((ISNUMBER(FIND(C39,Faturamento!$F$2:$F$1014)))*(Faturamento!$R$2:$R$1014))} -> 112240 | K39: =$AD$2/30*$AA$1 -> 7856.0195 | L39: 3.55 | M39: 47896 | N39: =Tabela1[[#This Row],[RESULTADO]]/Tabela1[[#This Row],[EBITDA ESTIMADO]] -> 0.10436351 | O39: =Tabela1[[#This Row],[FATURAMENTO]]-Tabela1[[#This Row],[CUSTO FIXO (SEM DEPREC.)]]-(Tabela1[[#This Row],[CUSTO VARIÁVEL]]*Tabela1[[#This Row],[HODÔMETRO]])+IF(COUNTIFS('ROTAS REALIZADAS'!A:A,Tabela1[[#This Row],[PLACA]],'ROTAS REALIZADAS'!A:A,"SANTOS/PAULINIA")>0,$AA$1*1233.33,0) -> 4998.5945 | P39: =IFERROR(Tabela1[[#This Row],[RESULTADO]]/Tabela1[[#This Row],[FATURAMENTO]],"-") -> 0.29221618 | Q39: =IFERROR(I39/H39,"-") -> 14.284363 | R39: =_xlfn.XLOOKUP(C39,'Telemetria Sighra'!F:F,'Telemetria Sighra'!S:S,0) -> 1.55823 | S39: =_xlfn.XLOOKUP(Tabela1[[#This Row],[PLACA]],'Telemetria Sighra'!F:F,'Telemetria Sighra'!I:I,0) -> 768.59 | T39: =IFERROR((Tabela1[[#This Row],[LITROS CONSUMIDOS]]*$U$1)/Tabela1[[#This Row],[HODÔMETRO]],"-") -> 3.8509085
A40: SCANIA/R 480 A6X4 | B40: 2017 | C40: BBL9D24 | D40: METANOL | E40: =IFERROR(_xlfn.XLOOKUP(Tabela1[[#This Row],[PLACA]],'Telemetria Sighra'!F:F,'Telemetria Sighra'!T:T),"NÃO EMBARCADO") -> ANTONIO MARCOS GONCALVES - 90 | F40: {=SUMPRODUCT((ISNUMBER(FIND(C40,Faturamento!$F$2:$F$1014)))*(Faturamento!$AA$2:$AA$1014))} -> 1412 | G40: =Tabela1[[#This Row],[HODÔMETRO]]-Tabela1[[#This Row],[KM CARREGADO]] -> 871.68 | H40: =_xlfn.XLOOKUP(C40,'Telemetria Sighra'!F:F,'Telemetria Sighra'!R:R,0) -> 2283.68 | I40: =SUMIF(Faturamento!AC:AC,C40,Faturamento!T:T) -> 20994.5 | J40: {=SUMPRODUCT((ISNUMBER(FIND(C40,Faturamento!$F$2:$F$1014)))*(Faturamento!$R$2:$R$1014))} -> 165378 | K40: =$AD$2/30*$AA$1 -> 7856.0195 | L40: 3.55 | M40: 47896 | N40: =Tabela1[[#This Row],[RESULTADO]]/Tabela1[[#This Row],[EBITDA ESTIMADO]] -> 0.10504878 | O40: =Tabela1[[#This Row],[FATURAMENTO]]-Tabela1[[#This Row],[CUSTO FIXO (SEM DEPREC.)]]-(Tabela1[[#This Row],[CUSTO VARIÁVEL]]*Tabela1[[#This Row],[HODÔMETRO]])+IF(COUNTIFS('ROTAS REALIZADAS'!A:A,Tabela1[[#This Row],[PLACA]],'ROTAS REALIZADAS'!A:A,"SANTOS/PAULINIA")>0,$AA$1*1233.33,0) -> 5031.4165 | P40: =IFERROR(Tabela1[[#This Row],[RESULTADO]]/Tabela1[[#This Row],[FATURAMENTO]],"-") -> 0.23965403 | Q40: =IFERROR(I40/H40,"-") -> 9.1932758 | R40: =_xlfn.XLOOKUP(C40,'Telemetria Sighra'!F:F,'Telemetria Sighra'!S:S,0) -> 2.0101474 | S40: =_xlfn.XLOOKUP(Tabela1[[#This Row],[PLACA]],'Telemetria Sighra'!F:F,'Telemetria Sighra'!I:I,0) -> 1136.25 | T40: =IFERROR((Tabela1[[#This Row],[LITROS CONSUMIDOS]]*$U$1)/Tabela1[[#This Row],[HODÔMETRO]],"-") -> 2.9853132
A41: DAF/XF FTT 530 | B41: 2021 | C41: RHH5C95 | D41: SANTOS X PAULINIA | E41: =IFERROR(_xlfn.XLOOKUP(Tabela1[[#This Row],[PLACA]],'Telemetria Sighra'!F:F,'Telemetria Sighra'!T:T),"NÃO EMBARCADO") -> REINALDO FERNEDA - 249 | F41: {=SUMPRODUCT((ISNUMBER(FIND(C41,Faturamento!$F$2:$F$1014)))*(Faturamento!$AA$2:$AA$1014))} -> 1443 | G41: =Tabela1[[#This Row],[HODÔMETRO]]-Tabela1[[#This Row],[KM CARREGADO]] -> 1286.03 | H41: =_xlfn.XLOOKUP(C41,'Telemetria Sighra'!F:F,'Telemetria Sighra'!R:R,0) -> 2729.03 | I41: =SUMIF(Faturamento!AC:AC,C41,Faturamento!T:T) -> 28435.69 | J41: {=SUMPRODUCT((ISNUMBER(FIND(C41,Faturamento!$F$2:$F$1014)))*(Faturamento!$R$2:$R$1014))} -> 117175 | K41: =$AH$2/30*$AA$1 -> 9479.7957 | L41: 4.4694 | M41: 39990 | N41: =Tabela1[[#This Row],[RESULTADO]]/Tabela1[[#This Row],[EBITDA ESTIMADO]] -> 0.16901144 | O41: =Tabela1[[#This Row],[FATURAMENTO]]-Tabela1[[#This Row],[CUSTO FIXO (SEM DEPREC.)]]-(Tabela1[[#This Row],[CUSTO VARIÁVEL]]*Tabela1[[#This Row],[HODÔMETRO]])+IF(COUNTIFS('ROTAS REALIZADAS'!A:A,Tabela1[[#This Row],[PLACA]],'ROTAS REALIZADAS'!A:A,"SANTOS/PAULINIA")>0,$AA$1*1233.33,0) -> 6758.7676 | P41: =IFERROR(Tabela1[[#This Row],[RESULTADO]]/Tabela1[[#This Row],[FATURAMENTO]],"-") -> 0.23768608 | Q41: =IFERROR(I41/H41,"-") -> 10.419706 | R41: =_xlfn.XLOOKUP(C41,'Telemetria Sighra'!F:F,'Telemetria Sighra'!S:S,0) -> 1.6615204 | S41: =_xlfn.XLOOKUP(Tabela1[[#This Row],[PLACA]],'Telemetria Sighra'!F:F,'Telemetria Sighra'!I:I,0) -> 1642.61 | T41: =IFERROR((Tabela1[[#This Row],[LITROS CONSUMIDOS]]*$U$1)/Tabela1[[#This Row],[HODÔMETRO]],"-") -> 3.611415
A42: VOLVO/FH 540 6X4T | B42: 2020 | C42: BDQ4E53 | D42: ARAUCARIA X CASCAVEL | E42: =IFERROR(_xlfn.XLOOKUP(Tabela1[[#This Row],[PLACA]],'Telemetria Sighra'!F:F,'Telemetria Sighra'!T:T),"NÃO EMBARCADO") -> JOAO GABRIEL DA CRUZ - 10724 | F42: {=SUMPRODUCT((ISNUMBER(FIND(C42,Faturamento!$F$2:$F$1014)))*(Faturamento!$AA$2:$AA$1014))} -> 1583 | G42: =Tabela1[[#This Row],[HODÔMETRO]]-Tabela1[[#This Row],[KM CARREGADO]] -> 300.7 | H42: =_xlfn.XLOOKUP(C42,'Telemetria Sighra'!F:F,'Telemetria Sighra'!R:R,0) -> 1883.7 | I42: =SUMIF(Faturamento!AC:AC,C42,Faturamento!T:T) -> 25279.56 | J42: {=SUMPRODUCT((ISNUMBER(FIND(C42,Faturamento!$F$2:$F$1014)))*(Faturamento!$R$2:$R$1014))} -> 104635 | K42: =$AH$2/30*$AA$1 -> 9479.7957 | L42: 4.4694 | M42: 34268 | N42: =Tabela1[[#This Row],[RESULTADO]]/Tabela1[[#This Row],[EBITDA ESTIMADO]] -> 0.21538332 | O42: =Tabela1[[#This Row],[FATURAMENTO]]-Tabela1[[#This Row],[CUSTO FIXO (SEM DEPREC.)]]-(Tabela1[[#This Row],[CUSTO VARIÁVEL]]*Tabela1[[#This Row],[HODÔMETRO]])+IF(COUNTIFS('ROTAS REALIZADAS'!A:A,Tabela1[[#This Row],[PLACA]],'ROTAS REALIZADAS'!A:A,"SANTOS/PAULINIA")>0,$AA$1*1233.33,0) -> 7380.7555 | P42: =IFERROR(Tabela1[[#This Row],[RESULTADO]]/Tabela1[[#This Row],[FATURAMENTO]],"-") -> 0.29196535 | Q42: =IFERROR(I42/H42,"-") -> 13.420162 | R42: =_xlfn.XLOOKUP(C42,'Telemetria Sighra'!F:F,'Telemetria Sighra'!S:S,0) -> 1.3760546 | S42: =_xlfn.XLOOKUP(Tabela1[[#This Row],[PLACA]],'Telemetria Sighra'!F:F,'Telemetria Sighra'!I:I,0) -> 1369.03 | T42: =IFERROR((Tabela1[[#This Row],[LITROS CONSUMIDOS]]*$U$1)/Tabela1[[#This Row],[HODÔMETRO]],"-") -> 4.3606625
A43: VOLVO/FH 540 6X4T | B43: 2020 | C43: BDQ4E32 | D43: ARAUCARIA X CASCAVEL | E43: =IFERROR(_xlfn.XLOOKUP(Tabela1[[#This Row],[PLACA]],'Telemetria Sighra'!F:F,'Telemetria Sighra'!T:T),"NÃO EMBARCADO") -> OSVALDIR RIBEIRO PINTO - 52 | F43: {=SUMPRODUCT((ISNUMBER(FIND(C43,Faturamento!$F$2:$F$1014)))*(Faturamento!$AA$2:$AA$1014))} -> 1809 | G43: =Tabela1[[#This Row],[HODÔMETRO]]-Tabela1[[#This Row],[KM CARREGADO]] -> 1605.22 | H43: =_xlfn.XLOOKUP(C43,'Telemetria Sighra'!F:F,'Telemetria Sighra'!R:R,0) -> 3414.22 | I43: =SUMIF(Faturamento!AC:AC,C43,Faturamento!T:T) -> 32148.2 | J43: {=SUMPRODUCT((ISNUMBER(FIND(C43,Faturamento!$F$2:$F$1014)))*(Faturamento!$R$2:$R$1014))} -> 165961 | K43: =$AH$2/30*$AA$1 -> 9479.7957 | L43: 4.4694 | M43: 34268 | N43: =Tabela1[[#This Row],[RESULTADO]]/Tabela1[[#This Row],[EBITDA ESTIMADO]] -> 0.21620431 | O43: =Tabela1[[#This Row],[FATURAMENTO]]-Tabela1[[#This Row],[CUSTO FIXO (SEM DEPREC.)]]-(Tabela1[[#This Row],[CUSTO VARIÁVEL]]*Tabela1[[#This Row],[HODÔMETRO]])+IF(COUNTIFS('ROTAS REALIZADAS'!A:A,Tabela1[[#This Row],[PLACA]],'ROTAS REALIZADAS'!A:A,"SANTOS/PAULINIA")>0,$AA$1*1233.33,0) -> 7408.8894 | P43: =IFERROR(Tabela1[[#This Row],[RESULTADO]]/Tabela1[[#This Row],[FATURAMENTO]],"-") -> 0.23046047 | Q43: =IFERROR(I43/H43,"-") -> 9.415972 | R43: =_xlfn.XLOOKUP(C43,'Telemetria Sighra'!F:F,'Telemetria Sighra'!S:S,0) -> 1.4617729 | S43: =_xlfn.XLOOKUP(Tabela1[[#This Row],[PLACA]],'Telemetria Sighra'!F:F,'Telemetria Sighra'!I:I,0) -> 2335.91 | T43: =IFERROR((Tabela1[[#This Row],[LITROS CONSUMIDOS]]*$U$1)/Tabela1[[#This Row],[HODÔMETRO]],"-") -> 4.1050255
A44: VOLVO/FH 500 6X4T S BIO | B44: 2025 | C44: TAW8B80 | D44: VIBRA | E44: =IFERROR(_xlfn.XLOOKUP(Tabela1[[#This Row],[PLACA]],'Telemetria Sighra'!F:F,'Telemetria Sighra'!T:T),"NÃO EMBARCADO") -> LAURO LORETO TEIXEIRA - 111 | F44: {=SUMPRODUCT((ISNUMBER(FIND(C44,Faturamento!$F$2:$F$1014)))*(Faturamento!$AA$2:$AA$1014))} -> 1590 | G44: =Tabela1[[#This Row],[HODÔMETRO]]-Tabela1[[#This Row],[KM CARREGADO]] -> 1556.36 | H44: =_xlfn.XLOOKUP(C44,'Telemetria Sighra'!F:F,'Telemetria Sighra'!R:R,0) -> 3146.36 | I44: =SUMIF(Faturamento!AC:AC,C44,Faturamento!T:T) -> 31729.81 | J44: {=SUMPRODUCT((ISNUMBER(FIND(C44,Faturamento!$F$2:$F$1014)))*(Faturamento!$R$2:$R$1014))} -> 166014 | K44: =$AH$2/30*$AA$1 -> 9479.7957 | L44: 4.4694 | M44: 69761 | N44: =Tabela1[[#This Row],[RESULTADO]]/Tabela1[[#This Row],[EBITDA ESTIMADO]] -> 0.11736748 | O44: =Tabela1[[#This Row],[FATURAMENTO]]-Tabela1[[#This Row],[CUSTO FIXO (SEM DEPREC.)]]-(Tabela1[[#This Row],[CUSTO VARIÁVEL]]*Tabela1[[#This Row],[HODÔMETRO]])+IF(COUNTIFS('ROTAS REALIZADAS'!A:A,Tabela1[[#This Row],[PLACA]],'ROTAS REALIZADAS'!A:A,"SANTOS/PAULINIA")>0,$AA$1*1233.33,0) -> 8187.6729 | P44: =IFERROR(Tabela1[[#This Row],[RESULTADO]]/Tabela1[[#This Row],[FATURAMENTO]],"-") -> 0.25804355 | Q44: =IFERROR(I44/H44,"-") -> 10.084609 | R44: =_xlfn.XLOOKUP(C44,'Telemetria Sighra'!F:F,'Telemetria Sighra'!S:S,0) -> 1.6155947 | S44: =_xlfn.XLOOKUP(Tabela1[[#This Row],[PLACA]],'Telemetria Sighra'!F:F,'Telemetria Sighra'!I:I,0) -> 1947.71 | T44: =IFERROR((Tabela1[[#This Row],[LITROS CONSUMIDOS]]*$U$1)/Tabela1[[#This Row],[HODÔMETRO]],"-") -> 3.7142158
A45: DAF/XF FTT 530 | B45: 2023 | C45: SED7D20 | D45: SANTOS X PAULINIA | E45: =IFERROR(_xlfn.XLOOKUP(Tabela1[[#This Row],[PLACA]],'Telemetria Sighra'!F:F,'Telemetria Sighra'!T:T),"NÃO EMBARCADO") -> VALDEREZ MAINARDES - 229 | F45: {=SUMPRODUCT((ISNUMBER(FIND(C45,Faturamento!$F$2:$F$1014)))*(Faturamento!$AA$2:$AA$1014))} -> 1644 | G45: =Tabela1[[#This Row],[HODÔMETRO]]-Tabela1[[#This Row],[KM CARREGADO]] -> 1481.28 | H45: =_xlfn.XLOOKUP(C45,'Telemetria Sighra'!F:F,'Telemetria Sighra'!R:R,0) -> 3125.28 | I45: =SUMIF(Faturamento!AC:AC,C45,Faturamento!T:T) -> 31742.36 | J45: {=SUMPRODUCT((ISNUMBER(FIND(C45,Faturamento!$F$2:$F$1014)))*(Faturamento!$R$2:$R$1014))} -> 238766 | K45: =$AH$2/30*$AA$1 -> 9479.7957 | L45: 4.4694 | M45: 39990 | N45: =Tabela1[[#This Row],[RESULTADO]]/Tabela1[[#This Row],[EBITDA ESTIMADO]] -> 0.2074128 | O45: =Tabela1[[#This Row],[FATURAMENTO]]-Tabela1[[#This Row],[CUSTO FIXO (SEM DEPREC.)]]-(Tabela1[[#This Row],[CUSTO VARIÁVEL]]*Tabela1[[#This Row],[HODÔMETRO]])+IF(COUNTIFS('ROTAS REALIZADAS'!A:A,Tabela1[[#This Row],[PLACA]],'ROTAS REALIZADAS'!A:A,"SANTOS/PAULINIA")>0,$AA$1*1233.33,0) -> 8294.4378 | P45: =IFERROR(Tabela1[[#This Row],[RESULTADO]]/Tabela1[[#This Row],[FATURAMENTO]],"-") -> 0.26130501 | Q45: =IFERROR(I45/H45,"-") -> 10.156645 | R45: =_xlfn.XLOOKUP(C45,'Telemetria Sighra'!F:F,'Telemetria Sighra'!S:S,0) -> 1.9767324 | S45: =_xlfn.XLOOKUP(Tabela1[[#This Row],[PLACA]],'Telemetria Sighra'!F:F,'Telemetria Sighra'!I:I,0) -> 1581.17 | T45: =IFERROR((Tabela1[[#This Row],[LITROS CONSUMIDOS]]*$U$1)/Tabela1[[#This Row],[HODÔMETRO]],"-") -> 3.0355744
A46: SCANIA/R 480 A6X4 | B46: 2017 | C46: BBM5I48 | D46: PGUA X LAPA | E46: =IFERROR(_xlfn.XLOOKUP(Tabela1[[#This Row],[PLACA]],'Telemetria Sighra'!F:F,'Telemetria Sighra'!T:T),"NÃO EMBARCADO") -> FERNANDO JOSE CARVALHO - 10762 | F46: {=SUMPRODUCT((ISNUMBER(FIND(C46,Faturamento!$F$2:$F$1014)))*(Faturamento!$AA$2:$AA$1014))} -> 918 | G46: =Tabela1[[#This Row],[HODÔMETRO]]-Tabela1[[#This Row],[KM CARREGADO]] -> 1092.29 | H46: =_xlfn.XLOOKUP(C46,'Telemetria Sighra'!F:F,'Telemetria Sighra'!R:R,0) -> 2010.29 | I46: =SUMIF(Faturamento!AC:AC,C46,Faturamento!T:T) -> 23624.8 | J46: {=SUMPRODUCT((ISNUMBER(FIND(C46,Faturamento!$F$2:$F$1014)))*(Faturamento!$R$2:$R$1014))} -> 230037 | K46: =$AD$2/30*$AA$1 -> 7856.0195 | L46: 3.55 | M46: 36051 | N46: =Tabela1[[#This Row],[RESULTADO]]/Tabela1[[#This Row],[EBITDA ESTIMADO]] -> 0.23944553 | O46: =Tabela1[[#This Row],[FATURAMENTO]]-Tabela1[[#This Row],[CUSTO FIXO (SEM DEPREC.)]]-(Tabela1[[#This Row],[CUSTO VARIÁVEL]]*Tabela1[[#This Row],[HODÔMETRO]])+IF(COUNTIFS('ROTAS REALIZADAS'!A:A,Tabela1[[#This Row],[PLACA]],'ROTAS REALIZADAS'!A:A,"SANTOS/PAULINIA")>0,$AA$1*1233.33,0) -> 8632.251 | P46: =IFERROR(Tabela1[[#This Row],[RESULTADO]]/Tabela1[[#This Row],[FATURAMENTO]],"-") -> 0.36538938 | Q46: =IFERROR(I46/H46,"-") -> 11.751936 | R46: =_xlfn.XLOOKUP(C46,'Telemetria Sighra'!F:F,'Telemetria Sighra'!S:S,0) -> 1.7028135 | S46: =_xlfn.XLOOKUP(Tabela1[[#This Row],[PLACA]],'Telemetria Sighra'!F:F,'Telemetria Sighra'!I:I,0) -> 1180.74 | T46: =IFERROR((Tabela1[[#This Row],[LITROS CONSUMIDOS]]*$U$1)/Tabela1[[#This Row],[HODÔMETRO]],"-") -> 3.5240886
A47: VOLVO/FH 540 6X4T | B47: 2020 | C47: BDQ4E39 | D47: ARAUCARIA X CASCAVEL | E47: =IFERROR(_xlfn.XLOOKUP(Tabela1[[#This Row],[PLACA]],'Telemetria Sighra'!F:F,'Telemetria Sighra'!T:T),"NÃO EMBARCADO") -> WERNER DUCK - 47 | F47: {=SUMPRODUCT((ISNUMBER(FIND(C47,Faturamento!$F$2:$F$1014)))*(Faturamento!$AA$2:$AA$1014))} -> 1027 | G47: =Tabela1[[#This Row],[HODÔMETRO]]-Tabela1[[#This Row],[KM CARREGADO]] -> 918.52 | H47: =_xlfn.XLOOKUP(C47,'Telemetria Sighra'!F:F,'Telemetria Sighra'!R:R,0) -> 1945.52 | I47: =SUMIF(Faturamento!AC:AC,C47,Faturamento!T:T) -> 26974.51 | J47: {=SUMPRODUCT((ISNUMBER(FIND(C47,Faturamento!$F$2:$F$1014)))*(Faturamento!$R$2:$R$1014))} -> 346629 | K47: =$AH$2/30*$AA$1 -> 9479.7957 | L47: 4.4694 | M47: 34268 | N47: =Tabela1[[#This Row],[RESULTADO]]/Tabela1[[#This Row],[EBITDA ESTIMADO]] -> 0.25678205 | O47: =Tabela1[[#This Row],[FATURAMENTO]]-Tabela1[[#This Row],[CUSTO FIXO (SEM DEPREC.)]]-(Tabela1[[#This Row],[CUSTO VARIÁVEL]]*Tabela1[[#This Row],[HODÔMETRO]])+IF(COUNTIFS('ROTAS REALIZADAS'!A:A,Tabela1[[#This Row],[PLACA]],'ROTAS REALIZADAS'!A:A,"SANTOS/PAULINIA")>0,$AA$1*1233.33,0) -> 8799.4072 | P47: =IFERROR(Tabela1[[#This Row],[RESULTADO]]/Tabela1[[#This Row],[FATURAMENTO]],"-") -> 0.32621194 | Q47: =IFERROR(I47/H47,"-") -> 13.864936 | R47: =_xlfn.XLOOKUP(C47,'Telemetria Sighra'!F:F,'Telemetria Sighra'!S:S,0) -> 1.7366176 | S47: =_xlfn.XLOOKUP(Tabela1[[#This Row],[PLACA]],'Telemetria Sighra'!F:F,'Telemetria Sighra'!I:I,0) -> 1120.5 | T47: =IFERROR((Tabela1[[#This Row],[LITROS CONSUMIDOS]]*$U$1)/Tabela1[[#This Row],[HODÔMETRO]],"-") -> 3.4556314
A48: DAF/XF FTT 530 | B48: 2024 | C48: SFA7G28 | D48: SANTOS X PAULINIA | E48: =IFERROR(_xlfn.XLOOKUP(Tabela1[[#This Row],[PLACA]],'Telemetria Sighra'!F:F,'Telemetria Sighra'!T:T),"NÃO EMBARCADO") -> EDUARDO RAFAEL BORGES - 253 | F48: {=SUMPRODUCT((ISNUMBER(FIND(C48,Faturamento!$F$2:$F$1014)))*(Faturamento!$AA$2:$AA$1014))} -> 2217 | G48: =Tabela1[[#This Row],[HODÔMETRO]]-Tabela1[[#This Row],[KM CARREGADO]] -> 680.27 | H48: =_xlfn.XLOOKUP(C48,'Telemetria Sighra'!F:F,'Telemetria Sighra'!R:R,0) -> 2897.27 | I48: =SUMIF(Faturamento!AC:AC,C48,Faturamento!T:T) -> 32474.43 | J48: {=SUMPRODUCT((ISNUMBER(FIND(C48,Faturamento!$F$2:$F$1014)))*(Faturamento!$R$2:$R$1014))} -> 119160 | K48: =$AH$2/30*$AA$1 -> 9479.7957 | L48: 4.4694 | M48: 39990 | N48: =Tabela1[[#This Row],[RESULTADO]]/Tabela1[[#This Row],[EBITDA ESTIMADO]] -> 0.25120219 | O48: =Tabela1[[#This Row],[FATURAMENTO]]-Tabela1[[#This Row],[CUSTO FIXO (SEM DEPREC.)]]-(Tabela1[[#This Row],[CUSTO VARIÁVEL]]*Tabela1[[#This Row],[HODÔMETRO]])+IF(COUNTIFS('ROTAS REALIZADAS'!A:A,Tabela1[[#This Row],[PLACA]],'ROTAS REALIZADAS'!A:A,"SANTOS/PAULINIA")>0,$AA$1*1233.33,0) -> 10045.576 | P48: =IFERROR(Tabela1[[#This Row],[RESULTADO]]/Tabela1[[#This Row],[FATURAMENTO]],"-") -> 0.30933802 | Q48: =IFERROR(I48/H48,"-") -> 11.208631 | R48: =_xlfn.XLOOKUP(C48,'Telemetria Sighra'!F:F,'Telemetria Sighra'!S:S,0) -> 1.4904269 | S48: =_xlfn.XLOOKUP(Tabela1[[#This Row],[PLACA]],'Telemetria Sighra'!F:F,'Telemetria Sighra'!I:I,0) -> 1943.98 | T48: =IFERROR((Tabela1[[#This Row],[LITROS CONSUMIDOS]]*$U$1)/Tabela1[[#This Row],[HODÔMETRO]],"-") -> 4.0258174
A49: DAF/XF FTT 530 | B49: 2024 | C49: SFF3I82 | D49: SANTOS X PAULINIA | E49: =IFERROR(_xlfn.XLOOKUP(Tabela1[[#This Row],[PLACA]],'Telemetria Sighra'!F:F,'Telemetria Sighra'!T:T),"NÃO EMBARCADO") -> ANDRIELIA APARECIDA GOMES - 238 | F49: {=SUMPRODUCT((ISNUMBER(FIND(C49,Faturamento!$F$2:$F$1014)))*(Faturamento!$AA$2:$AA$1014))} -> 1712 | G49: =Tabela1[[#This Row],[HODÔMETRO]]-Tabela1[[#This Row],[KM CARREGADO]] -> 71.09 | H49: =_xlfn.XLOOKUP(C49,'Telemetria Sighra'!F:F,'Telemetria Sighra'!R:R,0) -> 1783.09 | I49: =SUMIF(Faturamento!AC:AC,C49,Faturamento!T:T) -> 30696.67 | J49: {=SUMPRODUCT((ISNUMBER(FIND(C49,Faturamento!$F$2:$F$1014)))*(Faturamento!$R$2:$R$1014))} -> 164905 | K49: =$AH$2/30*$AA$1 -> 9479.7957 | L49: 4.4694 | M49: 39990 | N49: =Tabela1[[#This Row],[RESULTADO]]/Tabela1[[#This Row],[EBITDA ESTIMADO]] -> 0.33127111 | O49: =Tabela1[[#This Row],[FATURAMENTO]]-Tabela1[[#This Row],[CUSTO FIXO (SEM DEPREC.)]]-(Tabela1[[#This Row],[CUSTO VARIÁVEL]]*Tabela1[[#This Row],[HODÔMETRO]])+IF(COUNTIFS('ROTAS REALIZADAS'!A:A,Tabela1[[#This Row],[PLACA]],'ROTAS REALIZADAS'!A:A,"SANTOS/PAULINIA")>0,$AA$1*1233.33,0) -> 13247.532 | P49: =IFERROR(Tabela1[[#This Row],[RESULTADO]]/Tabela1[[#This Row],[FATURAMENTO]],"-") -> 0.43156251 | Q49: =IFERROR(I49/H49,"-") -> 17.215435 | R49: =_xlfn.XLOOKUP(C49,'Telemetria Sighra'!F:F,'Telemetria Sighra'!S:S,0) -> 1.2980797 | S49: =_xlfn.XLOOKUP(Tabela1[[#This Row],[PLACA]],'Telemetria Sighra'!F:F,'Telemetria Sighra'!I:I,0) -> 1373.76 | T49: =IFERROR((Tabela1[[#This Row],[LITROS CONSUMIDOS]]*$U$1)/Tabela1[[#This Row],[HODÔMETRO]],"-") -> 4.622627
A50: VOLVO/FH 500 6X4T S BIO | B50: 2025 | C50: TAW8B90 | D50: VIBRA | E50: =IFERROR(_xlfn.XLOOKUP(Tabela1[[#This Row],[PLACA]],'Telemetria Sighra'!F:F,'Telemetria Sighra'!T:T),"NÃO EMBARCADO") -> DEIZE CRISTINA WEILER - 10569 | F50: {=SUMPRODUCT((ISNUMBER(FIND(C50,Faturamento!$F$2:$F$1014)))*(Faturamento!$AA$2:$AA$1014))} -> 1638 | G50: =Tabela1[[#This Row],[HODÔMETRO]]-Tabela1[[#This Row],[KM CARREGADO]] -> 587.91 | H50: =_xlfn.XLOOKUP(C50,'Telemetria Sighra'!F:F,'Telemetria Sighra'!R:R,0) -> 2225.91 | I50: =SUMIF(Faturamento!AC:AC,C50,Faturamento!T:T) -> 33105.73 | J50: {=SUMPRODUCT((ISNUMBER(FIND(C50,Faturamento!$F$2:$F$1014)))*(Faturamento!$R$2:$R$1014))} -> 119193 | K50: =$AH$2/30*$AA$1 -> 9479.7957 | L50: 4.4694 | M50: 69761 | N50: =Tabela1[[#This Row],[RESULTADO]]/Tabela1[[#This Row],[EBITDA ESTIMADO]] -> 0.19606158 | O50: =Tabela1[[#This Row],[FATURAMENTO]]-Tabela1[[#This Row],[CUSTO FIXO (SEM DEPREC.)]]-(Tabela1[[#This Row],[CUSTO VARIÁVEL]]*Tabela1[[#This Row],[HODÔMETRO]])+IF(COUNTIFS('ROTAS REALIZADAS'!A:A,Tabela1[[#This Row],[PLACA]],'ROTAS REALIZADAS'!A:A,"SANTOS/PAULINIA")>0,$AA$1*1233.33,0) -> 13677.452 | P50: =IFERROR(Tabela1[[#This Row],[RESULTADO]]/Tabela1[[#This Row],[FATURAMENTO]],"-") -> 0.41314456 | Q50: =IFERROR(I50/H50,"-") -> 14.872897 | R50: =_xlfn.XLOOKUP(C50,'Telemetria Sighra'!F:F,'Telemetria Sighra'!S:S,0) -> 1.5803676 | S50: =_xlfn.XLOOKUP(Tabela1[[#This Row],[PLACA]],'Telemetria Sighra'!F:F,'Telemetria Sighra'!I:I,0) -> 1408.59 | T50: =IFERROR((Tabela1[[#This Row],[LITROS CONSUMIDOS]]*$U$1)/Tabela1[[#This Row],[HODÔMETRO]],"-") -> 3.7968921
A51: VOLVO/FH 500 6X4T S BIO | B51: 2025 | C51: TAW2A61 | D51: VIBRA | E51: =IFERROR(_xlfn.XLOOKUP(Tabela1[[#This Row],[PLACA]],'Telemetria Sighra'!F:F,'Telemetria Sighra'!T:T),"NÃO EMBARCADO") -> ALCIONE DE CASTRO - 180 | F51: {=SUMPRODUCT((ISNUMBER(FIND(C51,Faturamento!$F$2:$F$1014)))*(Faturamento!$AA$2:$AA$1014))} -> 2415 | G51: =Tabela1[[#This Row],[HODÔMETRO]]-Tabela1[[#This Row],[KM CARREGADO]] -> 914.08 | H51: =_xlfn.XLOOKUP(C51,'Telemetria Sighra'!F:F,'Telemetria Sighra'!R:R,0) -> 3329.08 | I51: =SUMIF(Faturamento!AC:AC,C51,Faturamento!T:T) -> 38108.13 | J51: {=SUMPRODUCT((ISNUMBER(FIND(C51,Faturamento!$F$2:$F$1014)))*(Faturamento!$R$2:$R$1014))} -> 167353 | K51: =$AH$2/30*$AA$1 -> 9479.7957 | L51: 4.4694 | M51: 69761 | N51: =Tabela1[[#This Row],[RESULTADO]]/Tabela1[[#This Row],[EBITDA ESTIMADO]] -> 0.19709213 | O51: =Tabela1[[#This Row],[FATURAMENTO]]-Tabela1[[#This Row],[CUSTO FIXO (SEM DEPREC.)]]-(Tabela1[[#This Row],[CUSTO VARIÁVEL]]*Tabela1[[#This Row],[HODÔMETRO]])+IF(COUNTIFS('ROTAS REALIZADAS'!A:A,Tabela1[[#This Row],[PLACA]],'ROTAS REALIZADAS'!A:A,"SANTOS/PAULINIA")>0,$AA$1*1233.33,0) -> 13749.344 | P51: =IFERROR(Tabela1[[#This Row],[RESULTADO]]/Tabela1[[#This Row],[FATURAMENTO]],"-") -> 0.36079818 | Q51: =IFERROR(I51/H51,"-") -> 11.447045 | R51: =_xlfn.XLOOKUP(C51,'Telemetria Sighra'!F:F,'Telemetria Sighra'!S:S,0) -> 1.6191895 | S51: =_xlfn.XLOOKUP(Tabela1[[#This Row],[PLACA]],'Telemetria Sighra'!F:F,'Telemetria Sighra'!I:I,0) -> 2053.83 | T51: =IFERROR((Tabela1[[#This Row],[LITROS CONSUMIDOS]]*$U$1)/Tabela1[[#This Row],[HODÔMETRO]],"-") -> 3.7016173
A52: DAF/XF FTT 530 | B52: 2024 | C52: SFC5F71 | D52: SANTOS X PAULINIA | E52: =IFERROR(_xlfn.XLOOKUP(Tabela1[[#This Row],[PLACA]],'Telemetria Sighra'!F:F,'Telemetria Sighra'!T:T),"NÃO EMBARCADO") -> ANTONIO MARCOS GONCALVES - 90 | F52: {=SUMPRODUCT((ISNUMBER(FIND(C52,Faturamento!$F$2:$F$1014)))*(Faturamento!$AA$2:$AA$1014))} -> 1968 | G52: =Tabela1[[#This Row],[HODÔMETRO]]-Tabela1[[#This Row],[KM CARREGADO]] -> 683.64 | H52: =_xlfn.XLOOKUP(C52,'Telemetria Sighra'!F:F,'Telemetria Sighra'!R:R,0) -> 2651.64 | I52: =SUMIF(Faturamento!AC:AC,C52,Faturamento!T:T) -> 35328.86 | J52: {=SUMPRODUCT((ISNUMBER(FIND(C52,Faturamento!$F$2:$F$1014)))*(Faturamento!$R$2:$R$1014))} -> 167265 | K52: =$AH$2/30*$AA$1 -> 9479.7957 | L52: 4.4694 | M52: 39990 | N52: =Tabela1[[#This Row],[RESULTADO]]/Tabela1[[#This Row],[EBITDA ESTIMADO]] -> 0.35003312 | O52: =Tabela1[[#This Row],[FATURAMENTO]]-Tabela1[[#This Row],[CUSTO FIXO (SEM DEPREC.)]]-(Tabela1[[#This Row],[CUSTO VARIÁVEL]]*Tabela1[[#This Row],[HODÔMETRO]])+IF(COUNTIFS('ROTAS REALIZADAS'!A:A,Tabela1[[#This Row],[PLACA]],'ROTAS REALIZADAS'!A:A,"SANTOS/PAULINIA")>0,$AA$1*1233.33,0) -> 13997.824 | P52: =IFERROR(Tabela1[[#This Row],[RESULTADO]]/Tabela1[[#This Row],[FATURAMENTO]],"-") -> 0.39621501 | Q52: =IFERROR(I52/H52,"-") -> 13.3234 | R52: =_xlfn.XLOOKUP(C52,'Telemetria Sighra'!F:F,'Telemetria Sighra'!S:S,0) -> 1.4117728 | S52: =_xlfn.XLOOKUP(Tabela1[[#This Row],[PLACA]],'Telemetria Sighra'!F:F,'Telemetria Sighra'!I:I,0) -> 1878.39 | T52: =IFERROR((Tabela1[[#This Row],[LITROS CONSUMIDOS]]*$U$1)/Tabela1[[#This Row],[HODÔMETRO]],"-") -> 4.2503281
A53: SCANIA/R 440 A6X2 | B53: 2013 | C53: AWZ2403 | D53: PGUA X LAPA | E53: =IFERROR(_xlfn.XLOOKUP(Tabela1[[#This Row],[PLACA]],'Telemetria Sighra'!F:F,'Telemetria Sighra'!T:T),"NÃO EMBARCADO") -> ANTONIO MARCOS GONCALVES - 90 | F53: {=SUMPRODUCT((ISNUMBER(FIND(C53,Faturamento!$F$2:$F$1014)))*(Faturamento!$AA$2:$AA$1014))} -> 1224 | G53: =Tabela1[[#This Row],[HODÔMETRO]]-Tabela1[[#This Row],[KM CARREGADO]] -> 1605.5 | H53: =_xlfn.XLOOKUP(C53,'Telemetria Sighra'!F:F,'Telemetria Sighra'!R:R,0) -> 2829.5 | I53: =SUMIF(Faturamento!AC:AC,C53,Faturamento!T:T) -> 32145.51 | J53: {=SUMPRODUCT((ISNUMBER(FIND(C53,Faturamento!$F$2:$F$1014)))*(Faturamento!$R$2:$R$1014))} -> 313004 | K53: =$AD$2/30*$AA$1 -> 7856.0195 | L53: 3.55 | M53: 63000 | N53: =Tabela1[[#This Row],[RESULTADO]]/Tabela1[[#This Row],[EBITDA ESTIMADO]] -> 0.22610739 | O53: =Tabela1[[#This Row],[FATURAMENTO]]-Tabela1[[#This Row],[CUSTO FIXO (SEM DEPREC.)]]-(Tabela1[[#This Row],[CUSTO VARIÁVEL]]*Tabela1[[#This Row],[HODÔMETRO]])+IF(COUNTIFS('ROTAS REALIZADAS'!A:A,Tabela1[[#This Row],[PLACA]],'ROTAS REALIZADAS'!A:A,"SANTOS/PAULINIA")>0,$AA$1*1233.33,0) -> 14244.765 | P53: =IFERROR(Tabela1[[#This Row],[RESULTADO]]/Tabela1[[#This Row],[FATURAMENTO]],"-") -> 0.44313391 | Q53: =IFERROR(I53/H53,"-") -> 11.360845 | R53: =_xlfn.XLOOKUP(C53,'Telemetria Sighra'!F:F,'Telemetria Sighra'!S:S,0) -> 1.8846269 | S53: =_xlfn.XLOOKUP(Tabela1[[#This Row],[PLACA]],'Telemetria Sighra'!F:F,'Telemetria Sighra'!I:I,0) -> 1501.65 | T53: =IFERROR((Tabela1[[#This Row],[LITROS CONSUMIDOS]]*$U$1)/Tabela1[[#This Row],[HODÔMETRO]],"-") -> 3.1842728
A54: DAF/XF FTT 530 | B54: 2024 | C54: SEY8B40 | D54: METANOL | E54: =IFERROR(_xlfn.XLOOKUP(Tabela1[[#This Row],[PLACA]],'Telemetria Sighra'!F:F,'Telemetria Sighra'!T:T),"NÃO EMBARCADO") -> ALEX DE OLIVEIRA RODRIGUES - 50100 | F54: {=SUMPRODUCT((ISNUMBER(FIND(C54,Faturamento!$F$2:$F$1014)))*(Faturamento!$AA$2:$AA$1014))} -> 1896 | G54: =Tabela1[[#This Row],[HODÔMETRO]]-Tabela1[[#This Row],[KM CARREGADO]] -> 1867.48 | H54: =_xlfn.XLOOKUP(C54,'Telemetria Sighra'!F:F,'Telemetria Sighra'!R:R,0) -> 3763.48 | I54: =SUMIF(Faturamento!AC:AC,C54,Faturamento!T:T) -> 41124.25 | J54: {=SUMPRODUCT((ISNUMBER(FIND(C54,Faturamento!$F$2:$F$1014)))*(Faturamento!$R$2:$R$1014))} -> 235743 | K54: =$AH$2/30*$AA$1 -> 9479.7957 | L54: 4.4694 | M54: 47896 | N54: =Tabela1[[#This Row],[RESULTADO]]/Tabela1[[#This Row],[EBITDA ESTIMADO]] -> 0.30950302 | O54: =Tabela1[[#This Row],[FATURAMENTO]]-Tabela1[[#This Row],[CUSTO FIXO (SEM DEPREC.)]]-(Tabela1[[#This Row],[CUSTO VARIÁVEL]]*Tabela1[[#This Row],[HODÔMETRO]])+IF(COUNTIFS('ROTAS REALIZADAS'!A:A,Tabela1[[#This Row],[PLACA]],'ROTAS REALIZADAS'!A:A,"SANTOS/PAULINIA")>0,$AA$1*1233.33,0) -> 14823.957 | P54: =IFERROR(Tabela1[[#This Row],[RESULTADO]]/Tabela1[[#This Row],[FATURAMENTO]],"-") -> 0.36046753 | Q54: =IFERROR(I54/H54,"-") -> 10.927187 | R54: =_xlfn.XLOOKUP(C54,'Telemetria Sighra'!F:F,'Telemetria Sighra'!S:S,0) -> 1.616824 | S54: =_xlfn.XLOOKUP(Tabela1[[#This Row],[PLACA]],'Telemetria Sighra'!F:F,'Telemetria Sighra'!I:I,0) -> 2327.86 | T54: =IFERROR((Tabela1[[#This Row],[LITROS CONSUMIDOS]]*$U$1)/Tabela1[[#This Row],[HODÔMETRO]],"-") -> 3.7112353
A55: DAF/XF FTT 530 | B55: 2021 | C55: RHI3D46 | D55: SANTOS X PAULINIA | E55: =IFERROR(_xlfn.XLOOKUP(Tabela1[[#This Row],[PLACA]],'Telemetria Sighra'!F:F,'Telemetria Sighra'!T:T),"NÃO EMBARCADO") -> ELENILDO GOMES DA SILVA - 10843 | F55: {=SUMPRODUCT((ISNUMBER(FIND(C55,Faturamento!$F$2:$F$1014)))*(Faturamento!$AA$2:$AA$1014))} -> 2133 | G55: =Tabela1[[#This Row],[HODÔMETRO]]-Tabela1[[#This Row],[KM CARREGADO]] -> 554.43 | H55: =_xlfn.XLOOKUP(C55,'Telemetria Sighra'!F:F,'Telemetria Sighra'!R:R,0) -> 2687.43 | I55: =SUMIF(Faturamento!AC:AC,C55,Faturamento!T:T) -> 36457.62 | J55: {=SUMPRODUCT((ISNUMBER(FIND(C55,Faturamento!$F$2:$F$1014)))*(Faturamento!$R$2:$R$1014))} -> 177843 | K55: =$AH$2/30*$AA$1 -> 9479.7957 | L55: 4.4694 | M55: 39990 | N55: =Tabela1[[#This Row],[RESULTADO]]/Tabela1[[#This Row],[EBITDA ESTIMADO]] -> 0.37425918 | O55: =Tabela1[[#This Row],[FATURAMENTO]]-Tabela1[[#This Row],[CUSTO FIXO (SEM DEPREC.)]]-(Tabela1[[#This Row],[CUSTO VARIÁVEL]]*Tabela1[[#This Row],[HODÔMETRO]])+IF(COUNTIFS('ROTAS REALIZADAS'!A:A,Tabela1[[#This Row],[PLACA]],'ROTAS REALIZADAS'!A:A,"SANTOS/PAULINIA")>0,$AA$1*1233.33,0) -> 14966.625 | P55: =IFERROR(Tabela1[[#This Row],[RESULTADO]]/Tabela1[[#This Row],[FATURAMENTO]],"-") -> 0.41052117 | Q55: =IFERROR(I55/H55,"-") -> 13.565979 | R55: =_xlfn.XLOOKUP(C55,'Telemetria Sighra'!F:F,'Telemetria Sighra'!S:S,0) -> 1.3177646 | S55: =_xlfn.XLOOKUP(Tabela1[[#This Row],[PLACA]],'Telemetria Sighra'!F:F,'Telemetria Sighra'!I:I,0) -> 2039.56 | T55: =IFERROR((Tabela1[[#This Row],[LITROS CONSUMIDOS]]*$U$1)/Tabela1[[#This Row],[HODÔMETRO]],"-") -> 4.5535549
A56: DAF/XF FTT 530 | B56: 2024 | C56: SEY8B43 | D56: CAMERA | E56: =IFERROR(_xlfn.XLOOKUP(Tabela1[[#This Row],[PLACA]],'Telemetria Sighra'!F:F,'Telemetria Sighra'!T:T),"NÃO EMBARCADO") -> JOAQUIM RAIMUNDO PORTES JUNIOR - 195 | F56: {=SUMPRODUCT((ISNUMBER(FIND(C56,Faturamento!$F$2:$F$1014)))*(Faturamento!$AA$2:$AA$1014))} -> 2868 | G56: =Tabela1[[#This Row],[HODÔMETRO]]-Tabela1[[#This Row],[KM CARREGADO]] -> 821.73 | H56: =_xlfn.XLOOKUP(C56,'Telemetria Sighra'!F:F,'Telemetria Sighra'!R:R,0) -> 3689.73 | I56: =SUMIF(Faturamento!AC:AC,C56,Faturamento!T:T) -> 41228.52 | J56: {=SUMPRODUCT((ISNUMBER(FIND(C56,Faturamento!$F$2:$F$1014)))*(Faturamento!$R$2:$R$1014))} -> 220246 | K56: =$AH$2/30*$AA$1 -> 9479.7957 | L56: 4.4694 | M56: 53428 | N56: =Tabela1[[#This Row],[RESULTADO]]/Tabela1[[#This Row],[EBITDA ESTIMADO]] -> 0.28557769 | O56: =Tabela1[[#This Row],[FATURAMENTO]]-Tabela1[[#This Row],[CUSTO FIXO (SEM DEPREC.)]]-(Tabela1[[#This Row],[CUSTO VARIÁVEL]]*Tabela1[[#This Row],[HODÔMETRO]])+IF(COUNTIFS('ROTAS REALIZADAS'!A:A,Tabela1[[#This Row],[PLACA]],'ROTAS REALIZADAS'!A:A,"SANTOS/PAULINIA")>0,$AA$1*1233.33,0) -> 15257.845 | P56: =IFERROR(Tabela1[[#This Row],[RESULTADO]]/Tabela1[[#This Row],[FATURAMENTO]],"-") -> 0.37007986 | Q56: =IFERROR(I56/H56,"-") -> 11.173858 | R56: =_xlfn.XLOOKUP(C56,'Telemetria Sighra'!F:F,'Telemetria Sighra'!S:S,0) -> 1.4356536 | S56: =_xlfn.XLOOKUP(Tabela1[[#This Row],[PLACA]],'Telemetria Sighra'!F:F,'Telemetria Sighra'!I:I,0) -> 2570.23 | T56: =IFERROR((Tabela1[[#This Row],[LITROS CONSUMIDOS]]*$U$1)/Tabela1[[#This Row],[HODÔMETRO]],"-") -> 4.1795416
A57: DAF/XF FTT 530 | B57: 2024 | C57: SFF3I83 | D57: VIBRA | E57: =IFERROR(_xlfn.XLOOKUP(Tabela1[[#This Row],[PLACA]],'Telemetria Sighra'!F:F,'Telemetria Sighra'!T:T),"NÃO EMBARCADO") -> WALDECIR JOSE XAVIER - 135 | F57: {=SUMPRODUCT((ISNUMBER(FIND(C57,Faturamento!$F$2:$F$1014)))*(Faturamento!$AA$2:$AA$1014))} -> 1690 | G57: =Tabela1[[#This Row],[HODÔMETRO]]-Tabela1[[#This Row],[KM CARREGADO]] -> 993.97 | H57: =_xlfn.XLOOKUP(C57,'Telemetria Sighra'!F:F,'Telemetria Sighra'!R:R,0) -> 2683.97 | I57: =SUMIF(Faturamento!AC:AC,C57,Faturamento!T:T) -> 36739.29 | J57: {=SUMPRODUCT((ISNUMBER(FIND(C57,Faturamento!$F$2:$F$1014)))*(Faturamento!$R$2:$R$1014))} -> 107981 | K57: =$AH$2/30*$AA$1 -> 9479.7957 | L57: 4.4694 | M57: 69761 | N57: =Tabela1[[#This Row],[RESULTADO]]/Tabela1[[#This Row],[EBITDA ESTIMADO]] -> 0.21880074 | O57: =Tabela1[[#This Row],[FATURAMENTO]]-Tabela1[[#This Row],[CUSTO FIXO (SEM DEPREC.)]]-(Tabela1[[#This Row],[CUSTO VARIÁVEL]]*Tabela1[[#This Row],[HODÔMETRO]])+IF(COUNTIFS('ROTAS REALIZADAS'!A:A,Tabela1[[#This Row],[PLACA]],'ROTAS REALIZADAS'!A:A,"SANTOS/PAULINIA")>0,$AA$1*1233.33,0) -> 15263.759 | P57: =IFERROR(Tabela1[[#This Row],[RESULTADO]]/Tabela1[[#This Row],[FATURAMENTO]],"-") -> 0.41546145 | Q57: =IFERROR(I57/H57,"-") -> 13.688413 | R57: =_xlfn.XLOOKUP(C57,'Telemetria Sighra'!F:F,'Telemetria Sighra'!S:S,0) -> 1.5120778 | S57: =_xlfn.XLOOKUP(Tabela1[[#This Row],[PLACA]],'Telemetria Sighra'!F:F,'Telemetria Sighra'!I:I,0) -> 1775.16 | T57: =IFERROR((Tabela1[[#This Row],[LITROS CONSUMIDOS]]*$U$1)/Tabela1[[#This Row],[HODÔMETRO]],"-") -> 3.9683603
A58: VOLVO/FH 500 6X4T S BIO | B58: 2025 | C58: TAW8B87 | D58: VIBRA | E58: =IFERROR(_xlfn.XLOOKUP(Tabela1[[#This Row],[PLACA]],'Telemetria Sighra'!F:F,'Telemetria Sighra'!T:T),"NÃO EMBARCADO") -> VITOR RAFAEL PEDROZO - 143 | F58: {=SUMPRODUCT((ISNUMBER(FIND(C58,Faturamento!$F$2:$F$1014)))*(Faturamento!$AA$2:$AA$1014))} -> 1896 | G58: =Tabela1[[#This Row],[HODÔMETRO]]-Tabela1[[#This Row],[KM CARREGADO]] -> 1899.29 | H58: =_xlfn.XLOOKUP(C58,'Telemetria Sighra'!F:F,'Telemetria Sighra'!R:R,0) -> 3795.29 | I58: =SUMIF(Faturamento!AC:AC,C58,Faturamento!T:T) -> 42151.26 | J58: {=SUMPRODUCT((ISNUMBER(FIND(C58,Faturamento!$F$2:$F$1014)))*(Faturamento!$R$2:$R$1014))} -> 238540 | K58: =$AH$2/30*$AA$1 -> 9479.7957 | L58: 4.4694 | M58: 69761 | N58: =Tabela1[[#This Row],[RESULTADO]]/Tabela1[[#This Row],[EBITDA ESTIMADO]] -> 0.22518019 | O58: =Tabela1[[#This Row],[FATURAMENTO]]-Tabela1[[#This Row],[CUSTO FIXO (SEM DEPREC.)]]-(Tabela1[[#This Row],[CUSTO VARIÁVEL]]*Tabela1[[#This Row],[HODÔMETRO]])+IF(COUNTIFS('ROTAS REALIZADAS'!A:A,Tabela1[[#This Row],[PLACA]],'ROTAS REALIZADAS'!A:A,"SANTOS/PAULINIA")>0,$AA$1*1233.33,0) -> 15708.795 | P58: =IFERROR(Tabela1[[#This Row],[RESULTADO]]/Tabela1[[#This Row],[FATURAMENTO]],"-") -> 0.37267676 | Q58: =IFERROR(I58/H58,"-") -> 11.106203 | R58: =_xlfn.XLOOKUP(C58,'Telemetria Sighra'!F:F,'Telemetria Sighra'!S:S,0) -> 1.8209173 | S58: =_xlfn.XLOOKUP(Tabela1[[#This Row],[PLACA]],'Telemetria Sighra'!F:F,'Telemetria Sighra'!I:I,0) -> 2084.4 | T58: =IFERROR((Tabela1[[#This Row],[LITROS CONSUMIDOS]]*$U$1)/Tabela1[[#This Row],[HODÔMETRO]],"-") -> 3.2952423
A59: VOLVO/FH 540 6X4T | B59: 2020 | C59: BDQ4E23 | D59: VIBRA | E59: =IFERROR(_xlfn.XLOOKUP(Tabela1[[#This Row],[PLACA]],'Telemetria Sighra'!F:F,'Telemetria Sighra'!T:T),"NÃO EMBARCADO") -> DANIEL ANTONIO DOS SANTOS JUNIOR - 224 | F59: {=SUMPRODUCT((ISNUMBER(FIND(C59,Faturamento!$F$2:$F$1014)))*(Faturamento!$AA$2:$AA$1014))} -> 2199 | G59: =Tabela1[[#This Row],[HODÔMETRO]]-Tabela1[[#This Row],[KM CARREGADO]] -> 23.02 | H59: =_xlfn.XLOOKUP(C59,'Telemetria Sighra'!F:F,'Telemetria Sighra'!R:R,0) -> 2222.02 | I59: =SUMIF(Faturamento!AC:AC,C59,Faturamento!T:T) -> 36198.19 | J59: {=SUMPRODUCT((ISNUMBER(FIND(C59,Faturamento!$F$2:$F$1014)))*(Faturamento!$R$2:$R$1014))} -> 163526 | K59: =$AH$2/30*$AA$1 -> 9479.7957 | L59: 4.4694 | M59: 69761 | N59: =Tabela1[[#This Row],[RESULTADO]]/Tabela1[[#This Row],[EBITDA ESTIMADO]] -> 0.24064016 | O59: =Tabela1[[#This Row],[FATURAMENTO]]-Tabela1[[#This Row],[CUSTO FIXO (SEM DEPREC.)]]-(Tabela1[[#This Row],[CUSTO VARIÁVEL]]*Tabela1[[#This Row],[HODÔMETRO]])+IF(COUNTIFS('ROTAS REALIZADAS'!A:A,Tabela1[[#This Row],[PLACA]],'ROTAS REALIZADAS'!A:A,"SANTOS/PAULINIA")>0,$AA$1*1233.33,0) -> 16787.298 | P59: =IFERROR(Tabela1[[#This Row],[RESULTADO]]/Tabela1[[#This Row],[FATURAMENTO]],"-") -> 0.4637607 | Q59: =IFERROR(I59/H59,"-") -> 16.290668 | R59: =_xlfn.XLOOKUP(C59,'Telemetria Sighra'!F:F,'Telemetria Sighra'!S:S,0) -> 1.4418808 | S59: =_xlfn.XLOOKUP(Tabela1[[#This Row],[PLACA]],'Telemetria Sighra'!F:F,'Telemetria Sighra'!I:I,0) -> 1541.23 | T59: =IFERROR((Tabela1[[#This Row],[LITROS CONSUMIDOS]]*$U$1)/Tabela1[[#This Row],[HODÔMETRO]],"-") -> 4.1616997
A60: VOLVO/FH 500 6X4T S BIO | B60: 2025 | C60: TAW8B89 | D60: VIBRA | E60: =IFERROR(_xlfn.XLOOKUP(Tabela1[[#This Row],[PLACA]],'Telemetria Sighra'!F:F,'Telemetria Sighra'!T:T),"NÃO EMBARCADO") -> AMAURI DOS SANTOS PEREIRA - 240 | F60: {=SUMPRODUCT((ISNUMBER(FIND(C60,Faturamento!$F$2:$F$1014)))*(Faturamento!$AA$2:$AA$1014))} -> 2123 | G60: =Tabela1[[#This Row],[HODÔMETRO]]-Tabela1[[#This Row],[KM CARREGADO]] -> 272.96 | H60: =_xlfn.XLOOKUP(C60,'Telemetria Sighra'!F:F,'Telemetria Sighra'!R:R,0) -> 2395.96 | I60: =SUMIF(Faturamento!AC:AC,C60,Faturamento!T:T) -> 37115.97 | J60: {=SUMPRODUCT((ISNUMBER(FIND(C60,Faturamento!$F$2:$F$1014)))*(Faturamento!$R$2:$R$1014))} -> 119192 | K60: =$AH$2/30*$AA$1 -> 9479.7957 | L60: 4.4694 | M60: 69761 | N60: =Tabela1[[#This Row],[RESULTADO]]/Tabela1[[#This Row],[EBITDA ESTIMADO]] -> 0.24265235 | O60: =Tabela1[[#This Row],[FATURAMENTO]]-Tabela1[[#This Row],[CUSTO FIXO (SEM DEPREC.)]]-(Tabela1[[#This Row],[CUSTO VARIÁVEL]]*Tabela1[[#This Row],[HODÔMETRO]])+IF(COUNTIFS('ROTAS REALIZADAS'!A:A,Tabela1[[#This Row],[PLACA]],'ROTAS REALIZADAS'!A:A,"SANTOS/PAULINIA")>0,$AA$1*1233.33,0) -> 16927.671 | P60: =IFERROR(Tabela1[[#This Row],[RESULTADO]]/Tabela1[[#This Row],[FATURAMENTO]],"-") -> 0.45607512 | Q60: =IFERROR(I60/H60,"-") -> 15.491064 | R60: =_xlfn.XLOOKUP(C60,'Telemetria Sighra'!F:F,'Telemetria Sighra'!S:S,0) -> 1.7598434 | S60: =_xlfn.XLOOKUP(Tabela1[[#This Row],[PLACA]],'Telemetria Sighra'!F:F,'Telemetria Sighra'!I:I,0) -> 1361.57 | T60: =IFERROR((Tabela1[[#This Row],[LITROS CONSUMIDOS]]*$U$1)/Tabela1[[#This Row],[HODÔMETRO]],"-") -> 3.4096646
A61: DAF/XF FTT 530 | B61: 2024 | C61: SFC5G04 | D61: VIBRA | E61: =IFERROR(_xlfn.XLOOKUP(Tabela1[[#This Row],[PLACA]],'Telemetria Sighra'!F:F,'Telemetria Sighra'!T:T),"NÃO EMBARCADO") -> JONATAN MODESTO - 187 | F61: {=SUMPRODUCT((ISNUMBER(FIND(C61,Faturamento!$F$2:$F$1014)))*(Faturamento!$AA$2:$AA$1014))} -> 2216 | G61: =Tabela1[[#This Row],[HODÔMETRO]]-Tabela1[[#This Row],[KM CARREGADO]] -> 1410.76 | H61: =_xlfn.XLOOKUP(C61,'Telemetria Sighra'!F:F,'Telemetria Sighra'!R:R,0) -> 3626.76 | I61: =SUMIF(Faturamento!AC:AC,C61,Faturamento!T:T) -> 44163.73 | J61: {=SUMPRODUCT((ISNUMBER(FIND(C61,Faturamento!$F$2:$F$1014)))*(Faturamento!$R$2:$R$1014))} -> 178791 | K61: =$AH$2/30*$AA$1 -> 9479.7957 | L61: 4.4694 | M61: 69761 | N61: =Tabela1[[#This Row],[RESULTADO]]/Tabela1[[#This Row],[EBITDA ESTIMADO]] -> 0.26482552 | O61: =Tabela1[[#This Row],[FATURAMENTO]]-Tabela1[[#This Row],[CUSTO FIXO (SEM DEPREC.)]]-(Tabela1[[#This Row],[CUSTO VARIÁVEL]]*Tabela1[[#This Row],[HODÔMETRO]])+IF(COUNTIFS('ROTAS REALIZADAS'!A:A,Tabela1[[#This Row],[PLACA]],'ROTAS REALIZADAS'!A:A,"SANTOS/PAULINIA")>0,$AA$1*1233.33,0) -> 18474.493 | P61: =IFERROR(Tabela1[[#This Row],[RESULTADO]]/Tabela1[[#This Row],[FATURAMENTO]],"-") -> 0.41831822 | Q61: =IFERROR(I61/H61,"-") -> 12.177186 | R61: =_xlfn.XLOOKUP(C61,'Telemetria Sighra'!F:F,'Telemetria Sighra'!S:S,0) -> 1.469692 | S61: =_xlfn.XLOOKUP(Tabela1[[#This Row],[PLACA]],'Telemetria Sighra'!F:F,'Telemetria Sighra'!I:I,0) -> 2467.83 | T61: =IFERROR((Tabela1[[#This Row],[LITROS CONSUMIDOS]]*$U$1)/Tabela1[[#This Row],[HODÔMETRO]],"-") -> 4.0827019
A62: DAF/XF FTT 530 | B62: 2023 | C62: SEE0I38 | D62: SANTOS X PAULINIA | E62: =IFERROR(_xlfn.XLOOKUP(Tabela1[[#This Row],[PLACA]],'Telemetria Sighra'!F:F,'Telemetria Sighra'!T:T),"NÃO EMBARCADO") -> FELIPE NUNES - 251 | F62: {=SUMPRODUCT((ISNUMBER(FIND(C62,Faturamento!$F$2:$F$1014)))*(Faturamento!$AA$2:$AA$1014))} -> 2613 | G62: =Tabela1[[#This Row],[HODÔMETRO]]-Tabela1[[#This Row],[KM CARREGADO]] -> 416.72 | H62: =_xlfn.XLOOKUP(C62,'Telemetria Sighra'!F:F,'Telemetria Sighra'!R:R,0) -> 3029.72 | I62: =SUMIF(Faturamento!AC:AC,C62,Faturamento!T:T) -> 42642.42 | J62: {=SUMPRODUCT((ISNUMBER(FIND(C62,Faturamento!$F$2:$F$1014)))*(Faturamento!$R$2:$R$1014))} -> 166866 | K62: =$AH$2/30*$AA$1 -> 9479.7957 | L62: 4.4694 | M62: 39990 | N62: =Tabela1[[#This Row],[RESULTADO]]/Tabela1[[#This Row],[EBITDA ESTIMADO]] -> 0.49066251 | O62: =Tabela1[[#This Row],[FATURAMENTO]]-Tabela1[[#This Row],[CUSTO FIXO (SEM DEPREC.)]]-(Tabela1[[#This Row],[CUSTO VARIÁVEL]]*Tabela1[[#This Row],[HODÔMETRO]])+IF(COUNTIFS('ROTAS REALIZADAS'!A:A,Tabela1[[#This Row],[PLACA]],'ROTAS REALIZADAS'!A:A,"SANTOS/PAULINIA")>0,$AA$1*1233.33,0) -> 19621.594 | P62: =IFERROR(Tabela1[[#This Row],[RESULTADO]]/Tabela1[[#This Row],[FATURAMENTO]],"-") -> 0.46014259 | Q62: =IFERROR(I62/H62,"-") -> 14.074707 | R62: =_xlfn.XLOOKUP(C62,'Telemetria Sighra'!F:F,'Telemetria Sighra'!S:S,0) -> 1.4161043 | S62: =_xlfn.XLOOKUP(Tabela1[[#This Row],[PLACA]],'Telemetria Sighra'!F:F,'Telemetria Sighra'!I:I,0) -> 2047.9 | T62: =IFERROR((Tabela1[[#This Row],[LITROS CONSUMIDOS]]*$U$1)/Tabela1[[#This Row],[HODÔMETRO]],"-") -> 4.0556223
A63: SCANIA/R500 A6X4 | B63: 2019 | C63: BDF9C15 | D63: PGUA X LAPA | E63: =IFERROR(_xlfn.XLOOKUP(Tabela1[[#This Row],[PLACA]],'Telemetria Sighra'!F:F,'Telemetria Sighra'!T:T),"NÃO EMBARCADO") -> GUSTAVO ANTONIO NOGUEIRA - 73 | F63: {=SUMPRODUCT((ISNUMBER(FIND(C63,Faturamento!$F$2:$F$1014)))*(Faturamento!$AA$2:$AA$1014))} -> 1683 | G63: =Tabela1[[#This Row],[HODÔMETRO]]-Tabela1[[#This Row],[KM CARREGADO]] -> 1752.08 | H63: =_xlfn.XLOOKUP(C63,'Telemetria Sighra'!F:F,'Telemetria Sighra'!R:R,0) -> 3435.08 | I63: =SUMIF(Faturamento!AC:AC,C63,Faturamento!T:T) -> 42980.98 | J63: {=SUMPRODUCT((ISNUMBER(FIND(C63,Faturamento!$F$2:$F$1014)))*(Faturamento!$R$2:$R$1014))} -> 418510 | K63: =$AD$2/30*$AA$1 -> 7856.0195 | L63: 3.55 | M63: 36051 | N63: =Tabela1[[#This Row],[RESULTADO]]/Tabela1[[#This Row],[EBITDA ESTIMADO]] -> 0.63605521 | O63: =Tabela1[[#This Row],[FATURAMENTO]]-Tabela1[[#This Row],[CUSTO FIXO (SEM DEPREC.)]]-(Tabela1[[#This Row],[CUSTO VARIÁVEL]]*Tabela1[[#This Row],[HODÔMETRO]])+IF(COUNTIFS('ROTAS REALIZADAS'!A:A,Tabela1[[#This Row],[PLACA]],'ROTAS REALIZADAS'!A:A,"SANTOS/PAULINIA")>0,$AA$1*1233.33,0) -> 22930.426 | P63: =IFERROR(Tabela1[[#This Row],[RESULTADO]]/Tabela1[[#This Row],[FATURAMENTO]],"-") -> 0.53350171 | Q63: =IFERROR(I63/H63,"-") -> 12.512367 | R63: =_xlfn.XLOOKUP(C63,'Telemetria Sighra'!F:F,'Telemetria Sighra'!S:S,0) -> 1.9231183 | S63: =_xlfn.XLOOKUP(Tabela1[[#This Row],[PLACA]],'Telemetria Sighra'!F:F,'Telemetria Sighra'!I:I,0) -> 1786.51 | T63: =IFERROR((Tabela1[[#This Row],[LITROS CONSUMIDOS]]*$U$1)/Tabela1[[#This Row],[HODÔMETRO]],"-") -> 3.1204688
A64: DAF/XF FTT 530 | B64: 2023 | C64: SEE3G48 | D64: SANTOS X PAULINIA | E64: =IFERROR(_xlfn.XLOOKUP(Tabela1[[#This Row],[PLACA]],'Telemetria Sighra'!F:F,'Telemetria Sighra'!T:T),"NÃO EMBARCADO") -> RAFAEL SOUZA MIRANDA - 5004 | F64: {=SUMPRODUCT((ISNUMBER(FIND(C64,Faturamento!$F$2:$F$1014)))*(Faturamento!$AA$2:$AA$1014))} -> 2779 | G64: =Tabela1[[#This Row],[HODÔMETRO]]-Tabela1[[#This Row],[KM CARREGADO]] -> -79.95 | H64: =_xlfn.XLOOKUP(C64,'Telemetria Sighra'!F:F,'Telemetria Sighra'!R:R,0) -> 2699.05 | I64: =SUMIF(Faturamento!AC:AC,C64,Faturamento!T:T) -> 46662.6 | J64: {=SUMPRODUCT((ISNUMBER(FIND(C64,Faturamento!$F$2:$F$1014)))*(Faturamento!$R$2:$R$1014))} -> 225111 | K64: =$AH$2/30*$AA$1 -> 9479.7957 | L64: 4.4694 | M64: 39990 | N64: =Tabela1[[#This Row],[RESULTADO]]/Tabela1[[#This Row],[EBITDA ESTIMADO]] -> 0.62814879 | O64: =Tabela1[[#This Row],[FATURAMENTO]]-Tabela1[[#This Row],[CUSTO FIXO (SEM DEPREC.)]]-(Tabela1[[#This Row],[CUSTO VARIÁVEL]]*Tabela1[[#This Row],[HODÔMETRO]])+IF(COUNTIFS('ROTAS REALIZADAS'!A:A,Tabela1[[#This Row],[PLACA]],'ROTAS REALIZADAS'!A:A,"SANTOS/PAULINIA")>0,$AA$1*1233.33,0) -> 25119.67 | P64: =IFERROR(Tabela1[[#This Row],[RESULTADO]]/Tabela1[[#This Row],[FATURAMENTO]],"-") -> 0.53832556 | Q64: =IFERROR(I64/H64,"-") -> 17.288527 | R64: =_xlfn.XLOOKUP(C64,'Telemetria Sighra'!F:F,'Telemetria Sighra'!S:S,0) -> 1.4514131 | S64: =_xlfn.XLOOKUP(Tabela1[[#This Row],[PLACA]],'Telemetria Sighra'!F:F,'Telemetria Sighra'!I:I,0) -> 1859.76 | T64: =IFERROR((Tabela1[[#This Row],[LITROS CONSUMIDOS]]*$U$1)/Tabela1[[#This Row],[HODÔMETRO]],"-") -> 4.1342546
A65: DAF/XF FTT 530 | B65: 2021 | C65: RHG5D74 | D65: SANTOS X PAULINIA | E65: =IFERROR(_xlfn.XLOOKUP(Tabela1[[#This Row],[PLACA]],'Telemetria Sighra'!F:F,'Telemetria Sighra'!T:T),"NÃO EMBARCADO") -> CLAUDINIR RODRIGUES GARCIA - 186 | F65: {=SUMPRODUCT((ISNUMBER(FIND(C65,Faturamento!$F$2:$F$1014)))*(Faturamento!$AA$2:$AA$1014))} -> 2787 | G65: =Tabela1[[#This Row],[HODÔMETRO]]-Tabela1[[#This Row],[KM CARREGADO]] -> 1077.27 | H65: =_xlfn.XLOOKUP(C65,'Telemetria Sighra'!F:F,'Telemetria Sighra'!R:R,0) -> 3864.27 | I65: =SUMIF(Faturamento!AC:AC,C65,Faturamento!T:T) -> 54119.66 | J65: {=SUMPRODUCT((ISNUMBER(FIND(C65,Faturamento!$F$2:$F$1014)))*(Faturamento!$R$2:$R$1014))} -> 239071 | K65: =$AH$2/30*$AA$1 -> 9479.7957 | L65: 4.4694 | M65: 39990 | N65: =Tabela1[[#This Row],[RESULTADO]]/Tabela1[[#This Row],[EBITDA ESTIMADO]] -> 0.6843935 | O65: =Tabela1[[#This Row],[FATURAMENTO]]-Tabela1[[#This Row],[CUSTO FIXO (SEM DEPREC.)]]-(Tabela1[[#This Row],[CUSTO VARIÁVEL]]*Tabela1[[#This Row],[HODÔMETRO]])+IF(COUNTIFS('ROTAS REALIZADAS'!A:A,Tabela1[[#This Row],[PLACA]],'ROTAS REALIZADAS'!A:A,"SANTOS/PAULINIA")>0,$AA$1*1233.33,0) -> 27368.896 | P65: =IFERROR(Tabela1[[#This Row],[RESULTADO]]/Tabela1[[#This Row],[FATURAMENTO]],"-") -> 0.50571079 | Q65: =IFERROR(I65/H65,"-") -> 14.005145 | R65: =_xlfn.XLOOKUP(C65,'Telemetria Sighra'!F:F,'Telemetria Sighra'!S:S,0) -> 1.5079231 | S65: =_xlfn.XLOOKUP(Tabela1[[#This Row],[PLACA]],'Telemetria Sighra'!F:F,'Telemetria Sighra'!I:I,0) -> 2562.77 | T65: =IFERROR((Tabela1[[#This Row],[LITROS CONSUMIDOS]]*$U$1)/Tabela1[[#This Row],[HODÔMETRO]],"-") -> 3.9791785
A66: DAF/XF FTT 530 | B66: 2021 | C66: RHH5C90 | D66: SANTOS X PAULINIA | E66: =IFERROR(_xlfn.XLOOKUP(Tabela1[[#This Row],[PLACA]],'Telemetria Sighra'!F:F,'Telemetria Sighra'!T:T),"NÃO EMBARCADO") -> ANTONIO HENRIQUE DE SOUZA - 50102 | F66: {=SUMPRODUCT((ISNUMBER(FIND(C66,Faturamento!$F$2:$F$1014)))*(Faturamento!$AA$2:$AA$1014))} -> 2621 | G66: =Tabela1[[#This Row],[HODÔMETRO]]-Tabela1[[#This Row],[KM CARREGADO]] -> 717.39 | H66: =_xlfn.XLOOKUP(C66,'Telemetria Sighra'!F:F,'Telemetria Sighra'!R:R,0) -> 3338.39 | I66: =SUMIF(Faturamento!AC:AC,C66,Faturamento!T:T) -> 53683.77 | J66: {=SUMPRODUCT((ISNUMBER(FIND(C66,Faturamento!$F$2:$F$1014)))*(Faturamento!$R$2:$R$1014))} -> 238988 | K66: =$AH$2/30*$AA$1 -> 9479.7957 | L66: 4.4694 | M66: 39990 | N66: =Tabela1[[#This Row],[RESULTADO]]/Tabela1[[#This Row],[EBITDA ESTIMADO]] -> 0.73226742 | O66: =Tabela1[[#This Row],[FATURAMENTO]]-Tabela1[[#This Row],[CUSTO FIXO (SEM DEPREC.)]]-(Tabela1[[#This Row],[CUSTO VARIÁVEL]]*Tabela1[[#This Row],[HODÔMETRO]])+IF(COUNTIFS('ROTAS REALIZADAS'!A:A,Tabela1[[#This Row],[PLACA]],'ROTAS REALIZADAS'!A:A,"SANTOS/PAULINIA")>0,$AA$1*1233.33,0) -> 29283.374 | P66: =IFERROR(Tabela1[[#This Row],[RESULTADO]]/Tabela1[[#This Row],[FATURAMENTO]],"-") -> 0.54547909 | Q66: =IFERROR(I66/H66,"-") -> 16.080737 | R66: =_xlfn.XLOOKUP(C66,'Telemetria Sighra'!F:F,'Telemetria Sighra'!S:S,0) -> 1.5166982 | S66: =_xlfn.XLOOKUP(Tabela1[[#This Row],[PLACA]],'Telemetria Sighra'!F:F,'Telemetria Sighra'!I:I,0) -> 2200.84 | T66: =IFERROR((Tabela1[[#This Row],[LITROS CONSUMIDOS]]*$U$1)/Tabela1[[#This Row],[HODÔMETRO]],"-") -> 3.9555115
H67: =SUBTOTAL(109,Tabela1[HODÔMETRO]) -> 151718.5 | I67: =SUBTOTAL(109,Tabela1[FATURAMENTO]) -> 1464867 | M67: =SUBTOTAL(109,Tabela1[EBITDA ESTIMADO]) -> 3134411 | N67: =SUBTOTAL(101,Tabela1[EBITDA ATINGIDO]) -> 0.062139065 | O67: =SUBTOTAL(109,Tabela1[RESULTADO]) -> 202319.24 | Q67: =SUBTOTAL(101,Tabela1[FATURAMENTO POR KM]) -> 9.3803231 | R67: =SUBTOTAL(101,Tabela1[MÉDIA KM/L]) -> 1.6701987 | S67: =SUBTOTAL(109,Tabela1[LITROS CONSUMIDOS]) -> 90594.95

Sheet ROTAS REALIZADAS
A3: Rótulos de Linha | B3: Contagem de ROTA | C3: Soma de VALOR TOTAL
A4: PARANAGUA/LAPA | B4: 44 | C4: 176375.67
A5: 0 | B5: 5 | C5: 20762.39
A6: AWZ2403 | B6: 8 | C6: 32145.51
A7: BBL9D24 | B7: 4 | C7: 13589.06
A8: BBM5I48 | B8: 6 | C8: 23624.8
A9: BBM8G62 | B9: 2 | C9: 7963.76
A10: BDF9C15 | B10: 11 | C10: 42980.98
A11: BDQ4E29 | B11: 2 | C11: 8906.55
A12: BDQ4E39 | B12: 6 | C12: 26402.62
A13: SANTOS/PAULINIA | B13: 53 | C13: 159841
A14: BAX9A94 | B14: 3 | C14: 7079.88
A15: BBM5I45 | B15: 2 | C15: 4720.25
A16: BDQ4E29 | B16: 4 | C16: 12600.12
A17: BDQ4E30 | B17: 3 | C17: 7080.2
... A39: PARANAGUA/MUITOS CAPOES | B39: 10 | C39: 103769.32
A40: 0 | B40: 3 | C40: 31187.69
A41: BDQ4E19 | B41: 1 | C41: 10466.42
A42: BDQ4E53 | B42: 1 | C42: 10311.18
A43: SFC5F71 | B43: 1 | C43: 10367.3
A44: SFF3I82 | B44: 1 | C44: 10272.7
A45: SFF3I83 | B45: 1 | C45: 10394.6
A46: TAW8B80 | B46: 1 | C46: 10384.93
A47: TAW8B84 | B47: 1 | C47: 10384.5
A48: PARANAGUA/IJUI | B48: 7 | C48: 71993.83
A49: BBL9D24 | B49: 1 | C49: 7405.44
A50: BDQ4E23 | B50: 1 | C50: 10783.36
A51: BDQ4E32 | B51: 1 | C51: 10808
A52: SEE0I38 | B52: 1 | C52: 10765.44
... A56: LAPA/PARANAGUA | B56: 19 | C56: 50350
A57: 0 | B57: 7 | C57: 18550
A58: BEZ9A98 | B58: 4 | C58: 10600
A59: RHG5D75 | B59: 4 | C59: 10600
A60: SEE0I16 | B60: 4 | C60: 10600
A61: MUITOS CAPOES/ARAUCARIA | B61: 5 | C61: 41018.19
A62: BDQ4E19 | B62: 1 | C62: 7986.58
A63: RHH5C95 | B63: 1 | C63: 7996.1
A64: RHI3D46 | B64: 1 | C64: 8338.13
A65: SFF3I82 | B65: 1 | C65: 8344.56
A66: TAW8B84 | B66: 1 | C66: 8352.82
A67: JOACABA/CUBATAO | B67: 2 | C67: 40953.81
A68: SEY8B40 | B68: 1 | C68: 19961.53
A69: TAW8B87 | B69: 1 | C69: 20992.28
... A81: JOACABA/PAULINIA | B81: 2 | C81: 36703.6
A82: 0 | B82: 2 | C82: 36703.6
A83: COLORADO/CANOAS | B83: 2 | C83: 33765.8
A84: SFA7G28 | B84: 1 | C84: 16884.32
A85: TAW8B89 | B85: 1 | C85: 16881.48
A86: IJUI/PAULINIA | B86: 2 | C86: 31836.28
A87: SEE2J87 | B87: 1 | C87: 16056.6
A88: SEY8B43 | B88: 1 | C88: 15779.68
A89: NOVA INDEPENDENCIA/ARAUCARIA | B89: 3 | C89: 30014.53
A90: SEE0I38 | B90: 1 | C90: 9979.25
A91: SEY8B40 | B91: 1 | C91: 10017.64
A92: TAW8B87 | B92: 1 | C92: 10017.64
A93: PARANAGUA/LONDRINA | B93: 1 | C93: 14857.98
A94: SEE3G48 | B94: 1 | C94: 14857.98
... A101: PARANACITY/ITAJAI | B101: 1 | C101: 10246.16
A102: 0 | B102: 1 | C102: 10246.16
A103: PARANAGUA/ORTIGUEIRA | B103: 1 | C103: 9142.05
A104: BBM8G62 | B104: 1 | C104: 9142.05
A105: SANTOS/CIANORTE | B105: 1 | C105: 8500.1
A106: RHH5C92 | B106: 1 | C106: 8500.1
A107: IACANGA/ARAUCARIA | B107: 1 | C107: 8338.09
A108: SEE0H97 | B108: 1 | C108: 8338.09
A109: CAMARGO/ITAJAI | B109: 1 | C109: 8105.6
A110: SEE3G48 | B110: 1 | C110: 8105.6
A111: CT-e COMPLEMENTAR | B111: 12 | C111: 5822.45
A112: BDQ4E19 | B112: 1 | C112: 222.3
A113: BDQ4E39 | B113: 1 | C113: 215.98
A114: RHH5C95 | B114: 1 | C114: 172.54
... A122: Total Geral | B122: 184 | C122: 1046044.6

Sheet Faturamento
A1: CHAVE CTe | B1: FILIAL EMITENTE | C1: DATA | D1: CTe | E1: NFs | F1: PLACAS | G1: MOTORISTA | H1: ORIGEM | I1: UF ORIGEM | J1: DESTINO | K1: UF DESTINO | L1: TOMADOR | M1: REMETENTE | N1: EXPEDIDOR | O1: DESTINATÁRIO | P1: RECEBEDOR | Q1: PRODUTO | R1: QUANTIDADE | S1: PESO | T1: VALOR TOTAL | U1: FRETE PESO | V1: PEDÁGIO | W1: ICMS | X1: ALÍQUOTA ICMS | Y1: BASE CÁLCULO | Z1: ROTA | AA1: KM ROTA | AB1: EMPRESA | AC1: CAVALO
A2: 35260425102812000500570030000002211294583682 | B2: BWT TRANSPORTE E LOGISTICA S. A - PAULINIA | C2: 01/04/2026 | D2: 221 | E2: 117247 | F2: SEE0I38 - JBW6D87 - JBW6D88 | G2: FELIPE NUNES | H2: NOVA INDEPENDENCIA | I2: SP | J2: ARAUCARIA | K2: PR | L2: IPIRANGA PRODUTOS DE PETROLEO S/A | M2: Cooperativa Prod de Cana-de-AA A ca A A car e | N2: Cooperativa Prod de Cana-de-AA A ca A A car e | O2: IPIRANGA PRODUTOS DE PETROLEO S/A | P2: IPIRANGA PRODUTOS DE PETROLEO S/A | Q2: Etanol Anidro | R2: 59280 | S2: 46760 | T2: 9979.25 | U2: 8781.74 | V2: 0 | W2: 1197.51 | X2: 0.12 | Y2: 9979.25 | Z2: =IF(H2&J2="","CT-e COMPLEMENTAR",H2&"/"&J2) -> NOVA INDEPENDENCIA/ARAUCARIA | AA2: =IFERROR(_xlfn.XLOOKUP(Z2,Rotas!C:C,Rotas!D:D),"0") -> 689 | AB2: =IF(AC2=0,"SUBCONTRATADO","BWT") -> BWT | AC2: {=IFERROR( INDEX( _xlfn._xlws.FILTER( BWT!$C$1:$C$100, ISNUMBER(FIND( SUBSTITUTE(BWT!$C$1:$C$100," ",""), SUBSTITUTE(SUBSTITUTE(SUBSTITUTE(F2," ",""),"-",""),CHAR(160),"") )) ), 1 ), "")} -> SEE0I38
A3: 41260425102812000179570030000007811071870131 | B3: BWT ARAUCARIA - ARAUCARIA | C3: 01/04/2026 | D3: 781 | E3: 1094443 | F3: BDU5F20 - BDU5F25 - SEY8B43 | G3: JOAQUIM RAIMUNDO PORTES JUNIOR | H3: PARANAGUA | I3: PR | J3: IJUI | K3: RS | L3: CAMERA AGROALIMENTOS S A | M3: CATTALINI TERMINAIS MARITIMOS S/A | N3: CATTALINI TERMINAIS MARITIMOS S/A | O3: CAMERA AGROALIMENTOS S A | P3: CAMERA AGROALIMENTOS S A | Q3: METANOL - ONU 1230 | R3: 47654 | S3: 73774 | T3: 10674.5 | U3: 9106.06 | V3: 326.7 | W3: 1241.74 | X3: 0.12 | Y3: 10347.8 | Z3: =IF(H3&J3="","CT-e COMPLEMENTAR",H3&"/"&J3) -> PARANAGUA/IJUI | AA3: =IFERROR(_xlfn.XLOOKUP(Z3,Rotas!C:C,Rotas!D:D),"0") -> 800 | AB3: =IF(AC3=0,"SUBCONTRATADO","BWT") -> BWT | AC3: {=IFERROR( INDEX( _xlfn._xlws.FILTER( BWT!$C$1:$C$100, ISNUMBER(FIND( SUBSTITUTE(BWT!$C$1:$C$100," ",""), SUBSTITUTE(SUBSTITUTE(SUBSTITUTE(F3," ",""),"-",""),CHAR(160),"") )) ), 1 ), "")} -> SEY8B43
A4: 41260425102812000179570030000007821994434323 | B4: BWT ARAUCARIA - ARAUCARIA | C4: 01/04/2026 | D4: 782 | E4: 1094454 | F4: BDF9C15 - JCH2G41 | G4: GUSTAVO ANTONIO NOGUEIRA | H4: PARANAGUA | I4: PR | J4: LAPA | K4: PR | L4: POTENCIAL AGRO S/A - MATRIZ | M4: CATTALINI TERMINAIS MARITIMOS S/A | N4: CATTALINI TERMINAIS MARITIMOS S/A | O4: POTENCIAL AGRO S/A - MATRIZ | P4: POTENCIAL AGRO S/A - MATRIZ | Q4: METANOL - ONU 1230 | R4: 37800 | S4: 58260 | T4: 3882.06 | U4: 3882.06 | V4: 0 | W4: 0 | Z4: =IF(H4&J4="","CT-e COMPLEMENTAR",H4&"/"&J4) -> PARANAGUA/LAPA | AA4: =IFERROR(_xlfn.XLOOKUP(Z4,Rotas!C:C,Rotas!D:D),"0") -> 153 | AB4: =IF(AC4=0,"SUBCONTRATADO","BWT") -> BWT | AC4: {=IFERROR( INDEX( _xlfn._xlws.FILTER( BWT!$C$1:$C$100, ISNUMBER(FIND( SUBSTITUTE(BWT!$C$1:$C$100," ",""), SUBSTITUTE(SUBSTITUTE(SUBSTITUTE(F4," ",""),"-",""),CHAR(160),"") )) ), 1 ), "")} -> BDF9C15
A5: 41260425102812000179570030000007831986410787 | B5: BWT ARAUCARIA - ARAUCARIA | C5: 01/04/2026 | D5: 783 | E5: 1094464 | F5: BDQ4E29 - IZW8A03 - IZW8A02 | G5: LUIZ CARLOS COELHO | H5: PARANAGUA | I5: PR | J5: LAPA | K5: PR | L5: POTENCIAL AGRO S/A - MATRIZ | M5: CATTALINI TERMINAIS MARITIMOS S/A | N5: CATTALINI TERMINAIS MARITIMOS S/A | O5: POTENCIAL AGRO S/A - MATRIZ | P5: POTENCIAL AGRO S/A - MATRIZ | Q5: METANOL - ONU 1230 | R5: 48480 | S5: 73760 | T5: 4443.19 | U5: 4443.19 | V5: 0 | W5: 0 | Z5: =IF(H5&J5="","CT-e COMPLEMENTAR",H5&"/"&J5) -> PARANAGUA/LAPA | AA5: =IFERROR(_xlfn.XLOOKUP(Z5,Rotas!C:C,Rotas!D:D),"0") -> 153 | AB5: =IF(AC5=0,"SUBCONTRATADO","BWT") -> BWT | AC5: {=IFERROR( INDEX( _xlfn._xlws.FILTER( BWT!$C$1:$C$100, ISNUMBER(FIND( SUBSTITUTE(BWT!$C$1:$C$100," ",""), SUBSTITUTE(SUBSTITUTE(SUBSTITUTE(F5," ",""),"-",""),CHAR(160),"") )) ), 1 ), "")} -> BDQ4E29
A6: 41260425102812000179570030000007861155759734 | B6: BWT ARAUCARIA - ARAUCARIA | C6: 01/04/2026 | D6: 786 | E6: 1160372 - 1160373 | F6: JCV2H63 - TAW8B89 - JCV2H01 | G6: AMAURI DOS SANTOS PEREIRA | H6: COLORADO | I6: PR | J6: CANOAS | K6: RS | L6: IPIRANGA PRODUTOS DE PETROLEO S/A | M6: USINA ALTO ALEGRE S.A - ACUCAR E AL | N6: USINA ALTO ALEGRE S.A - ACUCAR E AL | O6: IPIRANGA PRODUTOS DE PETROLEO S/A | P6: IPIRANGA PRODUTOS DE PETROLEO S/A | Q6: Etanol Anidro | R6: 59468 | S6: 47120 | T6: 16881.48 | U6: 14855.7 | V6: 0 | W6: 2025.78 | X6: 0.12 | Y6: 16881.48 | Z6: =IF(H6&J6="","CT-e COMPLEMENTAR",H6&"/"&J6) -> COLORADO/CANOAS | AA6: =IFERROR(_xlfn.XLOOKUP(Z6,Rotas!C:C,Rotas!D:D),"0") -> 1123 | AB6: =IF(AC6=0,"SUBCONTRATADO","BWT") -> BWT | AC6: {=IFERROR( INDEX( _xlfn._xlws.FILTER( BWT!$C$1:$C$100, ISNUMBER(FIND( SUBSTITUTE(BWT!$C$1:$C$100," ",""), SUBSTITUTE(SUBSTITUTE(SUBSTITUTE(F6," ",""),"-",""),CHAR(160),"") )) ), 1 ), "")} -> TAW8B89
A7: 41260425102812000179570030000007871097679700 | B7: BWT ARAUCARIA - ARAUCARIA | C7: 01/04/2026 | D7: 787 | E7: 1160384 | F7: JAS1A99 - JAS0J82 - SFA7G28 | G7: EDUARDO RAFAEL BORGES | H7: COLORADO | I7: PR | J7: CANOAS | K7: RS | L7: IPIRANGA PRODUTOS DE PETROLEO S/A | M7: USINA ALTO ALEGRE S.A - ACUCAR E AL | N7: USINA ALTO ALEGRE S.A - ACUCAR E AL | O7: IPIRANGA PRODUTOS DE PETROLEO S/A | P7: IPIRANGA PRODUTOS DE PETROLEO S/A | Q7: Etanol Anidro | R7: 59478 | S7: 47000 | T7: 16884.32 | U7: 14858.2 | V7: 0 | W7: 2026.12 | X7: 0.12 | Y7: 16884.32 | Z7: =IF(H7&J7="","CT-e COMPLEMENTAR",H7&"/"&J7) -> COLORADO/CANOAS | AA7: =IFERROR(_xlfn.XLOOKUP(Z7,Rotas!C:C,Rotas!D:D),"0") -> 1123 | AB7: =IF(AC7=0,"SUBCONTRATADO","BWT") -> BWT | AC7: {=IFERROR( INDEX( _xlfn._xlws.FILTER( BWT!$C$1:$C$100, ISNUMBER(FIND( SUBSTITUTE(BWT!$C$1:$C$100," ",""), SUBSTITUTE(SUBSTITUTE(SUBSTITUTE(F7," ",""),"-",""),CHAR(160),"") )) ), 1 ), "")} -> SFA7G28
A8: 41260425102812000179570030000007881910591310 | B8: BWT ARAUCARIA - ARAUCARIA | C8: 01/04/2026 | D8: 788 | E8: 1094523 | F8: SFF3I76 - JCP3I14 - JCP5G54 | G8: JOSIANE DE FREITAS CABRAL | H8: PARANAGUA | I8: PR | J8: LAPA | K8: PR | L8: POTENCIAL AGRO S/A - MATRIZ | M8: CATTALINI TERMINAIS MARITIMOS S/A | N8: CATTALINI TERMINAIS MARITIMOS S/A | O8: POTENCIAL AGRO S/A - MATRIZ | P8: POTENCIAL AGRO S/A - MATRIZ | Q8: METANOL - ONU 1230 | R8: 47500 | S8: 73680 | T8: 4353.38 | U8: 4353.38 | V8: 0 | W8: 0 | Z8: =IF(H8&J8="","CT-e COMPLEMENTAR",H8&"/"&J8) -> PARANAGUA/LAPA | AA8: =IFERROR(_xlfn.XLOOKUP(Z8,Rotas!C:C,Rotas!D:D),"0") -> 153 | AB8: =IF(AC8=0,"SUBCONTRATADO","BWT") -> SUBCONTRATADO | AC8: {=IFERROR( INDEX( _xlfn._xlws.FILTER( BWT!$C$1:$C$100, ISNUMBER(FIND( SUBSTITUTE(BWT!$C$1:$C$100," ",""), SUBSTITUTE(SUBSTITUTE(SUBSTITUTE(F8," ",""),"-",""),CHAR(160),"") )) ), 1 ), "")} -> 0
A9: 41260425102812000179570030000007891751295078 | B9: BWT ARAUCARIA - ARAUCARIA | C9: 01/04/2026 | D9: 789 | E9: 1094543 | F9: SED7C99 - RYD5E39 - RYD5E29 | G9: WESLEY MILHOMEM DE SOUSA | H9: PARANAGUA | I9: PR | J9: LAPA | K9: PR | L9: POTENCIAL AGRO S/A - MATRIZ | M9: CATTALINI TERMINAIS MARITIMOS S/A | N9: CATTALINI TERMINAIS MARITIMOS S/A | O9: POTENCIAL AGRO S/A - MATRIZ | P9: POTENCIAL AGRO S/A - MATRIZ | Q9: METANOL - ONU 1230 | R9: 48560 | S9: 73900 | T9: 4450.52 | U9: 4450.52 | V9: 0 | W9: 0 | Z9: =IF(H9&J9="","CT-e COMPLEMENTAR",H9&"/"&J9) -> PARANAGUA/LAPA | AA9: =IFERROR(_xlfn.XLOOKUP(Z9,Rotas!C:C,Rotas!D:D),"0") -> 153 | AB9: =IF(AC9=0,"SUBCONTRATADO","BWT") -> SUBCONTRATADO | AC9: {=IFERROR( INDEX( _xlfn._xlws.FILTER( BWT!$C$1:$C$100, ISNUMBER(FIND( SUBSTITUTE(BWT!$C$1:$C$100," ",""), SUBSTITUTE(SUBSTITUTE(SUBSTITUTE(F9," ",""),"-",""),CHAR(160),"") )) ), 1 ), "")} -> 0
A10: 41260425102812000179570030000007901039058957 | B10: BWT ARAUCARIA - ARAUCARIA | C10: 01/04/2026 | D10: 790 | E10: 1094592 | F10: BBQ6I94 - BBM8G62 | G10: LUIZ GERVASIO STROPARO | H10: PARANAGUA | I10: PR | J10: LAPA | K10: PR | L10: POTENCIAL AGRO S/A - MATRIZ | M10: CATTALINI TERMINAIS MARITIMOS S/A | N10: CATTALINI TERMINAIS MARITIMOS S/A | O10: POTENCIAL AGRO S/A - MATRIZ | P10: POTENCIAL AGRO S/A - MATRIZ | Q10: METANOL - ONU 1230 | R10: 38720 | S10: 58360 | T10: 3976.54 | U10: 3976.54 | V10: 0 | W10: 0 | Z10: =IF(H10&J10="","CT-e COMPLEMENTAR",H10&"/"&J10) -> PARANAGUA/LAPA | AA10: =IFERROR(_xlfn.XLOOKUP(Z10,Rotas!C:C,Rotas!D:D),"0") -> 153 | AB10: =IF(AC10=0,"SUBCONTRATADO","BWT") -> BWT | AC10: {=IFERROR( INDEX( _xlfn._xlws.FILTER( BWT!$C$1:$C$100, ISNUMBER(FIND( SUBSTITUTE(BWT!$C$1:$C$100," ",""), SUBSTITUTE(SUBSTITUTE(SUBSTITUTE(F10," ",""),"-",""),CHAR(160),"") )) ), 1 ), "")} -> BBM8G62
A11: 41260425102812000179570030000007911314509389 | B11: BWT ARAUCARIA - ARAUCARIA | C11: 01/04/2026 | D11: 791 | E11: 1094646 | F11: JCI5E48 - AWZ2403 | G11: JOAO GABRIEL DA CRUZ | H11: PARANAGUA | I11: PR | J11: LAPA | K11: PR | L11: POTENCIAL AGRO S/A - MATRIZ | M11: CATTALINI TERMINAIS MARITIMOS S/A | N11: CATTALINI TERMINAIS MARITIMOS S/A | O11: POTENCIAL AGRO S/A - MATRIZ | P11: POTENCIAL AGRO S/A - MATRIZ | Q11: METANOL - ONU 1230 | R11: 39020 | S11: 58300 | T11: 4007.35 | U11: 4007.35 | V11: 0 | W11: 0 | Z11: =IF(H11&J11="","CT-e COMPLEMENTAR",H11&"/"&J11) -> PARANAGUA/LAPA | AA11: =IFERROR(_xlfn.XLOOKUP(Z11,Rotas!C:C,Rotas!D:D),"0") -> 153 | AB11: =IF(AC11=0,"SUBCONTRATADO","BWT") -> BWT | AC11: {=IFERROR( INDEX( _xlfn._xlws.FILTER( BWT!$C$1:$C$100, ISNUMBER(FIND( SUBSTITUTE(BWT!$C$1:$C$100," ",""), SUBSTITUTE(SUBSTITUTE(SUBSTITUTE(F11," ",""),"-",""),CHAR(160),"") )) ), 1 ), "")} -> AWZ2403
A12: 43260425102812000250570030000002421011066038 | B12: BWT TRANSPORTE E LOGISTICA S. A - ESTEIO | C12: 01/04/2026 | D12: 242 | E12: 86696 | F12: SEE3G48 - JBT6B10 - JBT6B27 | G12: RAFAEL SOUZA MIRANDA | H12: CAMARGO | I12: RS | J12: ITAJAI | K12: SC | L12: IPIRANGA PRODUTOS DE PETROLEO S.A | M12: FUGA S.A | N12: FUGA S.A | O12: IPIRANGA PRODUTOS DE PETROLEO S.A | P12: IPIRANGA PRODUTOS DE PETROLEO S.A | Q12: Biodiesel - B100 | R12: 59610 | S12: 52060 | T12: 8105.6 | U12: 7132.93 | V12: 0 | W12: 972.67 | X12: 0.12 | Y12: 8105.6 | Z12: =IF(H12&J12="","CT-e COMPLEMENTAR",H12&"/"&J12) -> CAMARGO/ITAJAI | AA12: =IFERROR(_xlfn.XLOOKUP(Z12,Rotas!C:C,Rotas!D:D),"0") -> 560 | AB12: =IF(AC12=0,"SUBCONTRATADO","BWT") -> BWT | AC12: {=IFERROR( INDEX( _xlfn._xlws.FILTER( BWT!$C$1:$C$100, ISNUMBER(FIND( SUBSTITUTE(BWT!$C$1:$C$100," ",""), SUBSTITUTE(SUBSTITUTE(SUBSTITUTE(F12," ",""),"-",""),CHAR(160),"") )) ), 1 ), "")} -> SEE3G48
A13: 35260425102812000500570030000002221953168362 | B13: BWT TRANSPORTE E LOGISTICA S. A - PAULINIA | C13: 02/04/2026 | D13: 222 | E13: 30130 | F13: TAW8C01 - RYF3A30 - RYF2J90 | G13: ROBERTO RIVELINO CABRAL | H13: SANTOS | I13: SP | J13: PAULINIA | K13: SP | L13: IPIRANGA PRODUTOS DE PETROLEO S.A. | M13: ULTRACARGO LOGISTICA S.A | N13: IPIRANGA PRODUTOS DE PETROLEO S.A. | O13: IPIRANGA PRODUTOS DE PETROLEO S/A | P13: IPIRANGA PRODUTOS DE PETROLEO S/A | Q13: Gasolina A | R13: 63536 | S13: 44469 | T13: 3150.09 | U13: 2772.08 | V13: 0 | W13: 378.01 | X13: 0.12 | Y13: 3150.09 | Z13: =IF(H13&J13="","CT-e COMPLEMENTAR",H13&"/"&J13) -> SANTOS/PAULINIA | AA13: =IFERROR(_xlfn.XLOOKUP(Z13,Rotas!C:C,Rotas!D:D),"0") -> 215 | AB13: =IF(AC13=0,"SUBCONTRATADO","BWT") -> BWT | AC13: {=IFERROR( INDEX( _xlfn._xlws.FILTER( BWT!$C$1:$C$100, ISNUMBER(FIND( SUBSTITUTE(BWT!$C$1:$C$100," ",""), SUBSTITUTE(SUBSTITUTE(SUBSTITUTE(F13," ",""),"-",""),CHAR(160),"") )) ), 1 ), "")} -> TAW8C01
A14: 35260425102812000500570030000002241867421432 | B14: BWT TRANSPORTE E LOGISTICA S. A - PAULINIA | C14: 02/04/2026 | D14: 224 | E14: 30141 | F14: JBT9E33 - SEE2J92 - JBT9E30 | G14: SILAS DE LIMA | H14: SANTOS | I14: SP | J14: PAULINIA | K14: SP | L14: IPIRANGA PRODUTOS DE PETROLEO S.A. | M14: IPIRANGA PRODUTOS DE PETROLEO S.A. | N14: ULTRACARGO LOGISTICA S.A | O14: IPIRANGA PRODUTOS DE PETROLEO S/A | P14: IPIRANGA PRODUTOS DE PETROLEO S/A | Q14: Gasolina A | R14: 63294 | S14: 44299 | T14: 3150.32 | U14: 2772.28 | V14: 0 | W14: 378.04 | X14: 0.12 | Y14: 3150.32 | Z14: =IF(H14&J14="","CT-e COMPLEMENTAR",H14&"/"&J14) -> SANTOS/PAULINIA | AA14: =IFERROR(_xlfn.XLOOKUP(Z14,Rotas!C:C,Rotas!D:D),"0") -> 215 | AB14: =IF(AC14=0,"SUBCONTRATADO","BWT") -> BWT | AC14: {=IFERROR( INDEX( _xlfn._xlws.FILTER( BWT!$C$1:$C$100, ISNUMBER(FIND( SUBSTITUTE(BWT!$C$1:$C$100," ",""), SUBSTITUTE(SUBSTITUTE(SUBSTITUTE(F14," ",""),"-",""),CHAR(160),"") )) ), 1 ), "")} -> SEE2J92
A15: 35260425102812000500570030000002251350531823 | B15: BWT TRANSPORTE E LOGISTICA S. A - PAULINIA | C15: 02/04/2026 | D15: 225 | E15: 30161 | F15: JCW7D75 - TAW8C09 - JCX7F40 | G15: CLAIR SONAI | H15: SANTOS | I15: SP | J15: PAULINIA | K15: SP | L15: IPIRANGA PRODUTOS DE PETROLEO S.A. | M15: IPIRANGA PRODUTOS DE PETROLEO S.A. | N15: ULTRACARGO LOGISTICA S.A | O15: IPIRANGA PRODUTOS DE PETROLEO S/A | P15: IPIRANGA PRODUTOS DE PETROLEO S/A | Q15: Gasolina A | R15: 63081 | S15: 44150 | T15: 3149.75 | U15: 2771.78 | V15: 0 | W15: 377.97 | X15: 0.12 | Y15: 3149.75 | Z15: =IF(H15&J15="","CT-e COMPLEMENTAR",H15&"/"&J15) -> SANTOS/PAULINIA | AA15: =IFERROR(_xlfn.XLOOKUP(Z15,Rotas!C:C,Rotas!D:D),"0") -> 215 | AB15: =IF(AC15=0,"SUBCONTRATADO","BWT") -> BWT | AC15: {=IFERROR( INDEX( _xlfn._xlws.FILTER( BWT!$C$1:$C$100, ISNUMBER(FIND( SUBSTITUTE(BWT!$C$1:$C$100," ",""), SUBSTITUTE(SUBSTITUTE(SUBSTITUTE(F15," ",""),"-",""),CHAR(160),"") )) ), 1 ), "")} -> TAW8C09
A16: 35260425102812000500570030000002271876374885 | B16: BWT TRANSPORTE E LOGISTICA S. A - PAULINIA | C16: 02/04/2026 | D16: 227 | E16: 30177 | F16: AYP3139 - SEX2C73 - AYP3138 | G16: MARIOVANY QUIRINO GOMES | H16: SANTOS | I16: SP | J16: PAULINIA | K16: SP | L16: IPIRANGA PRODUTOS DE PETROLEO S.A. | M16: ULTRACARGO LOGISTICA S.A | N16: IPIRANGA PRODUTOS DE PETROLEO S.A. | O16: IPIRANGA PRODUTOS DE PETROLEO S/A | P16: IPIRANGA PRODUTOS DE PETROLEO S/A | Q16: Gasolina A | R16: 63102 | S16: 44165 | T16: 3150.08 | U16: 2772.07 | V16: 0 | W16: 378.01 | X16: 0.12 | Y16: 3150.08 | Z16: =IF(H16&J16="","CT-e COMPLEMENTAR",H16&"/"&J16) -> SANTOS/PAULINIA | AA16: =IFERROR(_xlfn.XLOOKUP(Z16,Rotas!C:C,Rotas!D:D),"0") -> 215 | AB16: =IF(AC16=0,"SUBCONTRATADO","BWT") -> BWT | AC16: {=IFERROR( INDEX( _xlfn._xlws.FILTER( BWT!$C$1:$C$100, ISNUMBER(FIND( SUBSTITUTE(BWT!$C$1:$C$100," ",""), SUBSTITUTE(SUBSTITUTE(SUBSTITUTE(F16," ",""),"-",""),CHAR(160),"") )) ), 1 ), "")} -> SEX2C73
A17: 35260425102812000500570030000002281305142289 | B17: BWT TRANSPORTE E LOGISTICA S. A - PAULINIA | C17: 02/04/2026 | D17: 228 | E17: 30197 | F17: SEE0I13 - RYG6E81 - RYG6F31 | G17: ALAOR BATISTA DE FREITAS | H17: SANTOS | I17: SP | J17: PAULINIA | K17: SP | L17: IPIRANGA PRODUTOS DE PETROLEO S.A. | M17: ULTRACARGO LOGISTICA S.A | N17: IPIRANGA PRODUTOS DE PETROLEO S.A. | O17: IPIRANGA PRODUTOS DE PETROLEO S/A | P17: IPIRANGA PRODUTOS DE PETROLEO S/A | Q17: Gasolina A | R17: 63218 | S17: 45700 | T17: 3150.12 | U17: 2772.11 | V17: 0 | W17: 378.01 | X17: 0.12 | Y17: 3150.12 | Z17: =IF(H17&J17="","CT-e COMPLEMENTAR",H17&"/"&J17) -> SANTOS/PAULINIA | AA17: =IFERROR(_xlfn.XLOOKUP(Z17,Rotas!C:C,Rotas!D:D),"0") -> 215 | AB17: =IF(AC17=0,"SUBCONTRATADO","BWT") -> BWT | AC17: {=IFERROR( INDEX( _xlfn._xlws.FILTER( BWT!$C$1:$C$100, ISNUMBER(FIND( SUBSTITUTE(BWT!$C$1:$C$100," ",""), SUBSTITUTE(SUBSTITUTE(SUBSTITUTE(F17," ",""),"-",""),CHAR(160),"") )) ), 1 ), "")} -> SEE0I13
A18: 35260425102812000500570030000002291341401032 | B18: BWT TRANSPORTE E LOGISTICA S. A - PAULINIA | C18: 02/04/2026 | D18: 229 | E18: 30198 | F18: JBT6B33 - BDQ4E30 | G18: NEY CESAR WANDERLINDE LEINEKER | H18: SANTOS | I18: SP | J18: PAULINIA | K18: SP | L18: IPIRANGA PRODUTOS DE PETROLEO S.A. | M18: ULTRACARGO LOGISTICA S.A | N18: IPIRANGA PRODUTOS DE PETROLEO S.A. | O18: IPIRANGA PRODUTOS DE PETROLEO S/A | P18: IPIRANGA PRODUTOS DE PETROLEO S/A | Q18: Gasolina A | R18: 49711 | S18: 35911 | T18: 2360.15 | U18: 2076.93 | V18: 0 | W18: 283.22 | X18: 0.12 | Y18: 2360.15 | Z18: =IF(H18&J18="","CT-e COMPLEMENTAR",H18&"/"&J18) -> SANTOS/PAULINIA | AA18: =IFERROR(_xlfn.XLOOKUP(Z18,Rotas!C:C,Rotas!D:D),"0") -> 215 | AB18: =IF(AC18=0,"SUBCONTRATADO","BWT") -> BWT | AC18: {=IFERROR( INDEX( _xlfn._xlws.FILTER( BWT!$C$1:$C$100, ISNUMBER(FIND( SUBSTITUTE(BWT!$C$1:$C$100," ",""), SUBSTITUTE(SUBSTITUTE(SUBSTITUTE(F18," ",""),"-",""),CHAR(160),"") )) ), 1 ), "")} -> BDQ4E30
A19: 35260425102812000500570030000002301974589547 | B19: BWT TRANSPORTE E LOGISTICA S. A - PAULINIA | C19: 02/04/2026 | D19: 230 | E19: 30203 | F19: BBM5I45 - BBQ6I95 | G19: VLADEMIR JORGE SANTOS | H19: SANTOS | I19: SP | J19: PAULINIA | K19: SP | L19: IPIRANGA PRODUTOS DE PETROLEO S.A. | M19: ULTRACARGO LOGISTICA S.A | N19: IPIRANGA PRODUTOS DE PETROLEO S.A. | O19: IPIRANGA PRODUTOS DE PETROLEO S/A | P19: IPIRANGA PRODUTOS DE PETROLEO S/A | Q19: Gasolina A | R19: 42448 | S19: 30686 | T19: 2360.2 | U19: 2076.98 | V19: 0 | W19: 283.22 | X19: 0.12 | Y19: 2360.2 | Z19: =IF(H19&J19="","CT-e COMPLEMENTAR",H19&"/"&J19) -> SANTOS/PAULINIA | AA19: =IFERROR(_xlfn.XLOOKUP(Z19,Rotas!C:C,Rotas!D:D),"0") -> 215 | AB19: =IF(AC19=0,"SUBCONTRATADO","BWT") -> BWT | AC19: {=IFERROR( INDEX( _xlfn._xlws.FILTER( BWT!$C$1:$C$100, ISNUMBER(FIND( SUBSTITUTE(BWT!$C$1:$C$100," ",""), SUBSTITUTE(SUBSTITUTE(SUBSTITUTE(F19," ",""),"-",""),CHAR(160),"") )) ), 1 ), "")} -> BBM5I45
A20: 35260425102812000500570030000002311869894480 | B20: BWT TRANSPORTE E LOGISTICA S. A - PAULINIA | C20: 02/04/2026 | D20: 231 | E20: 30207 | F20: JCI7B71 - BAX9A94 | G20: FRANCISCO ADEMIR MORO JUNIOR | H20: SANTOS | I20: SP | J20: PAULINIA | K20: SP | L20: IPIRANGA PRODUTOS DE PETROLEO S.A. | M20: ULTRACARGO LOGISTICA S.A | N20: IPIRANGA PRODUTOS DE PETROLEO S.A. | O20: IPIRANGA PRODUTOS DE PETROLEO S/A | P20: IPIRANGA PRODUTOS DE PETROLEO S/A | Q20: Gasolina A | R20: 49574 | S20: 35812 | T20: 2359.83 | U20: 2076.65 | V20: 0 | W20: 283.18 | X20: 0.12 | Y20: 2359.83 | Z20: =IF(H20&J20="","CT-e COMPLEMENTAR",H20&"/"&J20) -> SANTOS/PAULINIA | AA20: =IFERROR(_xlfn.XLOOKUP(Z20,Rotas!C:C,Rotas!D:D),"0") -> 215 | AB20: =IF(AC20=0,"SUBCONTRATADO","BWT") -> BWT | AC20: {=IFERROR( INDEX( _xlfn._xlws.FILTER( BWT!$C$1:$C$100, ISNUMBER(FIND( SUBSTITUTE(BWT!$C$1:$C$100," ",""), SUBSTITUTE(SUBSTITUTE(SUBSTITUTE(F20," ",""),"-",""),CHAR(160),"") )) ), 1 ), "")} -> BAX9A94
A21: 41260425102812000179570030000007921843806643 | B21: BWT ARAUCARIA - ARAUCARIA | C21: 02/04/2026 | D21: 792 | E21: 1094764 | F21: BDF9C15 - JCH2G41 | G21: GUSTAVO ANTONIO NOGUEIRA | H21: PARANAGUA | I21: PR | J21: LAPA | K21: PR | L21: POTENCIAL AGRO S/A - MATRIZ | M21: CATTALINI TERMINAIS MARITIMOS S/A | N21: CATTALINI TERMINAIS MARITIMOS S/A | O21: POTENCIAL AGRO S/A - MATRIZ | P21: POTENCIAL AGRO S/A - MATRIZ | Q21: METANOL - ONU 1230 | R21: 37820 | S21: 58140 | T21: 3884.11 | U21: 3884.11 | V21: 0 | W21: 0 | Z21: =IF(H21&J21="","CT-e COMPLEMENTAR",H21&"/"&J21) -> PARANAGUA/LAPA | AA21: =IFERROR(_xlfn.XLOOKUP(Z21,Rotas!C:C,Rotas!D:D),"0") -> 153 | AB21: =IF(AC21=0,"SUBCONTRATADO","BWT") -> BWT | AC21: {=IFERROR( INDEX( _xlfn._xlws.FILTER( BWT!$C$1:$C$100, ISNUMBER(FIND( SUBSTITUTE(BWT!$C$1:$C$100," ",""), SUBSTITUTE(SUBSTITUTE(SUBSTITUTE(F21," ",""),"-",""),CHAR(160),"") )) ), 1 ), "")} -> BDF9C15
A22: 41260425102812000179570030000007931866698844 | B22: BWT ARAUCARIA - ARAUCARIA | C22: 02/04/2026 | D22: 793 | E22: 1066149 | F22: BDQ4E39 | G22: CESAR AUGUSTO DA SILVA | H22: PARANAGUA | I22: PR | J22: ARAUCARIA | K22: PR | L22: IPIRANGA PRODUTOS DE PETROLEO S/A | M22: CATTALINI TERMINAIS MARITIMOS S/A | N22: CATTALINI TERMINAIS MARITIMOS S/A | O22: IPIRANGA PRODUTOS DE PETROLEO S/A | P22: IPIRANGA PRODUTOS DE PETROLEO S/A | Q22: Diesel S10 A | R22: 58548 | S22: 73920 | T22: 355.91 | U22: 355.91 | V22: 0 | W22: 0 | Z22: =IF(H22&J22="","CT-e COMPLEMENTAR",H22&"/"&J22) -> PARANAGUA/ARAUCARIA | AA22: =IFERROR(_xlfn.XLOOKUP(Z22,Rotas!C:C,Rotas!D:D),"0") -> 109 | AB22: =IF(AC22=0,"SUBCONTRATADO","BWT") -> BWT | AC22: {=IFERROR( INDEX( _xlfn._xlws.FILTER( BWT!$C$1:$C$100, ISNUMBER(FIND( SUBSTITUTE(BWT!$C$1:$C$100," ",""), SUBSTITUTE(SUBSTITUTE(SUBSTITUTE(F22," ",""),"-",""),CHAR(160),"") )) ), 1 ), "")} -> BDQ4E39
A23: 41260425102812000179570030000007941740369970 | B23: BWT ARAUCARIA - ARAUCARIA | C23: 02/04/2026 | D23: 794 | E23: 1094904 | F23: BBQ6I94 - BBM8G62 | G23: LUIZ GERVASIO STROPARO | H23: PARANAGUA | I23: PR | J23: LAPA | K23: PR | L23: POTENCIAL AGRO S/A - MATRIZ | M23: CATTALINI TERMINAIS MARITIMOS S/A | N23: CATTALINI TERMINAIS MARITIMOS S/A | O23: POTENCIAL AGRO S/A - MATRIZ | P23: POTENCIAL AGRO S/A - MATRIZ | Q23: METANOL - ONU 1230 | R23: 38824 | S23: 58304 | T23: 3987.22 | U23: 3987.22 | V23: 0 | W23: 0 | Z23: =IF(H23&J23="","CT-e COMPLEMENTAR",H23&"/"&J23) -> PARANAGUA/LAPA | AA23: =IFERROR(_xlfn.XLOOKUP(Z23,Rotas!C:C,Rotas!D:D),"0") -> 153 | AB23: =IF(AC23=0,"SUBCONTRATADO","BWT") -> BWT | AC23: {=IFERROR( INDEX( _xlfn._xlws.FILTER( BWT!$C$1:$C$100, ISNUMBER(FIND( SUBSTITUTE(BWT!$C$1:$C$100," ",""), SUBSTITUTE(SUBSTITUTE(SUBSTITUTE(F23," ",""),"-",""),CHAR(160),"") )) ), 1 ), "")} -> BBM8G62
A24: 41260425102812000179570030000007951681978420 | B24: BWT ARAUCARIA - ARAUCARIA | C24: 02/04/2026 | D24: 795 | E24: 1094907 | F24: JCI5E48 - AWZ2403 | G24: JOAO GABRIEL DA CRUZ | H24: PARANAGUA | I24: PR | J24: LAPA | K24: PR | L24: POTENCIAL AGRO S/A - MATRIZ | M24: CATTALINI TERMINAIS MARITIMOS S/A | N24: CATTALINI TERMINAIS MARITIMOS S/A | O24: POTENCIAL AGRO S/A - MATRIZ | P24: POTENCIAL AGRO S/A - MATRIZ | Q24: METANOL - ONU 1230 | R24: 39040 | S24: 58200 | T24: 4009.41 | U24: 4009.41 | V24: 0 | W24: 0 | Z24: =IF(H24&J24="","CT-e COMPLEMENTAR",H24&"/"&J24) -> PARANAGUA/LAPA | AA24: =IFERROR(_xlfn.XLOOKUP(Z24,Rotas!C:C,Rotas!D:D),"0") -> 153 | AB24: =IF(AC24=0,"SUBCONTRATADO","BWT") -> BWT | AC24: {=IFERROR( INDEX( _xlfn._xlws.FILTER( BWT!$C$1:$C$100, ISNUMBER(FIND( SUBSTITUTE(BWT!$C$1:$C$100," ",""), SUBSTITUTE(SUBSTITUTE(SUBSTITUTE(F24," ",""),"-",""),CHAR(160),"") )) ), 1 ), "")} -> AWZ2403
A25: 41260425102812000179570030000007971561375005 | B25: BWT ARAUCARIA - ARAUCARIA | C25: 02/04/2026 | D25: 797 | E25: 1094918 | F25: BBM5I48 | G25: FERNANDO JOSE CARVALHO | H25: PARANAGUA | I25: PR | J25: LAPA | K25: PR | L25: POTENCIAL AGRO S/A - MATRIZ | M25: CATTALINI TERMINAIS MARITIMOS S/A | N25: CATTALINI TERMINAIS MARITIMOS S/A | O25: POTENCIAL AGRO S/A - MATRIZ | P25: POTENCIAL AGRO S/A - MATRIZ | Q25: METANOL - ONU 1230 | R25: 38357 | S25: 58357 | T25: 3939.26 | U25: 3939.26 | V25: 0 | W25: 0 | Z25: =IF(H25&J25="","CT-e COMPLEMENTAR",H25&"/"&J25) -> PARANAGUA/LAPA | AA25: =IFERROR(_xlfn.XLOOKUP(Z25,Rotas!C:C,Rotas!D:D),"0") -> 153 | AB25: =IF(AC25=0,"SUBCONTRATADO","BWT") -> BWT | AC25: {=IFERROR( INDEX( _xlfn._xlws.FILTER( BWT!$C$1:$C$100, ISNUMBER(FIND( SUBSTITUTE(BWT!$C$1:$C$100," ",""), SUBSTITUTE(SUBSTITUTE(SUBSTITUTE(F25," ",""),"-",""),CHAR(160),"") )) ), 1 ), "")} -> BBM5I48
A26: 41260425102812000179570030000007981828867258 | B26: BWT ARAUCARIA - ARAUCARIA | C26: 02/04/2026 | D26: 798 | E26: 327582 | F26: JCW7C11 - JCW7D87 - TAW2A61 | G26: ALCIONE DE CASTRO | H26: SAO CARLOS DO IVAI | I26: PR | J26: ARAUCARIA | K26: PR | L26: IPIRANGA PRODUTOS DE PETROLEO S/A | M26: COOPERATIVA AGRICOLA REGIONAL DE PR RES DE CAN | N26: COOPERATIVA AGRICOLA REGIONAL DE PR RES DE CAN | O26: IPIRANGA PRODUTOS DE PETROLEO S/A | P26: IPIRANGA PRODUTOS DE PETROLEO S/A | Q26: Etanol Anidro | R26: 59400 | S26: 46900 | T26: 6424.11 | U26: 6424.11 | V26: 0 | W26: 0 | Z26: =IF(H26&J26="","CT-e COMPLEMENTAR",H26&"/"&J26) -> SAO CARLOS DO IVAI/ARAUCARIA | AA26: =IFERROR(_xlfn.XLOOKUP(Z26,Rotas!C:C,Rotas!D:D),"0") -> 491 | AB26: =IF(AC26=0,"SUBCONTRATADO","BWT") -> BWT | AC26: {=IFERROR( INDEX( _xlfn._xlws.FILTER( BWT!$C$1:$C$100, ISNUMBER(FIND( SUBSTITUTE(BWT!$C$1:$C$100," ",""), SUBSTITUTE(SUBSTITUTE(SUBSTITUTE(F26," ",""),"-",""),CHAR(160),"") )) ), 1 ), "")} -> TAW2A61
A27: 41260425102812000179570030000007991523361048 | B27: BWT ARAUCARIA - ARAUCARIA | C27: 02/04/2026 | D27: 799 | E27: 327587 | F27: JAO3A97 - SFC5F71 - JAO3A88 | G27: RENATO GASPARELLO | H27: SAO CARLOS DO IVAI | I27: PR | J27: ARAUCARIA | K27: PR | L27: IPIRANGA PRODUTOS DE PETROLEO S/A | M27: COOPERATIVA AGRICOLA REGIONAL DE PR RES DE CAN | N27: COOPERATIVA AGRICOLA REGIONAL DE PR RES DE CAN | O27: IPIRANGA PRODUTOS DE PETROLEO S/A | P27: IPIRANGA PRODUTOS DE PETROLEO S/A | Q27: Etanol Anidro | R27: 59454 | S27: 46940 | T27: 6429.95 | U27: 6429.95 | V27: 0 | W27: 0 | Z27: =IF(H27&J27="","CT-e COMPLEMENTAR",H27&"/"&J27) -> SAO CARLOS DO IVAI/ARAUCARIA | AA27: =IFERROR(_xlfn.XLOOKUP(Z27,Rotas!C:C,Rotas!D:D),"0") -> 491 | AB27: =IF(AC27=0,"SUBCONTRATADO","BWT") -> BWT | AC27: {=IFERROR( INDEX( _xlfn._xlws.FILTER( BWT!$C$1:$C$100, ISNUMBER(FIND( SUBSTITUTE(BWT!$C$1:$C$100," ",""), SUBSTITUTE(SUBSTITUTE(SUBSTITUTE(F27," ",""),"-",""),CHAR(160),"") )) ), 1 ), "")} -> SFC5F71
A28: 41260425102812000179570030000008001608697825 | B28: BWT ARAUCARIA - ARAUCARIA | C28: 02/04/2026 | D28: 800 | E28: 2694 | F28: SED7C99 - RYD5E39 - RYD5E29 | G28: WESLEY MILHOMEM DE SOUSA | H28: PARANAGUA | I28: PR | J28: MUITOS CAPOES | K28: RS | L28: BOCCHI INDUSTRIA E COMERCIO DE CERE TDA | M28: BWI TRADING COMERCIAL IMPORTADORA E RTADORA LTDA | N28: CATTALINI TERMINAIS MARITIMOS S/A | O28: BOCCHI INDUSTRIA E COMERCIO DE CERE TDA | P28: BOCCHI INDUSTRIA E COMERCIO DE CERE TDA | Q28: METANOL - ONU 1230 | R28: 48660 | S28: 73820 | T28: 10461.9 | U28: 8671.87 | V28: 607.5 | W28: 1182.53 | X28: 0.12 | Y28: 9854.4 | Z28: =IF(H28&J28="","CT-e COMPLEMENTAR",H28&"/"&J28) -> PARANAGUA/MUITOS CAPOES | AA28: =IFERROR(_xlfn.XLOOKUP(Z28,Rotas!C:C,Rotas!D:D),"0") -> 581 | AB28: =IF(AC28=0,"SUBCONTRATADO","BWT") -> SUBCONTRATADO | AC28: {=IFERROR( INDEX( _xlfn._xlws.FILTER( BWT!$C$1:$C$100, ISNUMBER(FIND( SUBSTITUTE(BWT!$C$1:$C$100," ",""), SUBSTITUTE(SUBSTITUTE(SUBSTITUTE(F28," ",""),"-",""),CHAR(160),"") )) ), 1 ), "")} -> 0
A29: 43260425102812000250570030000002431986819908 | B29: BWT TRANSPORTE E LOGISTICA S. A - ESTEIO | C29: 02/04/2026 | D29: 243 | E29: 101064 | F29: SEE2J88 - RYF2J50 - RYF2J80 | G29: MARCOS AURELIO NOGUEIRA | H29: IJUI | I29: RS | J29: CHAPECO | K29: SC | L29: IPIRANGA PRODUTOS DE PETROLEO S.A. | M29: TRES TENTOS AGROINDUSTRIAL S/A | N29: TRES TENTOS AGROINDUSTRIAL S/A | O29: IPIRANGA PRODUTOS DE PETROLEO S.A. | P29: IPIRANGA PRODUTOS DE PETROLEO S.A. | Q29: Biodiesel - B100 | R29: 58599 | S29: 51680 | T29: 5327.18 | U29: 4687.92 | V29: 0 | W29: 639.26 | X29: 0.12 | Y29: 5327.18 | Z29: =IF(H29&J29="","CT-e COMPLEMENTAR",H29&"/"&J29) -> IJUI/CHAPECO | AA29: =IFERROR(_xlfn.XLOOKUP(Z29,Rotas!C:C,Rotas!D:D),"0") -> 279 | AB29: =IF(AC29=0,"SUBCONTRATADO","BWT") -> BWT | AC29: {=IFERROR( INDEX( _xlfn._xlws.FILTER( BWT!$C$1:$C$100, ISNUMBER(FIND( SUBSTITUTE(BWT!$C$1:$C$100," ",""), SUBSTITUTE(SUBSTITUTE(SUBSTITUTE(F29," ",""),"-",""),CHAR(160),"") )) ), 1 ), "")} -> SEE2J88
A30: 43260425102812000250570030000002461954966869 | B30: BWT TRANSPORTE E LOGISTICA S. A - ESTEIO | C30: 02/04/2026 | D30: 246 | E30: 86744 | F30: SFF3I83 - JCO8H43 - JCO8H36 | G30: WALDECIR JOSE XAVIER | H30: CAMARGO | I30: RS | J30: SAO JOSE DOS CAMPOS | K30: SP | L30: VIBRA ENERGIA SA | M30: FUGA S.A | N30: FUGA S.A | O30: VIBRA ENERGIA SA | P30: VIBRA ENERGIA SA | Q30: Biodiesel - B100 | R30: 59634 | S30: 52160 | T30: 26344.69 | U30: 22398.53 | V30: 784.8 | W30: 3161.36 | X30: 0.12 | Y30: 26344.69 | Z30: =IF(H30&J30="","CT-e COMPLEMENTAR",H30&"/"&J30) -> CAMARGO/SAO JOSE DOS CAMPOS | AA30: =IFERROR(_xlfn.XLOOKUP(Z30,Rotas!C:C,Rotas!D:D),"0") -> 1109 | AB30: =IF(AC30=0,"SUBCONTRATADO","BWT") -> BWT | AC30: {=IFERROR( INDEX( _xlfn._xlws.FILTER( BWT!$C$1:$C$100, ISNUMBER(FIND( SUBSTITUTE(BWT!$C$1:$C$100," ",""), SUBSTITUTE(SUBSTITUTE(SUBSTITUTE(F30," ",""),"-",""),CHAR(160),"") )) ), 1 ), "")} -> SFF3I83
A31: 43260425102812000250570030000002471825087432 | B31: BWT TRANSPORTE E LOGISTICA S. A - ESTEIO | C31: 02/04/2026 | D31: 247 | E31: 86743 | F31: RHG5D74 - JAO8A83 - JAO8A77 | G31: CLAUDINIR RODRIGUES GARCIA | H31: CAMARGO | I31: RS | J31: SAO JOSE DOS CAMPOS | K31: SP | L31: VIBRA ENERGIA SA | M31: FUGA S.A | N31: FUGA S.A | O31: VIBRA ENERGIA SA | P31: VIBRA ENERGIA SA | Q31: Biodiesel - B100 | R31: 59634 | S31: 52060 | T31: 26344.69 | U31: 22398.53 | V31: 784.8 | W31: 3161.36 | X31: 0.12 | Y31: 26344.69 | Z31: =IF(H31&J31="","CT-e COMPLEMENTAR",H31&"/"&J31) -> CAMARGO/SAO JOSE DOS CAMPOS | AA31: =IFERROR(_xlfn.XLOOKUP(Z31,Rotas!C:C,Rotas!D:D),"0") -> 1109 | AB31: =IF(AC31=0,"SUBCONTRATADO","BWT") -> BWT | AC31: {=IFERROR( INDEX( _xlfn._xlws.FILTER( BWT!$C$1:$C$100, ISNUMBER(FIND( SUBSTITUTE(BWT!$C$1:$C$100," ",""), SUBSTITUTE(SUBSTITUTE(SUBSTITUTE(F31," ",""),"-",""),CHAR(160),"") )) ), 1 ), "")} -> RHG5D74
A32: 43260425102812000250570030000002481326650228 | B32: BWT TRANSPORTE E LOGISTICA S. A - ESTEIO | C32: 02/04/2026 | D32: 248 | E32: 86750 | F32: JAZ8G73 - JAZ8G81 - RHH5C90 | G32: ANTONIO HENRIQUE DE SOUZA | H32: CAMARGO | I32: RS | J32: SAO JOSE DOS CAMPOS | K32: SP | L32: VIBRA ENERGIA SA | M32: FUGA S.A | N32: FUGA S.A | O32: VIBRA ENERGIA SA | P32: VIBRA ENERGIA SA | Q32: Biodiesel - B100 | R32: 59610 | S32: 52200 | T32: 26334.45 | U32: 22389.52 | V32: 784.8 | W32: 3160.13 | X32: 0.12 | Y32: 26334.45 | Z32: =IF(H32&J32="","CT-e COMPLEMENTAR",H32&"/"&J32) -> CAMARGO/SAO JOSE DOS CAMPOS | AA32: =IFERROR(_xlfn.XLOOKUP(Z32,Rotas!C:C,Rotas!D:D),"0") -> 1109 | AB32: =IF(AC32=0,"SUBCONTRATADO","BWT") -> BWT | AC32: {=IFERROR( INDEX( _xlfn._xlws.FILTER( BWT!$C$1:$C$100, ISNUMBER(FIND( SUBSTITUTE(BWT!$C$1:$C$100," ",""), SUBSTITUTE(SUBSTITUTE(SUBSTITUTE(F32," ",""),"-",""),CHAR(160),"") )) ), 1 ), "")} -> RHH5C90
A33: 43260425102812000250570030000002491425284286 | B33: BWT TRANSPORTE E LOGISTICA S. A - ESTEIO | C33: 02/04/2026 | D33: 249 | E33: 86751 | F33: SFC5G04 - JAU3A45 - JAU3A29 | G33: JONATAN MODESTO | H33: CAMARGO | I33: RS | J33: SAO JOSE DOS CAMPOS | K33: SP | L33: VIBRA ENERGIA SA | M33: FUGA S.A | N33: FUGA S.A | O33: VIBRA ENERGIA SA | P33: VIBRA ENERGIA SA | Q33: Biodiesel - B100 | R33: 59592 | S33: 52140 | T33: 26326.77 | U33: 22382.76 | V33: 784.8 | W33: 3159.21 | X33: 0.12 | Y33: 26326.77 | Z33: =IF(H33&J33="","CT-e COMPLEMENTAR",H33&"/"&J33) -> CAMARGO/SAO JOSE DOS CAMPOS | AA33: =IFERROR(_xlfn.XLOOKUP(Z33,Rotas!C:C,Rotas!D:D),"0") -> 1109 | AB33: =IF(AC33=0,"SUBCONTRATADO","BWT") -> BWT | AC33: {=IFERROR( INDEX( _xlfn._xlws.FILTER( BWT!$C$1:$C$100, ISNUMBER(FIND( SUBSTITUTE(BWT!$C$1:$C$100," ",""), SUBSTITUTE(SUBSTITUTE(SUBSTITUTE(F33," ",""),"-",""),CHAR(160),"") )) ), 1 ), "")} -> SFC5G04
A34: 43260425102812000250570030000002501559917748 | B34: BWT TRANSPORTE E LOGISTICA S. A - ESTEIO | C34: 02/04/2026 | D34: 250 | E34: 39287 | F34: SFF3I82 - JCO4B49 - JCO4B32 | G34: ANDRIELIA APARECIDA GOMES | H34: MUITOS CAPOES | I34: RS | J34: ARAUCARIA | K34: PR | L34: ROYAL FIC DISTRIBUIDORA DE DERIVADO OLEO S/A | M34: BOCCHI INDUSTRIA E COMERCIO DE CERE TDA | N34: BOCCHI INDUSTRIA E COMERCIO DE CERE TDA | O34: ROYAL FIC DISTRIBUIDORA DE DERIVADO OLEO S/A | P34: ROYAL FIC DISTRIBUIDORA DE DERIVADO OLEO S/A | Q34: Biodiesel - B100 | R34: 59604 | S34: 77880 | T34: 8344.56 | U34: 6951.71 | V34: 391.5 | W34: 1001.35 | X34: 0.12 | Y34: 8344.56 | Z34: =IF(H34&J34="","CT-e COMPLEMENTAR",H34&"/"&J34) -> MUITOS CAPOES/ARAUCARIA | AA34: =IFERROR(_xlfn.XLOOKUP(Z34,Rotas!C:C,Rotas!D:D),"0") -> 495 | AB34: =IF(AC34=0,"SUBCONTRATADO","BWT") -> BWT | AC34: {=IFERROR( INDEX( _xlfn._xlws.FILTER( BWT!$C$1:$C$100, ISNUMBER(FIND( SUBSTITUTE(BWT!$C$1:$C$100," ",""), SUBSTITUTE(SUBSTITUTE(SUBSTITUTE(F34," ",""),"-",""),CHAR(160),"") )) ), 1 ), "")} -> SFF3I82
A35: 43260425102812000250570030000002511709798290 | B35: BWT TRANSPORTE E LOGISTICA S. A - ESTEIO | C35: 02/04/2026 | D35: 251 | E35: 39288 | F35: JAS4J43 - JAS4J59 - RHI3D46 | G35: ELENILDO GOMES DA SILVA | H35: MUITOS CAPOES | I35: RS | J35: ARAUCARIA | K35: PR | L35: ROYAL FIC DISTRIBUIDORA DE DERIVADO OLEO S/A | M35: BOCCHI INDUSTRIA E COMERCIO DE CERE TDA | N35: BOCCHI INDUSTRIA E COMERCIO DE CERE TDA | O35: ROYAL FIC DISTRIBUIDORA DE DERIVADO OLEO S/A | P35: ROYAL FIC DISTRIBUIDORA DE DERIVADO OLEO S/A | Q35: Biodiesel - B100 | R35: 59558 | S35: 77960 | T35: 8338.13 | U35: 6946.05 | V35: 391.5 | W35: 1000.58 | X35: 0.12 | Y35: 8338.13 | Z35: =IF(H35&J35="","CT-e COMPLEMENTAR",H35&"/"&J35) -> MUITOS CAPOES/ARAUCARIA | AA35: =IFERROR(_xlfn.XLOOKUP(Z35,Rotas!C:C,Rotas!D:D),"0") -> 495 | AB35: =IF(AC35=0,"SUBCONTRATADO","BWT") -> BWT | AC35: {=IFERROR( INDEX( _xlfn._xlws.FILTER( BWT!$C$1:$C$100, ISNUMBER(FIND( SUBSTITUTE(BWT!$C$1:$C$100," ",""), SUBSTITUTE(SUBSTITUTE(SUBSTITUTE(F35," ",""),"-",""),CHAR(160),"") )) ), 1 ), "")} -> RHI3D46
A36: 35260425102812000500570030000002321200284957 | B36: BWT TRANSPORTE E LOGISTICA S. A - PAULINIA | C36: 03/04/2026 | D36: 232 | E36: 30222 | F36: JAV7E00 - SEX2C75 - JAV7E07 | G36: FRANCISCO JOSE ESTEVES | H36: SANTOS | I36: SP | J36: PAULINIA | K36: SP | L36: IPIRANGA PRODUTOS DE PETROLEO S.A. | M36: IPIRANGA PRODUTOS DE PETROLEO S.A. | N36: ULTRACARGO LOGISTICA S.A | O36: IPIRANGA PRODUTOS DE PETROLEO S/A | P36: IPIRANGA PRODUTOS DE PETROLEO S/A | Q36: Gasolina A | R36: 63211 | S36: 45664 | T36: 3149.77 | U36: 2771.8 | V36: 0 | W36: 377.97 | X36: 0.12 | Y36: 3149.77 | Z36: =IF(H36&J36="","CT-e COMPLEMENTAR",H36&"/"&J36) -> SANTOS/PAULINIA | AA36: =IFERROR(_xlfn.XLOOKUP(Z36,Rotas!C:C,Rotas!D:D),"0") -> 215 | AB36: =IF(AC36=0,"SUBCONTRATADO","BWT") -> BWT | AC36: {=IFERROR( INDEX( _xlfn._xlws.FILTER( BWT!$C$1:$C$100, ISNUMBER(FIND( SUBSTITUTE(BWT!$C$1:$C$100," ",""), SUBSTITUTE(SUBSTITUTE(SUBSTITUTE(F36," ",""),"-",""),CHAR(160),"") )) ), 1 ), "")} -> SEX2C75
A37: 35260425102812000500570030000002331121730382 | B37: BWT TRANSPORTE E LOGISTICA S. A - PAULINIA | C37: 03/04/2026 | D37: 233 | E37: 30224 | F37: SEE2J90 - RYG6E01 - RYG6D61 | G37: VILSO DE OLIVEIRA COSTA | H37: SANTOS | I37: SP | J37: PAULINIA | K37: SP | L37: IPIRANGA PRODUTOS DE PETROLEO S.A. | M37: IPIRANGA PRODUTOS DE PETROLEO S.A. | N37: ULTRACARGO LOGISTICA S.A | O37: IPIRANGA PRODUTOS DE PETROLEO S/A | P37: IPIRANGA PRODUTOS DE PETROLEO S/A | Q37: Gasolina A | R37: 63191 | S37: 45681 | T37: 3150.22 | U37: 2772.19 | V37: 0 | W37: 378.03 | X37: 0.12 | Y37: 3150.22 | Z37: =IF(H37&J37="","CT-e COMPLEMENTAR",H37&"/"&J37) -> SANTOS/PAULINIA | AA37: =IFERROR(_xlfn.XLOOKUP(Z37,Rotas!C:C,Rotas!D:D),"0") -> 215 | AB37: =IF(AC37=0,"SUBCONTRATADO","BWT") -> BWT | AC37: {=IFERROR( INDEX( _xlfn._xlws.FILTER( BWT!$C$1:$C$100, ISNUMBER(FIND( SUBSTITUTE(BWT!$C$1:$C$100," ",""), SUBSTITUTE(SUBSTITUTE(SUBSTITUTE(F37," ",""),"-",""),CHAR(160),"") )) ), 1 ), "")} -> SEE2J90
A38: 35260425102812000500570030000002341316483322 | B38: BWT TRANSPORTE E LOGISTICA S. A - PAULINIA | C38: 03/04/2026 | D38: 234 | E38: 30226 | F38: BDQ4E29 - IZW8A03 - IZW8A02 | G38: LUIZ CARLOS COELHO | H38: SANTOS | I38: SP | J38: PAULINIA | K38: SP | L38: IPIRANGA PRODUTOS DE PETROLEO S.A. | M38: IPIRANGA PRODUTOS DE PETROLEO S.A. | N38: ULTRACARGO LOGISTICA S.A | O38: IPIRANGA PRODUTOS DE PETROLEO S/A | P38: IPIRANGA PRODUTOS DE PETROLEO S/A | Q38: Gasolina A | R38: 63453 | S38: 45838 | T38: 3150.3 | U38: 2772.26 | V38: 0 | W38: 378.04 | X38: 0.12 | Y38: 3150.3 | Z38: =IF(H38&J38="","CT-e COMPLEMENTAR",H38&"/"&J38) -> SANTOS/PAULINIA | AA38: =IFERROR(_xlfn.XLOOKUP(Z38,Rotas!C:C,Rotas!D:D),"0") -> 215 | AB38: =IF(AC38=0,"SUBCONTRATADO","BWT") -> BWT | AC38: {=IFERROR( INDEX( _xlfn._xlws.FILTER( BWT!$C$1:$C$100, ISNUMBER(FIND( SUBSTITUTE(BWT!$C$1:$C$100," ",""), SUBSTITUTE(SUBSTITUTE(SUBSTITUTE(F38," ",""),"-",""),CHAR(160),"") )) ), 1 ), "")} -> BDQ4E29
A39: 35260425102812000500570030000002351180821237 | B39: BWT TRANSPORTE E LOGISTICA S. A - PAULINIA | C39: 03/04/2026 | D39: 235 | E39: 30229 | F39: JBU3A17 - JBU3A10 - SED7D20 | G39: VALDEREZ MAINARDES | H39: SANTOS | I39: SP | J39: PAULINIA | K39: SP | L39: IPIRANGA PRODUTOS DE PETROLEO S.A. | M39: IPIRANGA PRODUTOS DE PETROLEO S.A. | N39: ULTRACARGO LOGISTICA S.A | O39: IPIRANGA PRODUTOS DE PETROLEO S/A | P39: IPIRANGA PRODUTOS DE PETROLEO S/A | Q39: Gasolina A | R39: 63398 | S39: 45799 | T39: 3149.73 | U39: 2771.76 | V39: 0 | W39: 377.97 | X39: 0.12 | Y39: 3149.73 | Z39: =IF(H39&J39="","CT-e COMPLEMENTAR",H39&"/"&J39) -> SANTOS/PAULINIA | AA39: =IFERROR(_xlfn.XLOOKUP(Z39,Rotas!C:C,Rotas!D:D),"0") -> 215 | AB39: =IF(AC39=0,"SUBCONTRATADO","BWT") -> BWT | AC39: {=IFERROR( INDEX( _xlfn._xlws.FILTER( BWT!$C$1:$C$100, ISNUMBER(FIND( SUBSTITUTE(BWT!$C$1:$C$100," ",""), SUBSTITUTE(SUBSTITUTE(SUBSTITUTE(F39," ",""),"-",""),CHAR(160),"") )) ), 1 ), "")} -> SED7D20
... A41: 41260425102812000179570030000008031673837131 | B41: BWT ARAUCARIA - ARAUCARIA | C41: 03/04/2026 | D41: 803 | E41: 2695 - 2693 | F41: SED7D07 - RXU1C90 - RXU1D30 | G41: CLAUDINOR CAMPARIM | H41: PARANAGUA | I41: PR | J41: MUITOS CAPOES | K41: RS | L41: BOCCHI INDUSTRIA E COMERCIO DE CERE TDA | M41: BWI TRADING COMERCIAL IMPORTADORA E RTADORA LTDA | N41: CATTALINI TERMINAIS MARITIMOS S/A | O41: BOCCHI INDUSTRIA E COMERCIO DE CERE TDA | P41: BOCCHI INDUSTRIA E COMERCIO DE CERE TDA | Q41: METANOL - ONU 1230 | R41: 48477 | S41: 73837 | T41: 10422.56 | U41: 8637.25 | V41: 607.5 | W41: 1177.81 | X41: 0.12 | Y41: 9815.06 | Z41: =IF(H41&J41="","CT-e COMPLEMENTAR",H41&"/"&J41) -> PARANAGUA/MUITOS CAPOES | AA41: =IFERROR(_xlfn.XLOOKUP(Z41,Rotas!C:C,Rotas!D:D),"0") -> 581 | AB41: =IF(AC41=0,"SUBCONTRATADO","BWT") -> SUBCONTRATADO | AC41: {=IFERROR( INDEX( _xlfn._xlws.FILTER( BWT!$C$1:$C$100, ISNUMBER(FIND( SUBSTITUTE(BWT!$C$1:$C$100," ",""), SUBSTITUTE(SUBSTITUTE(SUBSTITUTE(F41," ",""),"-",""),CHAR(160),"") )) ), 1 ), "")} -> 0
A42: 41260425102812000179570030000008041262212631 | B42: BWT ARAUCARIA - ARAUCARIA | C42: 03/04/2026 | D42: 804 | E42: 1095147 | F42: BDF9C15 - JCH2G41 | G42: GUSTAVO ANTONIO NOGUEIRA | H42: PARANAGUA | I42: PR | J42: LAPA | K42: PR | L42: POTENCIAL AGRO S/A - MATRIZ | M42: CATTALINI TERMINAIS MARITIMOS S/A | N42: CATTALINI TERMINAIS MARITIMOS S/A | O42: POTENCIAL AGRO S/A - MATRIZ | P42: POTENCIAL AGRO S/A - MATRIZ | Q42: METANOL - ONU 1230 | R42: 38094 | S42: 58294 | T42: 3912.25 | U42: 3912.25 | V42: 0 | W42: 0 | Z42: =IF(H42&J42="","CT-e COMPLEMENTAR",H42&"/"&J42) -> PARANAGUA/LAPA | AA42: =IFERROR(_xlfn.XLOOKUP(Z42,Rotas!C:C,Rotas!D:D),"0") -> 153 | AB42: =IF(AC42=0,"SUBCONTRATADO","BWT") -> BWT | AC42: {=IFERROR( INDEX( _xlfn._xlws.FILTER( BWT!$C$1:$C$100, ISNUMBER(FIND( SUBSTITUTE(BWT!$C$1:$C$100," ",""), SUBSTITUTE(SUBSTITUTE(SUBSTITUTE(F42," ",""),"-",""),CHAR(160),"") )) ), 1 ), "")} -> BDF9C15
A43: 41260425102812000179570030000008051069089685 | B43: BWT ARAUCARIA - ARAUCARIA | C43: 03/04/2026 | D43: 805 | E43: 1095213 | F43: BDQ4E39 | G43: WERNER DUCK | H43: PARANAGUA | I43: PR | J43: LAPA | K43: PR | L43: POTENCIAL AGRO S/A - MATRIZ | M43: CATTALINI TERMINAIS MARITIMOS S/A | N43: CATTALINI TERMINAIS MARITIMOS S/A | O43: POTENCIAL AGRO S/A - MATRIZ | P43: POTENCIAL AGRO S/A - MATRIZ | Q43: METANOL - ONU 1230 | R43: 47720 | S43: 73880 | T43: 4373.54 | U43: 4373.54 | V43: 0 | W43: 0 | Z43: =IF(H43&J43="","CT-e COMPLEMENTAR",H43&"/"&J43) -> PARANAGUA/LAPA | AA43: =IFERROR(_xlfn.XLOOKUP(Z43,Rotas!C:C,Rotas!D:D),"0") -> 153 | AB43: =IF(AC43=0,"SUBCONTRATADO","BWT") -> BWT | AC43: {=IFERROR( INDEX( _xlfn._xlws.FILTER( BWT!$C$1:$C$100, ISNUMBER(FIND( SUBSTITUTE(BWT!$C$1:$C$100," ",""), SUBSTITUTE(SUBSTITUTE(SUBSTITUTE(F43," ",""),"-",""),CHAR(160),"") )) ), 1 ), "")} -> BDQ4E39
A44: 41260425102812000179570030000008061867953597 | B44: BWT ARAUCARIA - ARAUCARIA | C44: 03/04/2026 | D44: 806 | E44: 1095255 | F44: BAH3I06 - BDQ4E23 - BAH3I07 | G44: DANIEL ANTONIO DOS SANTOS JUNIOR | H44: PARANAGUA | I44: PR | J44: IJUI | K44: RS | L44: CAMERA AGROALIMENTOS S A | M44: CATTALINI TERMINAIS MARITIMOS S/A | N44: CATTALINI TERMINAIS MARITIMOS S/A | O44: CAMERA AGROALIMENTOS S A | P44: CAMERA AGROALIMENTOS S A | Q44: METANOL - ONU 1230 | R44: 48140 | S44: 73860 | T44: 10783.36 | U44: 9201.86 | V44: 326.7 | W44: 1254.8 | X44: 0.12 | Y44: 10456.66 | Z44: =IF(H44&J44="","CT-e COMPLEMENTAR",H44&"/"&J44) -> PARANAGUA/IJUI | AA44: =IFERROR(_xlfn.XLOOKUP(Z44,Rotas!C:C,Rotas!D:D),"0") -> 800 | AB44: =IF(AC44=0,"SUBCONTRATADO","BWT") -> BWT | AC44: {=IFERROR( INDEX( _xlfn._xlws.FILTER( BWT!$C$1:$C$100, ISNUMBER(FIND( SUBSTITUTE(BWT!$C$1:$C$100," ",""), SUBSTITUTE(SUBSTITUTE(SUBSTITUTE(F44," ",""),"-",""),CHAR(160),"") )) ), 1 ), "")} -> BDQ4E23
A45: 35260425102812000500570030000002371988609570 | B45: BWT TRANSPORTE E LOGISTICA S. A - PAULINIA | C45: 04/04/2026 | D45: 237 | E45: 30331 | F45: BDV9E57 - BDV9E56 - SEE0I05 | G45: RODRIGO DOS SANTOS ALVES | H45: SANTOS | I45: SP | J45: PAULINIA | K45: SP | L45: IPIRANGA PRODUTOS DE PETROLEO S.A. | M45: IPIRANGA PRODUTOS DE PETROLEO S.A. | N45: ULTRACARGO LOGISTICA S.A | O45: IPIRANGA PRODUTOS DE PETROLEO S/A | P45: IPIRANGA PRODUTOS DE PETROLEO S/A | Q45: Gasolina A | R45: 61128 | S45: 44183 | T45: 3150.17 | U45: 2772.15 | V45: 0 | W45: 378.02 | X45: 0.12 | Y45: 3150.17 | Z45: =IF(H45&J45="","CT-e COMPLEMENTAR",H45&"/"&J45) -> SANTOS/PAULINIA | AA45: =IFERROR(_xlfn.XLOOKUP(Z45,Rotas!C:C,Rotas!D:D),"0") -> 215 | AB45: =IF(AC45=0,"SUBCONTRATADO","BWT") -> BWT | AC45: {=IFERROR( INDEX( _xlfn._xlws.FILTER( BWT!$C$1:$C$100, ISNUMBER(FIND( SUBSTITUTE(BWT!$C$1:$C$100," ",""), SUBSTITUTE(SUBSTITUTE(SUBSTITUTE(F45," ",""),"-",""),CHAR(160),"") )) ), 1 ), "")} -> SEE0I05
A46: 35260425102812000500570030000002381821059531 | B46: BWT TRANSPORTE E LOGISTICA S. A - PAULINIA | C46: 04/04/2026 | D46: 238 | E46: 30359 | F46: JCM1E27 - SFC5F45 | G46: EMERSON MENON CUNHA | H46: SANTOS | I46: SP | J46: PAULINIA | K46: SP | L46: IPIRANGA PRODUTOS DE PETROLEO S.A. | M46: IPIRANGA PRODUTOS DE PETROLEO S.A. | N46: ULTRACARGO LOGISTICA S.A | O46: IPIRANGA PRODUTOS DE PETROLEO S/A | P46: IPIRANGA PRODUTOS DE PETROLEO S/A | Q46: Gasolina A | R46: 50358 | S46: 36243 | T46: 3150.24 | U46: 2772.21 | V46: 0 | W46: 378.03 | X46: 0.12 | Y46: 3150.24 | Z46: =IF(H46&J46="","CT-e COMPLEMENTAR",H46&"/"&J46) -> SANTOS/PAULINIA | AA46: =IFERROR(_xlfn.XLOOKUP(Z46,Rotas!C:C,Rotas!D:D),"0") -> 215 | AB46: =IF(AC46=0,"SUBCONTRATADO","BWT") -> BWT | AC46: {=IFERROR( INDEX( _xlfn._xlws.FILTER( BWT!$C$1:$C$100, ISNUMBER(FIND( SUBSTITUTE(BWT!$C$1:$C$100," ",""), SUBSTITUTE(SUBSTITUTE(SUBSTITUTE(F46," ",""),"-",""),CHAR(160),"") )) ), 1 ), "")} -> SFC5F45
A47: 35260425102812000500570030000002391313890608 | B47: BWT TRANSPORTE E LOGISTICA S. A - PAULINIA | C47: 04/04/2026 | D47: 239 | E47: 30385 | F47: JAP8F48 - SFA7F70 - JAP8F56 | G47: PAULO ROBERTO EVANGELISTA SOARES | H47: SANTOS | I47: SP | J47: PAULINIA | K47: SP | L47: IPIRANGA PRODUTOS DE PETROLEO S.A. | M47: IPIRANGA PRODUTOS DE PETROLEO S.A. | N47: ULTRACARGO LOGISTICA S.A | O47: IPIRANGA PRODUTOS DE PETROLEO S/A | P47: IPIRANGA PRODUTOS DE PETROLEO S/A | Q47: Gasolina A | R47: 63239 | S47: 45987 | T47: 3149.74 | U47: 2771.77 | V47: 0 | W47: 377.97 | X47: 0.12 | Y47: 3149.74 | Z47: =IF(H47&J47="","CT-e COMPLEMENTAR",H47&"/"&J47) -> SANTOS/PAULINIA | AA47: =IFERROR(_xlfn.XLOOKUP(Z47,Rotas!C:C,Rotas!D:D),"0") -> 215 | AB47: =IF(AC47=0,"SUBCONTRATADO","BWT") -> BWT | AC47: {=IFERROR( INDEX( _xlfn._xlws.FILTER( BWT!$C$1:$C$100, ISNUMBER(FIND( SUBSTITUTE(BWT!$C$1:$C$100," ",""), SUBSTITUTE(SUBSTITUTE(SUBSTITUTE(F47," ",""),"-",""),CHAR(160),"") )) ), 1 ), "")} -> SFA7F70
A48: 35260425102812000500570030000002401667023585 | B48: BWT TRANSPORTE E LOGISTICA S. A - PAULINIA | C48: 04/04/2026 | D48: 240 | E48: 30391 | F48: JDJ2B32 - JDJ2B43 - TAW8B84 | G48: EDENIR MALOSTI PEREIRA | H48: SANTOS | I48: SP | J48: PAULINIA | K48: SP | L48: IPIRANGA PRODUTOS DE PETROLEO S.A. | M48: IPIRANGA PRODUTOS DE PETROLEO S.A. | N48: ULTRACARGO LOGISTICA S.A | O48: IPIRANGA PRODUTOS DE PETROLEO S/A | P48: IPIRANGA PRODUTOS DE PETROLEO S/A | Q48: Gasolina A | R48: 63054 | S48: 46156 | T48: 3149.83 | U48: 2771.85 | V48: 0 | W48: 377.98 | X48: 0.12 | Y48: 3149.83 | Z48: =IF(H48&J48="","CT-e COMPLEMENTAR",H48&"/"&J48) -> SANTOS/PAULINIA | AA48: =IFERROR(_xlfn.XLOOKUP(Z48,Rotas!C:C,Rotas!D:D),"0") -> 215 | AB48: =IF(AC48=0,"SUBCONTRATADO","BWT") -> BWT | AC48: {=IFERROR( INDEX( _xlfn._xlws.FILTER( BWT!$C$1:$C$100, ISNUMBER(FIND( SUBSTITUTE(BWT!$C$1:$C$100," ",""), SUBSTITUTE(SUBSTITUTE(SUBSTITUTE(F48," ",""),"-",""),CHAR(160),"") )) ), 1 ), "")} -> TAW8B84
A49: 35260425102812000500570030000002421806628000 | B49: BWT TRANSPORTE E LOGISTICA S. A - PAULINIA | C49: 04/04/2026 | D49: 242 | E49: 30407 | F49: BDQ4E29 - IZW8A03 - IZW8A02 | G49: LUIZ CARLOS COELHO | H49: SANTOS | I49: SP | J49: PAULINIA | K49: SP | L49: IPIRANGA PRODUTOS DE PETROLEO S.A. | M49: IPIRANGA PRODUTOS DE PETROLEO S.A. | N49: AGEO NORTE TERMINAIS E ARMAZENS GER A | O49: IPIRANGA PRODUTOS DE PETROLEO S/A | P49: IPIRANGA PRODUTOS DE PETROLEO S/A | Q49: Gasolina A | R49: 58465 | S49: 48450 | T49: 3149.81 | U49: 2771.83 | V49: 0 | W49: 377.98 | X49: 0.12 | Y49: 3149.81 | Z49: =IF(H49&J49="","CT-e COMPLEMENTAR",H49&"/"&J49) -> SANTOS/PAULINIA | AA49: =IFERROR(_xlfn.XLOOKUP(Z49,Rotas!C:C,Rotas!D:D),"0") -> 215 | AB49: =IF(AC49=0,"SUBCONTRATADO","BWT") -> BWT | AC49: {=IFERROR( INDEX( _xlfn._xlws.FILTER( BWT!$C$1:$C$100, ISNUMBER(FIND( SUBSTITUTE(BWT!$C$1:$C$100," ",""), SUBSTITUTE(SUBSTITUTE(SUBSTITUTE(F49," ",""),"-",""),CHAR(160),"") )) ), 1 ), "")} -> BDQ4E29
A50: 35260425102812000500570030000002431445445612 | B50: BWT TRANSPORTE E LOGISTICA S. A - PAULINIA | C50: 04/04/2026 | D50: 243 | E50: 30452 | F50: JBT9E33 - SEE2J92 - JBT9E30 | G50: SILAS DE LIMA | H50: SANTOS | I50: SP | J50: PAULINIA | K50: SP | L50: IPIRANGA PRODUTOS DE PETROLEO S.A. | M50: IPIRANGA PRODUTOS DE PETROLEO S.A. | N50: ULTRACARGO LOGISTICA S.A | O50: IPIRANGA PRODUTOS DE PETROLEO S/A | P50: IPIRANGA PRODUTOS DE PETROLEO S/A | Q50: Gasolina A | R50: 62936 | S50: 44049 | T50: 3149.66 | U50: 2771.7 | V50: 0 | W50: 377.96 | X50: 0.12 | Y50: 3149.66 | Z50: =IF(H50&J50="","CT-e COMPLEMENTAR",H50&"/"&J50) -> SANTOS/PAULINIA | AA50: =IFERROR(_xlfn.XLOOKUP(Z50,Rotas!C:C,Rotas!D:D),"0") -> 215 | AB50: =IF(AC50=0,"SUBCONTRATADO","BWT") -> BWT | AC50: {=IFERROR( INDEX( _xlfn._xlws.FILTER( BWT!$C$1:$C$100, ISNUMBER(FIND( SUBSTITUTE(BWT!$C$1:$C$100," ",""), SUBSTITUTE(SUBSTITUTE(SUBSTITUTE(F50," ",""),"-",""),CHAR(160),"") )) ), 1 ), "")} -> SEE2J92
A51: 35260425102812000500570030000002441035880979 | B51: BWT TRANSPORTE E LOGISTICA S. A - PAULINIA | C51: 04/04/2026 | D51: 244 | E51: 30467 | F51: TAW8C01 - RYF3A30 - RYF2J90 | G51: ROBERTO RIVELINO CABRAL | H51: SANTOS | I51: SP | J51: PAULINIA | K51: SP | L51: IPIRANGA PRODUTOS DE PETROLEO S.A. | M51: IPIRANGA PRODUTOS DE PETROLEO S.A. | N51: ULTRACARGO LOGISTICA S.A | O51: IPIRANGA PRODUTOS DE PETROLEO S/A | P51: IPIRANGA PRODUTOS DE PETROLEO S/A | Q51: Gasolina A | R51: 63289 | S51: 45429 | T51: 3150.07 | U51: 2772.06 | V51: 0 | W51: 378.01 | X51: 0.12 | Y51: 3150.07 | Z51: =IF(H51&J51="","CT-e COMPLEMENTAR",H51&"/"&J51) -> SANTOS/PAULINIA | AA51: =IFERROR(_xlfn.XLOOKUP(Z51,Rotas!C:C,Rotas!D:D),"0") -> 215 | AB51: =IF(AC51=0,"SUBCONTRATADO","BWT") -> BWT | AC51: {=IFERROR( INDEX( _xlfn._xlws.FILTER( BWT!$C$1:$C$100, ISNUMBER(FIND( SUBSTITUTE(BWT!$C$1:$C$100," ",""), SUBSTITUTE(SUBSTITUTE(SUBSTITUTE(F51," ",""),"-",""),CHAR(160),"") )) ), 1 ), "")} -> TAW8C01
A52: 41260425102812000179570030000008071972050922 | B52: BWT ARAUCARIA - ARAUCARIA | C52: 04/04/2026 | D52: 807 | E52: 327592 | F52: BBM6H26 - BBM6H25 - RHH5D97 | G52: MARIO SERGIO DOS SANTOS ANDREOLA | H52: SAO CARLOS DO IVAI | I52: PR | J52: ARAUCARIA | K52: PR | L52: IPIRANGA PRODUTOS DE PETROLEO S/A | M52: COOPERATIVA AGRICOLA REGIONAL DE PR RES DE CAN | N52: COOPERATIVA AGRICOLA REGIONAL DE PR RES DE CAN | O52: IPIRANGA PRODUTOS DE PETROLEO S/A | P52: IPIRANGA PRODUTOS DE PETROLEO S/A | Q52: Etanol Anidro | R52: 59538 | S52: 47000 | T52: 6439.03 | U52: 6439.03 | V52: 0 | W52: 0 | Z52: =IF(H52&J52="","CT-e COMPLEMENTAR",H52&"/"&J52) -> SAO CARLOS DO IVAI/ARAUCARIA | AA52: =IFERROR(_xlfn.XLOOKUP(Z52,Rotas!C:C,Rotas!D:D),"0") -> 491 | AB52: =IF(AC52=0,"SUBCONTRATADO","BWT") -> BWT | AC52: {=IFERROR( INDEX( _xlfn._xlws.FILTER( BWT!$C$1:$C$100, ISNUMBER(FIND( SUBSTITUTE(BWT!$C$1:$C$100," ",""), SUBSTITUTE(SUBSTITUTE(SUBSTITUTE(F52," ",""),"-",""),CHAR(160),"") )) ), 1 ), "")} -> RHH5D97
A53: 41260425102812000179570030000008081268485353 | B53: BWT ARAUCARIA - ARAUCARIA | C53: 04/04/2026 | D53: 808 | E53: 327594 | F53: BBM6H24 - BBM6H15 - BDQ4E18 | G53: DANIEL EUFRAZIO | H53: SAO CARLOS DO IVAI | I53: PR | J53: ARAUCARIA | K53: PR | L53: IPIRANGA PRODUTOS DE PETROLEO S/A | M53: COOPERATIVA AGRICOLA REGIONAL DE PR RES DE CAN | N53: COOPERATIVA AGRICOLA REGIONAL DE PR RES DE CAN | O53: IPIRANGA PRODUTOS DE PETROLEO S/A | P53: IPIRANGA PRODUTOS DE PETROLEO S/A | Q53: Etanol Anidro | R53: 59472 | S53: 46940 | T53: 6431.9 | U53: 6431.9 | V53: 0 | W53: 0 | Z53: =IF(H53&J53="","CT-e COMPLEMENTAR",H53&"/"&J53) -> SAO CARLOS DO IVAI/ARAUCARIA | AA53: =IFERROR(_xlfn.XLOOKUP(Z53,Rotas!C:C,Rotas!D:D),"0") -> 491 | AB53: =IF(AC53=0,"SUBCONTRATADO","BWT") -> BWT | AC53: {=IFERROR( INDEX( _xlfn._xlws.FILTER( BWT!$C$1:$C$100, ISNUMBER(FIND( SUBSTITUTE(BWT!$C$1:$C$100," ",""), SUBSTITUTE(SUBSTITUTE(SUBSTITUTE(F53," ",""),"-",""),CHAR(160),"") )) ), 1 ), "")} -> BDQ4E18
A54: 41260425102812000179570030000008091189886905 | B54: BWT ARAUCARIA - ARAUCARIA | C54: 04/04/2026 | D54: 809 | E54: 2686 - 2687 | F54: SEE0I16 - TLA5E54 - TIV7C08 | G54: LEANDRO OLIVEIRA RODRIGUES | H54: PARANAGUA | I54: PR | J54: MAFRA | K54: SC | L54: BWI TRADING COMERCIAL IMPORTADORA E RTADORA LTDA | M54: BWI TRADING COMERCIAL IMPORTADORA E RTADORA LTDA | N54: CPA TERMINAL PARANAGUA S.A | O54: SEARA ALIMENTOS LTDA | P54: SEARA ALIMENTOS LTDA | Q54: METILATO DE SODIO 30% | R54: 45000 | S54: 45000 | T54: 6496.65 | U54: 5108.8 | V54: 691.2 | W54: 696.65 | X54: 0.12 | Y54: 5805.45 | Z54: =IF(H54&J54="","CT-e COMPLEMENTAR",H54&"/"&J54) -> PARANAGUA/MAFRA | AA54: =IFERROR(_xlfn.XLOOKUP(Z54,Rotas!C:C,Rotas!D:D),"0") -> 195 | AB54: =IF(AC54=0,"SUBCONTRATADO","BWT") -> BWT | AC54: {=IFERROR( INDEX( _xlfn._xlws.FILTER( BWT!$C$1:$C$100, ISNUMBER(FIND( SUBSTITUTE(BWT!$C$1:$C$100," ",""), SUBSTITUTE(SUBSTITUTE(SUBSTITUTE(F54," ",""),"-",""),CHAR(160),"") )) ), 1 ), "")} -> SEE0I16
A55: 41260425102812000179570030000008101167672970 | B55: BWT ARAUCARIA - ARAUCARIA | C55: 04/04/2026 | D55: 810 | E55: 79325 | F55: BDQ4E32 - IZW6J87 - IZW6J99 | G55: OSVALDIR RIBEIRO PINTO | H55: PARANAGUA | I55: PR | J55: SARANDI-PR | K55: PR | L55: IPIRANGA PRODUTOS DE PETROLEO S.A | M55: IPIRANGA PRODUTOS DE PETROLEO S.A | N55: CATTALINI TERMINAIS MARITIMOS S/A | O55: IPIRANGA PRODUTOS DE PETROLEO S/A | P55: IPIRANGA PRODUTOS DE PETROLEO S/A | Q55: Diesel S500 A | R55: 58233 | S55: 47850 | T55: 14907.65 | U55: 14907.65 | V55: 0 | W55: 0 | Z55: =IF(H55&J55="","CT-e COMPLEMENTAR",H55&"/"&J55) -> PARANAGUA/SARANDI-PR | AA55: =IFERROR(_xlfn.XLOOKUP(Z55,Rotas!C:C,Rotas!D:D),"0") -> 518 | AB55: =IF(AC55=0,"SUBCONTRATADO","BWT") -> BWT | AC55: {=IFERROR( INDEX( _xlfn._xlws.FILTER( BWT!$C$1:$C$100, ISNUMBER(FIND( SUBSTITUTE(BWT!$C$1:$C$100," ",""), SUBSTITUTE(SUBSTITUTE(SUBSTITUTE(F55," ",""),"-",""),CHAR(160),"") )) ), 1 ), "")} -> BDQ4E32
A56: 41260425102812000179570030000008111444890672 | B56: BWT ARAUCARIA - ARAUCARIA | C56: 04/04/2026 | D56: 811 | E56: 79332 | F56: TAW8B80 - JCV2H32 - JCV8B29 | G56: LAURO LORETO TEIXEIRA | H56: PARANAGUA | I56: PR | J56: SARANDI-PR | K56: PR | L56: IPIRANGA PRODUTOS DE PETROLEO S.A | M56: IPIRANGA PRODUTOS DE PETROLEO S.A | N56: CATTALINI TERMINAIS MARITIMOS S/A | O56: IPIRANGA PRODUTOS DE PETROLEO S/A | P56: IPIRANGA PRODUTOS DE PETROLEO S/A | Q56: Diesel S500 A | R56: 58264 | S56: 47876 | T56: 14915.58 | U56: 14915.58 | V56: 0 | W56: 0 | Z56: =IF(H56&J56="","CT-e COMPLEMENTAR",H56&"/"&J56) -> PARANAGUA/SARANDI-PR | AA56: =IFERROR(_xlfn.XLOOKUP(Z56,Rotas!C:C,Rotas!D:D),"0") -> 518 | AB56: =IF(AC56=0,"SUBCONTRATADO","BWT") -> BWT | AC56: {=IFERROR( INDEX( _xlfn._xlws.FILTER( BWT!$C$1:$C$100, ISNUMBER(FIND( SUBSTITUTE(BWT!$C$1:$C$100," ",""), SUBSTITUTE(SUBSTITUTE(SUBSTITUTE(F56," ",""),"-",""),CHAR(160),"") )) ), 1 ), "")} -> TAW8B80
A57: 41260425102812000179570030000008121489223176 | B57: BWT ARAUCARIA - ARAUCARIA | C57: 04/04/2026 | D57: 812 | E57: 1095499 | F57: BDF9C15 - JCH2G41 | G57: GUSTAVO ANTONIO NOGUEIRA | H57: PARANAGUA | I57: PR | J57: LAPA | K57: PR | L57: POTENCIAL AGRO S/A - MATRIZ | M57: CATTALINI TERMINAIS MARITIMOS S/A | N57: CATTALINI TERMINAIS MARITIMOS S/A | O57: POTENCIAL AGRO S/A - MATRIZ | P57: POTENCIAL AGRO S/A - MATRIZ | Q57: METANOL - ONU 1230 | R57: 38280 | S57: 58360 | T57: 3931.36 | U57: 3931.36 | V57: 0 | W57: 0 | Z57: =IF(H57&J57="","CT-e COMPLEMENTAR",H57&"/"&J57) -> PARANAGUA/LAPA | AA57: =IFERROR(_xlfn.XLOOKUP(Z57,Rotas!C:C,Rotas!D:D),"0") -> 153 | AB57: =IF(AC57=0,"SUBCONTRATADO","BWT") -> BWT | AC57: {=IFERROR( INDEX( _xlfn._xlws.FILTER( BWT!$C$1:$C$100, ISNUMBER(FIND( SUBSTITUTE(BWT!$C$1:$C$100," ",""), SUBSTITUTE(SUBSTITUTE(SUBSTITUTE(F57," ",""),"-",""),CHAR(160),"") )) ), 1 ), "")} -> BDF9C15
A58: 41260425102812000179570030000008131732805730 | B58: BWT ARAUCARIA - ARAUCARIA | C58: 04/04/2026 | D58: 813 | E58: 1095513 | F58: JCI5E48 - AWZ2403 | G58: JOAO GABRIEL DA CRUZ | H58: PARANAGUA | I58: PR | J58: LAPA | K58: PR | L58: POTENCIAL AGRO S/A - MATRIZ | M58: CATTALINI TERMINAIS MARITIMOS S/A | N58: CATTALINI TERMINAIS MARITIMOS S/A | O58: POTENCIAL AGRO S/A - MATRIZ | P58: POTENCIAL AGRO S/A - MATRIZ | Q58: METANOL - ONU 1230 | R58: 39020 | S58: 58340 | T58: 4007.35 | U58: 4007.35 | V58: 0 | W58: 0 | Z58: =IF(H58&J58="","CT-e COMPLEMENTAR",H58&"/"&J58) -> PARANAGUA/LAPA | AA58: =IFERROR(_xlfn.XLOOKUP(Z58,Rotas!C:C,Rotas!D:D),"0") -> 153 | AB58: =IF(AC58=0,"SUBCONTRATADO","BWT") -> BWT | AC58: {=IFERROR( INDEX( _xlfn._xlws.FILTER( BWT!$C$1:$C$100, ISNUMBER(FIND( SUBSTITUTE(BWT!$C$1:$C$100," ",""), SUBSTITUTE(SUBSTITUTE(SUBSTITUTE(F58," ",""),"-",""),CHAR(160),"") )) ), 1 ), "")} -> AWZ2403
A59: 42260425102812000330570030000000261154988701 | B59: BWT TRANSPORTE E LOGISTICA S. A - ITAJAI | C59: 04/04/2026 | D59: 26 | E59: 411703 | F59: TAW8B87 - JDJ0B76 - JDJ0B57 | G59: VITOR RAFAEL PEDROZO | H59: JOACABA | I59: SC | J59: CUBATAO | K59: SP | L59: VIBRA ENERGIA S.A - FILIAL 100 | M59: ADM DO BRASIL LTDA | N59: ADM DO BRASIL LTDA | O59: VIBRA ENERGIA S.A - FILIAL 100 | P59: VIBRA ENERGIA S.A - FILIAL 100 | Q59: Biodiesel - B100 | R59: 59591 | S59: 52360 | T59: 20992.28 | U59: 18473.21 | V59: 0 | W59: 2519.07 | X59: 0.12 | Y59: 20992.28 | Z59: =IF(H59&J59="","CT-e COMPLEMENTAR",H59&"/"&J59) -> JOACABA/CUBATAO | AA59: =IFERROR(_xlfn.XLOOKUP(Z59,Rotas!C:C,Rotas!D:D),"0") -> 782 | AB59: =IF(AC59=0,"SUBCONTRATADO","BWT") -> BWT | AC59: {=IFERROR( INDEX( _xlfn._xlws.FILTER( BWT!$C$1:$C$100, ISNUMBER(FIND( SUBSTITUTE(BWT!$C$1:$C$100," ",""), SUBSTITUTE(SUBSTITUTE(SUBSTITUTE(F59," ",""),"-",""),CHAR(160),"") )) ), 1 ), "")} -> TAW8B87
A60: 42260425102812000330570030000000271528564597 | B60: BWT TRANSPORTE E LOGISTICA S. A - ITAJAI | C60: 04/04/2026 | D60: 27 | E60: 411706 | F60: BDV9E54 - BDV9E55 - SEY8B40 | G60: ALEX DE OLIVEIRA RODRIGUES | H60: JOACABA | I60: SC | J60: CUBATAO | K60: SP | L60: VIBRA ENERGIA S.A - FILIAL 100 | M60: ADM DO BRASIL LTDA | N60: ADM DO BRASIL LTDA | O60: VIBRA ENERGIA S.A - FILIAL 100 | P60: VIBRA ENERGIA S.A - FILIAL 100 | Q60: Biodiesel - B100 | R60: 56655 | S60: 49760 | T60: 19961.53 | U60: 17566.15 | V60: 0 | W60: 2395.38 | X60: 0.12 | Y60: 19961.53 | Z60: =IF(H60&J60="","CT-e COMPLEMENTAR",H60&"/"&J60) -> JOACABA/CUBATAO | AA60: =IFERROR(_xlfn.XLOOKUP(Z60,Rotas!C:C,Rotas!D:D),"0") -> 782 | AB60: =IF(AC60=0,"SUBCONTRATADO","BWT") -> BWT | AC60: {=IFERROR( INDEX( _xlfn._xlws.FILTER( BWT!$C$1:$C$100, ISNUMBER(FIND( SUBSTITUTE(BWT!$C$1:$C$100," ",""), SUBSTITUTE(SUBSTITUTE(SUBSTITUTE(F60," ",""),"-",""),CHAR(160),"") )) ), 1 ), "")} -> SEY8B40
A61: 43260425102812000250570030000002521276221461 | B61: BWT TRANSPORTE E LOGISTICA S. A - ESTEIO | C61: 04/04/2026 | D61: 252 | E61: 230480 | F61: BDU5F20 - BDU5F25 - SEY8B43 | G61: JOAQUIM RAIMUNDO PORTES JUNIOR | H61: IJUI | I61: RS | J61: PAULINIA | K61: SP | L61: ROYAL FIC DISTRIBUIDORA DE DERIVADO PETROLEO S | M61: CAMERA AGROALIMENTOS S A | N61: CAMERA AGROALIMENTOS S A | O61: ROYAL FIC DISTRIBUIDORA DE DERIVADO PETROLEO S | P61: ROYAL FIC DISTRIBUIDORA DE DERIVADO PETROLEO S | Q61: Biodiesel - B100 | R61: 56356 | S61: 75380 | T61: 15779.68 | U61: 12815.75 | V61: 1070.37 | W61: 1893.56 | X61: 0.12 | Y61: 15779.68 | Z61: =IF(H61&J61="","CT-e COMPLEMENTAR",H61&"/"&J61) -> IJUI/PAULINIA | AA61: =IFERROR(_xlfn.XLOOKUP(Z61,Rotas!C:C,Rotas!D:D),"0") -> 1212 | AB61: =IF(AC61=0,"SUBCONTRATADO","BWT") -> BWT | AC61: {=IFERROR( INDEX( _xlfn._xlws.FILTER( BWT!$C$1:$C$100, ISNUMBER(FIND( SUBSTITUTE(BWT!$C$1:$C$100," ",""), SUBSTITUTE(SUBSTITUTE(SUBSTITUTE(F61," ",""),"-",""),CHAR(160),"") )) ), 1 ), "")} -> SEY8B43
A62: 43260425102812000250570030000002531152702406 | B62: BWT TRANSPORTE E LOGISTICA S. A - ESTEIO | C62: 04/04/2026 | D62: 253 | E62: 230482 | F62: SEE2J87 - RYD5E09 - RYD5D89 | G62: LUIZ CEZAR KELCZESKI | H62: IJUI | I62: RS | J62: PAULINIA | K62: SP | L62: ROYAL FIC DISTRIBUIDORA DE DERIVADO PETROLEO S | M62: CAMERA AGROALIMENTOS S A | N62: CAMERA AGROALIMENTOS S A | O62: ROYAL FIC DISTRIBUIDORA DE DERIVADO PETROLEO S | P62: ROYAL FIC DISTRIBUIDORA DE DERIVADO PETROLEO S | Q62: Biodiesel - B100 | R62: 57345 | S62: 75700 | T62: 16056.6 | U62: 13059.44 | V62: 1070.37 | W62: 1926.79 | X62: 0.12 | Y62: 16056.6 | Z62: =IF(H62&J62="","CT-e COMPLEMENTAR",H62&"/"&J62) -> IJUI/PAULINIA | AA62: =IFERROR(_xlfn.XLOOKUP(Z62,Rotas!C:C,Rotas!D:D),"0") -> 1212 | AB62: =IF(AC62=0,"SUBCONTRATADO","BWT") -> BWT | AC62: {=IFERROR( INDEX( _xlfn._xlws.FILTER( BWT!$C$1:$C$100, ISNUMBER(FIND( SUBSTITUTE(BWT!$C$1:$C$100," ",""), SUBSTITUTE(SUBSTITUTE(SUBSTITUTE(F62," ",""),"-",""),CHAR(160),"") )) ), 1 ), "")} -> SEE2J87
A63: 35260425102812000500570030000002451028456773 | B63: BWT TRANSPORTE E LOGISTICA S. A - PAULINIA | C63: 05/04/2026 | D63: 245 | E63: 30482 | F63: JCI7B71 - BAX9A94 | G63: FRANCISCO ADEMIR MORO JUNIOR | H63: SANTOS | I63: SP | J63: PAULINIA | K63: SP | L63: IPIRANGA PRODUTOS DE PETROLEO S.A. | M63: IPIRANGA PRODUTOS DE PETROLEO S.A. | N63: ULTRACARGO LOGISTICA S.A | O63: IPIRANGA PRODUTOS DE PETROLEO S/A | P63: IPIRANGA PRODUTOS DE PETROLEO S/A | Q63: Diesel S10 A | R63: 45692 | S63: 37920 | T63: 2359.89 | U63: 2076.7 | V63: 0 | W63: 283.19 | X63: 0.12 | Y63: 2359.89 | Z63: =IF(H63&J63="","CT-e COMPLEMENTAR",H63&"/"&J63) -> SANTOS/PAULINIA | AA63: =IFERROR(_xlfn.XLOOKUP(Z63,Rotas!C:C,Rotas!D:D),"0") -> 215 | AB63: =IF(AC63=0,"SUBCONTRATADO","BWT") -> BWT | AC63: {=IFERROR( INDEX( _xlfn._xlws.FILTER( BWT!$C$1:$C$100, ISNUMBER(FIND( SUBSTITUTE(BWT!$C$1:$C$100," ",""), SUBSTITUTE(SUBSTITUTE(SUBSTITUTE(F63," ",""),"-",""),CHAR(160),"") )) ), 1 ), "")} -> BAX9A94
A64: 35260425102812000500570030000002471331650810 | B64: BWT TRANSPORTE E LOGISTICA S. A - PAULINIA | C64: 05/04/2026 | D64: 247 | E64: 30487 | F64: JAV7E00 - SEX2C75 - JAV7E07 | G64: FRANCISCO JOSE ESTEVES | H64: SANTOS | I64: SP | J64: PAULINIA | K64: SP | L64: IPIRANGA PRODUTOS DE PETROLEO S.A. | M64: IPIRANGA PRODUTOS DE PETROLEO S.A. | N64: ULTRACARGO LOGISTICA S.A | O64: IPIRANGA PRODUTOS DE PETROLEO S/A | P64: IPIRANGA PRODUTOS DE PETROLEO S/A | Q64: Diesel S10 A | R64: 59561 | S64: 49114 | T64: 3149.97 | U64: 2771.97 | V64: 0 | W64: 378 | X64: 0.12 | Y64: 3149.97 | Z64: =IF(H64&J64="","CT-e COMPLEMENTAR",H64&"/"&J64) -> SANTOS/PAULINIA | AA64: =IFERROR(_xlfn.XLOOKUP(Z64,Rotas!C:C,Rotas!D:D),"0") -> 215 | AB64: =IF(AC64=0,"SUBCONTRATADO","BWT") -> BWT | AC64: {=IFERROR( INDEX( _xlfn._xlws.FILTER( BWT!$C$1:$C$100, ISNUMBER(FIND( SUBSTITUTE(BWT!$C$1:$C$100," ",""), SUBSTITUTE(SUBSTITUTE(SUBSTITUTE(F64," ",""),"-",""),CHAR(160),"") )) ), 1 ), "")} -> SEX2C75
A65: 35260425102812000500570030000002481245383695 | B65: BWT TRANSPORTE E LOGISTICA S. A - PAULINIA | C65: 05/04/2026 | D65: 248 | E65: 30503 | F65: JBU3A17 - JBU3A10 - SED7D20 | G65: VALDEREZ MAINARDES | H65: SANTOS | I65: SP | J65: PAULINIA | K65: SP | L65: IPIRANGA PRODUTOS DE PETROLEO S.A. | M65: IPIRANGA PRODUTOS DE PETROLEO S.A. | N65: ULTRACARGO LOGISTICA S.A | O65: IPIRANGA PRODUTOS DE PETROLEO S/A | P65: IPIRANGA PRODUTOS DE PETROLEO S/A | Q65: Diesel S10 A | R65: 59863 | S65: 49680 | T65: 3150.3 | U65: 2772.26 | V65: 0 | W65: 378.04 | X65: 0.12 | Y65: 3150.3 | Z65: =IF(H65&J65="","CT-e COMPLEMENTAR",H65&"/"&J65) -> SANTOS/PAULINIA | AA65: =IFERROR(_xlfn.XLOOKUP(Z65,Rotas!C:C,Rotas!D:D),"0") -> 215 | AB65: =IF(AC65=0,"SUBCONTRATADO","BWT") -> BWT | AC65: {=IFERROR( INDEX( _xlfn._xlws.FILTER( BWT!$C$1:$C$100, ISNUMBER(FIND( SUBSTITUTE(BWT!$C$1:$C$100," ",""), SUBSTITUTE(SUBSTITUTE(SUBSTITUTE(F65," ",""),"-",""),CHAR(160),"") )) ), 1 ), "")} -> SED7D20
A66: 35260425102812000500570030000002491346437631 | B66: BWT TRANSPORTE E LOGISTICA S. A - PAULINIA | C66: 05/04/2026 | D66: 249 | E66: 30504 | F66: JCW7D75 - JCX7F40 - TAW8C09 | G66: CLAIR SONAI | H66: SANTOS | I66: SP | J66: PAULINIA | K66: SP | L66: IPIRANGA PRODUTOS DE PETROLEO S.A. | M66: IPIRANGA PRODUTOS DE PETROLEO S.A. | N66: ULTRACARGO LOGISTICA S.A | O66: IPIRANGA PRODUTOS DE PETROLEO S/A | P66: IPIRANGA PRODUTOS DE PETROLEO S/A | Q66: Diesel S10 A | R66: 59755 | S66: 49644 | T66: 3150.03 | U66: 2772.03 | V66: 0 | W66: 378 | X66: 0.12 | Y66: 3150.03 | Z66: =IF(H66&J66="","CT-e COMPLEMENTAR",H66&"/"&J66) -> SANTOS/PAULINIA | AA66: =IFERROR(_xlfn.XLOOKUP(Z66,Rotas!C:C,Rotas!D:D),"0") -> 215 | AB66: =IF(AC66=0,"SUBCONTRATADO","BWT") -> BWT | AC66: {=IFERROR( INDEX( _xlfn._xlws.FILTER( BWT!$C$1:$C$100, ISNUMBER(FIND( SUBSTITUTE(BWT!$C$1:$C$100," ",""), SUBSTITUTE(SUBSTITUTE(SUBSTITUTE(F66," ",""),"-",""),CHAR(160),"") )) ), 1 ), "")} -> TAW8C09
A67: 35260425102812000500570030000002501849438230 | B67: BWT TRANSPORTE E LOGISTICA S. A - PAULINIA | C67: 05/04/2026 | D67: 250 | E67: 30509 | F67: SEE2J90 - RYG6E01 - RYG6D61 | G67: VILSO DE OLIVEIRA COSTA | H67: SANTOS | I67: SP | J67: PAULINIA | K67: SP | L67: IPIRANGA PRODUTOS DE PETROLEO S.A. | M67: IPIRANGA PRODUTOS DE PETROLEO S.A. | N67: ULTRACARGO LOGISTICA S.A | O67: IPIRANGA PRODUTOS DE PETROLEO S/A | P67: IPIRANGA PRODUTOS DE PETROLEO S/A | Q67: Diesel S10 A | R67: 59652 | S67: 49380 | T67: 3150.03 | U67: 2772.03 | V67: 0 | W67: 378 | X67: 0.12 | Y67: 3150.03 | Z67: =IF(H67&J67="","CT-e COMPLEMENTAR",H67&"/"&J67) -> SANTOS/PAULINIA | AA67: =IFERROR(_xlfn.XLOOKUP(Z67,Rotas!C:C,Rotas!D:D),"0") -> 215 | AB67: =IF(AC67=0,"SUBCONTRATADO","BWT") -> BWT | AC67: {=IFERROR( INDEX( _xlfn._xlws.FILTER( BWT!$C$1:$C$100, ISNUMBER(FIND( SUBSTITUTE(BWT!$C$1:$C$100," ",""), SUBSTITUTE(SUBSTITUTE(SUBSTITUTE(F67," ",""),"-",""),CHAR(160),"") )) ), 1 ), "")} -> SEE2J90
A68: 35260425102812000500570030000002511211851020 | B68: BWT TRANSPORTE E LOGISTICA S. A - PAULINIA | C68: 05/04/2026 | D68: 251 | E68: 30510 | F68: JBT6B33 - BDQ4E30 | G68: NEY CESAR WANDERLINDE LEINEKER | H68: SANTOS | I68: SP | J68: PAULINIA | K68: SP | L68: IPIRANGA PRODUTOS DE PETROLEO S.A. | M68: IPIRANGA PRODUTOS DE PETROLEO S.A. | N68: ULTRACARGO LOGISTICA S.A | O68: IPIRANGA PRODUTOS DE PETROLEO S/A | P68: IPIRANGA PRODUTOS DE PETROLEO S/A | Q68: Gasolina A | R68: 49511 | S68: 35712 | T68: 2360.22 | U68: 2076.99 | V68: 0 | W68: 283.23 | X68: 0.12 | Y68: 2360.22 | Z68: =IF(H68&J68="","CT-e COMPLEMENTAR",H68&"/"&J68) -> SANTOS/PAULINIA | AA68: =IFERROR(_xlfn.XLOOKUP(Z68,Rotas!C:C,Rotas!D:D),"0") -> 215 | AB68: =IF(AC68=0,"SUBCONTRATADO","BWT") -> BWT | AC68: {=IFERROR( INDEX( _xlfn._xlws.FILTER( BWT!$C$1:$C$100, ISNUMBER(FIND( SUBSTITUTE(BWT!$C$1:$C$100," ",""), SUBSTITUTE(SUBSTITUTE(SUBSTITUTE(F68," ",""),"-",""),CHAR(160),"") )) ), 1 ), "")} -> BDQ4E30
A69: 35260425102812000500570030000002521933463180 | B69: BWT TRANSPORTE E LOGISTICA S. A - PAULINIA | C69: 05/04/2026 | D69: 252 | E69: 30517 | F69: BBM5I45 - BBQ6I95 | G69: VLADEMIR JORGE SANTOS | H69: SANTOS | I69: SP | J69: PAULINIA | K69: SP | L69: IPIRANGA PRODUTOS DE PETROLEO S.A. | M69: IPIRANGA PRODUTOS DE PETROLEO S.A. | N69: ULTRACARGO LOGISTICA S.A | O69: IPIRANGA PRODUTOS DE PETROLEO S/A | P69: IPIRANGA PRODUTOS DE PETROLEO S/A | Q69: Gasolina A | R69: 44472 | S69: 32078 | T69: 2360.05 | U69: 2076.84 | V69: 0 | W69: 283.21 | X69: 0.12 | Y69: 2360.05 | Z69: =IF(H69&J69="","CT-e COMPLEMENTAR",H69&"/"&J69) -> SANTOS/PAULINIA | AA69: =IFERROR(_xlfn.XLOOKUP(Z69,Rotas!C:C,Rotas!D:D),"0") -> 215 | AB69: =IF(AC69=0,"SUBCONTRATADO","BWT") -> BWT | AC69: {=IFERROR( INDEX( _xlfn._xlws.FILTER( BWT!$C$1:$C$100, ISNUMBER(FIND( SUBSTITUTE(BWT!$C$1:$C$100," ",""), SUBSTITUTE(SUBSTITUTE(SUBSTITUTE(F69," ",""),"-",""),CHAR(160),"") )) ), 1 ), "")} -> BBM5I45
A70: 35260425102812000500570030000002531781474297 | B70: BWT TRANSPORTE E LOGISTICA S. A - PAULINIA | C70: 05/04/2026 | D70: 253 | E70: 30516 | F70: AYP3139 - SEX2C73 - AYP3138 | G70: MARIOVANY QUIRINO GOMES | H70: SANTOS | I70: SP | J70: PAULINIA | K70: SP | L70: IPIRANGA PRODUTOS DE PETROLEO S.A. | M70: IPIRANGA PRODUTOS DE PETROLEO S.A. | N70: ULTRACARGO LOGISTICA S.A | O70: IPIRANGA PRODUTOS DE PETROLEO S/A | P70: IPIRANGA PRODUTOS DE PETROLEO S/A | Q70: Gasolina A | R70: 63013 | S70: 45445 | T70: 3149.93 | U70: 2771.94 | V70: 0 | W70: 377.99 | X70: 0.12 | Y70: 3149.93 | Z70: =IF(H70&J70="","CT-e COMPLEMENTAR",H70&"/"&J70) -> SANTOS/PAULINIA | AA70: =IFERROR(_xlfn.XLOOKUP(Z70,Rotas!C:C,Rotas!D:D),"0") -> 215 | AB70: =IF(AC70=0,"SUBCONTRATADO","BWT") -> BWT | AC70: {=IFERROR( INDEX( _xlfn._xlws.FILTER( BWT!$C$1:$C$100, ISNUMBER(FIND( SUBSTITUTE(BWT!$C$1:$C$100," ",""), SUBSTITUTE(SUBSTITUTE(SUBSTITUTE(F70," ",""),"-",""),CHAR(160),"") )) ), 1 ), "")} -> SEX2C73
A71: 35260425102812000500570030000002541774528546 | B71: BWT TRANSPORTE E LOGISTICA S. A - PAULINIA | C71: 05/04/2026 | D71: 254 | E71: 30524 | F71: SEE0I13 - RYG6E81 - RYG6F31 | G71: ALAOR BATISTA DE FREITAS | H71: SANTOS | I71: SP | J71: PAULINIA | K71: SP | L71: IPIRANGA PRODUTOS DE PETROLEO S.A. | M71: IPIRANGA PRODUTOS DE PETROLEO S.A. | N71: ULTRACARGO LOGISTICA S.A | O71: IPIRANGA PRODUTOS DE PETROLEO S/A | P71: IPIRANGA PRODUTOS DE PETROLEO S/A | Q71: Gasolina A | R71: 63123 | S71: 45417 | T71: 3149.69 | U71: 2771.73 | V71: 0 | W71: 377.96 | X71: 0.12 | Y71: 3149.69 | Z71: =IF(H71&J71="","CT-e COMPLEMENTAR",H71&"/"&J71) -> SANTOS/PAULINIA | AA71: =IFERROR(_xlfn.XLOOKUP(Z71,Rotas!C:C,Rotas!D:D),"0") -> 215 | AB71: =IF(AC71=0,"SUBCONTRATADO","BWT") -> BWT | AC71: {=IFERROR( INDEX( _xlfn._xlws.FILTER( BWT!$C$1:$C$100, ISNUMBER(FIND( SUBSTITUTE(BWT!$C$1:$C$100," ",""), SUBSTITUTE(SUBSTITUTE(SUBSTITUTE(F71," ",""),"-",""),CHAR(160),"") )) ), 1 ), "")} -> SEE0I13
A72: 41260425102812000179570030000008141354487846 | B72: BWT ARAUCARIA - ARAUCARIA | C72: 05/04/2026 | D72: 814 | E72: 79373 | F72: SEE3G48 - JBT6B10 - JBT6B27 | G72: RAFAEL SOUZA MIRANDA | H72: PARANAGUA | I72: PR | J72: LONDRINA | K72: PR | L72: IPIRANGA PRODUTOS DE PETROLEO S.A | M72: IPIRANGA PRODUTOS DE PETROLEO S.A | N72: CATTALINI TERMINAIS MARITIMOS S/A | O72: IPIRANGA PRODUTOS DE PETROLEO S.A. | P72: IPIRANGA PRODUTOS DE PETROLEO S.A. | Q72: Diesel S10 A | R72: 58039 | S72: 47795 | T72: 14857.98 | U72: 14857.98 | V72: 0 | W72: 0 | Z72: =IF(H72&J72="","CT-e COMPLEMENTAR",H72&"/"&J72) -> PARANAGUA/LONDRINA | AA72: =IFERROR(_xlfn.XLOOKUP(Z72,Rotas!C:C,Rotas!D:D),"0") -> 485 | AB72: =IF(AC72=0,"SUBCONTRATADO","BWT") -> BWT | AC72: {=IFERROR( INDEX( _xlfn._xlws.FILTER( BWT!$C$1:$C$100, ISNUMBER(FIND( SUBSTITUTE(BWT!$C$1:$C$100," ",""), SUBSTITUTE(SUBSTITUTE(SUBSTITUTE(F72," ",""),"-",""),CHAR(160),"") )) ), 1 ), "")} -> SEE3G48
A73: 41260425102812000179570030000008201797129415 | B73: BWT ARAUCARIA - ARAUCARIA | C73: 06/04/2026 | D73: 820 | E73: 2665 | F73: SFF3I82 - JCO4B49 - JCO4B32 | G73: ANDRIELIA APARECIDA GOMES | H73: PARANAGUA | I73: PR | J73: MUITOS CAPOES | K73: RS | L73: BOCCHI INDUSTRIA E COMERCIO DE CERE TDA | M73: BWI TRADING COMERCIAL IMPORTADORA E RTADORA LTDA | N73: CATTALINI TERMINAIS MARITIMOS S/A | O73: BOCCHI INDUSTRIA E COMERCIO DE CERE TDA | P73: BOCCHI INDUSTRIA E COMERCIO DE CERE TDA | Q73: METANOL - ONU 1230 | R73: 47780 | S73: 73840 | T73: 10272.7 | U73: 8232.14 | V73: 918 | W73: 1122.56 | X73: 0.12 | Y73: 9354.7 | Z73: =IF(H73&J73="","CT-e COMPLEMENTAR",H73&"/"&J73) -> PARANAGUA/MUITOS CAPOES | AA73: =IFERROR(_xlfn.XLOOKUP(Z73,Rotas!C:C,Rotas!D:D),"0") -> 581 | AB73: =IF(AC73=0,"SUBCONTRATADO","BWT") -> BWT | AC73: {=IFERROR( INDEX( _xlfn._xlws.FILTER( BWT!$C$1:$C$100, ISNUMBER(FIND( SUBSTITUTE(BWT!$C$1:$C$100," ",""), SUBSTITUTE(SUBSTITUTE(SUBSTITUTE(F73," ",""),"-",""),CHAR(160),"") )) ), 1 ), "")} -> SFF3I82
A74: 41260425102812000179570030000008221761121230 | B74: BWT ARAUCARIA - ARAUCARIA | C74: 06/04/2026 | D74: 822 | E74: 2691 | F74: SFF3I76 - JCP3I14 - JCP5G54 | G74: JOSIANE DE FREITAS CABRAL | H74: PARANAGUA | I74: PR | J74: MUITOS CAPOES | K74: RS | L74: BOCCHI INDUSTRIA E COMERCIO DE CERE TDA | M74: BWI TRADING COMERCIAL IMPORTADORA E RTADORA LTDA | N74: CATTALINI TERMINAIS MARITIMOS S/A | O74: BOCCHI INDUSTRIA E COMERCIO DE CERE TDA | P74: BOCCHI INDUSTRIA E COMERCIO DE CERE TDA | Q74: METANOL - ONU 1230 | R74: 47922 | S74: 73842 | T74: 10303.23 | U74: 8532.24 | V74: 607.5 | W74: 1163.49 | X74: 0.12 | Y74: 9695.73 | Z74: =IF(H74&J74="","CT-e COMPLEMENTAR",H74&"/"&J74) -> PARANAGUA/MUITOS CAPOES | AA74: =IFERROR(_xlfn.XLOOKUP(Z74,Rotas!C:C,Rotas!D:D),"0") -> 581 | AB74: =IF(AC74=0,"SUBCONTRATADO","BWT") -> SUBCONTRATADO | AC74: {=IFERROR( INDEX( _xlfn._xlws.FILTER( BWT!$C$1:$C$100, ISNUMBER(FIND( SUBSTITUTE(BWT!$C$1:$C$100," ",""), SUBSTITUTE(SUBSTITUTE(SUBSTITUTE(F74," ",""),"-",""),CHAR(160),"") )) ), 1 ), "")} -> 0
A75: 35260425102812000500570030000002551664915020 | B75: BWT TRANSPORTE E LOGISTICA S. A - PAULINIA | C75: 06/04/2026 | D75: 255 | E75: 30550 | F75: JCM1E27 - SFC5F45 | G75: EMERSON MENON CUNHA | H75: SANTOS | I75: SP | J75: PAULINIA | K75: SP | L75: IPIRANGA PRODUTOS DE PETROLEO S.A. | M75: IPIRANGA PRODUTOS DE PETROLEO S.A. | N75: ULTRACARGO LOGISTICA S.A | O75: IPIRANGA PRODUTOS DE PETROLEO S/A | P75: IPIRANGA PRODUTOS DE PETROLEO S/A | Q75: Gasolina A | R75: 50365 | S75: 36303 | T75: 3150.1 | U75: 2772.09 | V75: 0 | W75: 378.01 | X75: 0.12 | Y75: 3150.1 | Z75: =IF(H75&J75="","CT-e COMPLEMENTAR",H75&"/"&J75) -> SANTOS/PAULINIA | AA75: =IFERROR(_xlfn.XLOOKUP(Z75,Rotas!C:C,Rotas!D:D),"0") -> 215 | AB75: =IF(AC75=0,"SUBCONTRATADO","BWT") -> BWT | AC75: {=IFERROR( INDEX( _xlfn._xlws.FILTER( BWT!$C$1:$C$100, ISNUMBER(FIND( SUBSTITUTE(BWT!$C$1:$C$100," ",""), SUBSTITUTE(SUBSTITUTE(SUBSTITUTE(F75," ",""),"-",""),CHAR(160),"") )) ), 1 ), "")} -> SFC5F45
A76: 35260425102812000500570030000002561706558880 | B76: BWT TRANSPORTE E LOGISTICA S. A - PAULINIA | C76: 06/04/2026 | D76: 256 | E76: 116975 | F76: JBW0G71 - SEE0H97 - JBW0G65 | G76: JOSE CLAUDIO DA CRUZ | H76: IACANGA | I76: SP | J76: ARAUCARIA | K76: PR | L76: IPIRANGA PRODUTOS DE PETROLEO S/A | M76: Cooperativa Prod de Cana-de-AA A ca A A car e | N76: Cooperativa Prod de Cana-de-AA A ca A A car e | O76: IPIRANGA PRODUTOS DE PETROLEO S/A | P76: IPIRANGA PRODUTOS DE PETROLEO S/A | Q76: Etanol Anidro | R76: 59250 | S76: 46.91 | T76: 8338.09 | U76: 7337.52 | V76: 0 | W76: 1000.57 | X76: 0.12 | Y76: 8338.09 | Z76: =IF(H76&J76="","CT-e COMPLEMENTAR",H76&"/"&J76) -> IACANGA/ARAUCARIA | AA76: =IFERROR(_xlfn.XLOOKUP(Z76,Rotas!C:C,Rotas!D:D),"0") -> 580 | AB76: =IF(AC76=0,"SUBCONTRATADO","BWT") -> BWT | AC76: {=IFERROR( INDEX( _xlfn._xlws.FILTER( BWT!$C$1:$C$100, ISNUMBER(FIND( SUBSTITUTE(BWT!$C$1:$C$100," ",""), SUBSTITUTE(SUBSTITUTE(SUBSTITUTE(F76," ",""),"-",""),CHAR(160),"") )) ), 1 ), "")} -> SEE0H97
A77: 35260425102812000500570030000002571012757966 | B77: BWT TRANSPORTE E LOGISTICA S. A - PAULINIA | C77: 06/04/2026 | D77: 257 | E77: 30585 | F77: JDJ2B32 - JDJ2B43 - TAW8B84 | G77: EDENIR MALOSTI PEREIRA | H77: SANTOS | I77: SP | J77: PAULINIA | K77: SP | L77: IPIRANGA PRODUTOS DE PETROLEO S.A. | M77: IPIRANGA PRODUTOS DE PETROLEO S.A. | N77: ULTRACARGO LOGISTICA S.A | O77: IPIRANGA PRODUTOS DE PETROLEO S/A | P77: IPIRANGA PRODUTOS DE PETROLEO S/A | Q77: Gasolina A | R77: 63291 | S77: 44297 | T77: 3150.17 | U77: 2772.15 | V77: 0 | W77: 378.02 | X77: 0.12 | Y77: 3150.17 | Z77: =IF(H77&J77="","CT-e COMPLEMENTAR",H77&"/"&J77) -> SANTOS/PAULINIA | AA77: =IFERROR(_xlfn.XLOOKUP(Z77,Rotas!C:C,Rotas!D:D),"0") -> 215 | AB77: =IF(AC77=0,"SUBCONTRATADO","BWT") -> BWT | AC77: {=IFERROR( INDEX( _xlfn._xlws.FILTER( BWT!$C$1:$C$100, ISNUMBER(FIND( SUBSTITUTE(BWT!$C$1:$C$100," ",""), SUBSTITUTE(SUBSTITUTE(SUBSTITUTE(F77," ",""),"-",""),CHAR(160),"") )) ), 1 ), "")} -> TAW8B84
A78: 35260425102812000500570030000002581469490165 | B78: BWT TRANSPORTE E LOGISTICA S. A - PAULINIA | C78: 06/04/2026 | D78: 258 | E78: 30615 | F78: JAP8F48 - SFA7F70 - JAP8F56 | G78: PAULO ROBERTO EVANGELISTA SOARES | H78: SANTOS | I78: SP | J78: PAULINIA | K78: SP | L78: IPIRANGA PRODUTOS DE PETROLEO S.A. | M78: IPIRANGA PRODUTOS DE PETROLEO S.A. | N78: ULTRACARGO LOGISTICA S.A | O78: IPIRANGA PRODUTOS DE PETROLEO S/A | P78: IPIRANGA PRODUTOS DE PETROLEO S/A | Q78: Gasolina A | R78: 61077 | S78: 44024 | T78: 3150.33 | U78: 2772.29 | V78: 0 | W78: 378.04 | X78: 0.12 | Y78: 3150.33 | Z78: =IF(H78&J78="","CT-e COMPLEMENTAR",H78&"/"&J78) -> SANTOS/PAULINIA | AA78: =IFERROR(_xlfn.XLOOKUP(Z78,Rotas!C:C,Rotas!D:D),"0") -> 215 | AB78: =IF(AC78=0,"SUBCONTRATADO","BWT") -> BWT | AC78: {=IFERROR( INDEX( _xlfn._xlws.FILTER( BWT!$C$1:$C$100, ISNUMBER(FIND( SUBSTITUTE(BWT!$C$1:$C$100," ",""), SUBSTITUTE(SUBSTITUTE(SUBSTITUTE(F78," ",""),"-",""),CHAR(160),"") )) ), 1 ), "")} -> SFA7F70
A79: 41260425102812000179570030000008151468961277 | B79: BWT ARAUCARIA - ARAUCARIA | C79: 06/04/2026 | D79: 815 | E79: 2703 | F79: BBQ6I94 - BBM8G62 | G79: LUIZ GERVASIO STROPARO | H79: PARANAGUA | I79: PR | J79: ORTIGUEIRA | K79: PR | L79: BWI TRADING COMERCIAL IMPORTADORA E RTADORA LTDA | M79: BWI TRADING COMERCIAL IMPORTADORA E RTADORA LTDA | N79: CATTALINI TERMINAIS MARITIMOS S/A | O79: KLABIN S.A. | P79: KLABIN S.A. | Q79: METANOL - ONU 1230 | R79: 34696 | S79: 54456 | T79: 9142.05 | U79: 8757.45 | V79: 384.6 | W79: 0 | Z79: =IF(H79&J79="","CT-e COMPLEMENTAR",H79&"/"&J79) -> PARANAGUA/ORTIGUEIRA | AA79: =IFERROR(_xlfn.XLOOKUP(Z79,Rotas!C:C,Rotas!D:D),"0") -> 354 | AB79: =IF(AC79=0,"SUBCONTRATADO","BWT") -> BWT | AC79: {=IFERROR( INDEX( _xlfn._xlws.FILTER( BWT!$C$1:$C$100, ISNUMBER(FIND( SUBSTITUTE(BWT!$C$1:$C$100," ",""), SUBSTITUTE(SUBSTITUTE(SUBSTITUTE(F79," ",""),"-",""),CHAR(160),"") )) ), 1 ), "")} -> BBM8G62
A80: 41260425102812000179570030000008161357257641 | B80: BWT ARAUCARIA - ARAUCARIA | C80: 06/04/2026 | D80: 816 | E80: 1095915 | F80: BBM5I48 | G80: FERNANDO JOSE CARVALHO | H80: PARANAGUA | I80: PR | J80: LAPA | K80: PR | L80: POTENCIAL AGRO S/A - MATRIZ | M80: CATTALINI TERMINAIS MARITIMOS S/A | N80: CATTALINI TERMINAIS MARITIMOS S/A | O80: POTENCIAL AGRO S/A - MATRIZ | P80: POTENCIAL AGRO S/A - MATRIZ | Q80: METANOL - ONU 1230 | R80: 38400 | S80: 58260 | T80: 3943.68 | U80: 3943.68 | V80: 0 | W80: 0 | Z80: =IF(H80&J80="","CT-e COMPLEMENTAR",H80&"/"&J80) -> PARANAGUA/LAPA | AA80: =IFERROR(_xlfn.XLOOKUP(Z80,Rotas!C:C,Rotas!D:D),"0") -> 153 | AB80: =IF(AC80=0,"SUBCONTRATADO","BWT") -> BWT | AC80: {=IFERROR( INDEX( _xlfn._xlws.FILTER( BWT!$C$1:$C$100, ISNUMBER(FIND( SUBSTITUTE(BWT!$C$1:$C$100," ",""), SUBSTITUTE(SUBSTITUTE(SUBSTITUTE(F80," ",""),"-",""),CHAR(160),"") )) ), 1 ), "")} -> BBM5I48
A81: 41260425102812000179570030000008171300775306 | B81: BWT ARAUCARIA - ARAUCARIA | C81: 06/04/2026 | D81: 817 | E81: 278422 | F81: RYG6B41 - RYG6D01 - SED7D05 | G81: JOEL RODYCZ | H81: PARANACITY | I81: PR | J81: ITAJAI | K81: SC | L81: IPIRANGA PRODUTOS DE PETROLEO S.A | M81: USINA DE ACUCAR SANTA TEREZINHA LTD | N81: USINA DE ACUCAR SANTA TEREZINHA LTD | O81: IPIRANGA PRODUTOS DE PETROLEO S.A | P81: IPIRANGA PRODUTOS DE PETROLEO S.A | Q81: Etanol Hidratado | R81: 58168 | S81: 47180 | T81: 10246.16 | U81: 9016.62 | V81: 0 | W81: 1229.54 | X81: 0.12 | Y81: 10246.16 | Z81: =IF(H81&J81="","CT-e COMPLEMENTAR",H81&"/"&J81) -> PARANACITY/ITAJAI | AA81: =IFERROR(_xlfn.XLOOKUP(Z81,Rotas!C:C,Rotas!D:D),"0") -> 716 | AB81: =IF(AC81=0,"SUBCONTRATADO","BWT") -> SUBCONTRATADO | AC81: {=IFERROR( INDEX( _xlfn._xlws.FILTER( BWT!$C$1:$C$100, ISNUMBER(FIND( SUBSTITUTE(BWT!$C$1:$C$100," ",""), SUBSTITUTE(SUBSTITUTE(SUBSTITUTE(F81," ",""),"-",""),CHAR(160),"") )) ), 1 ), "")} -> 0
A82: 41260425102812000179570030000008181206542554 | B82: BWT ARAUCARIA - ARAUCARIA | C82: 06/04/2026 | D82: 818 | E82: 1095999 | F82: SEE0I38 - JBW6D87 - JBW6D88 | G82: FELIPE NUNES | H82: PARANAGUA | I82: PR | J82: IJUI | K82: RS | L82: CAMERA AGROALIMENTOS S A | M82: CATTALINI TERMINAIS MARITIMOS S/A | N82: CATTALINI TERMINAIS MARITIMOS S/A | O82: CAMERA AGROALIMENTOS S A | P82: CAMERA AGROALIMENTOS S A | Q82: METANOL - ONU 1230 | R82: 48060 | S82: 73860 | T82: 10765.44 | U82: 8900.97 | V82: 650.7 | W82: 1213.77 | X82: 0.12 | Y82: 10114.74 | Z82: =IF(H82&J82="","CT-e COMPLEMENTAR",H82&"/"&J82) -> PARANAGUA/IJUI | AA82: =IFERROR(_xlfn.XLOOKUP(Z82,Rotas!C:C,Rotas!D:D),"0") -> 800 | AB82: =IF(AC82=0,"SUBCONTRATADO","BWT") -> BWT | AC82: {=IFERROR( INDEX( _xlfn._xlws.FILTER( BWT!$C$1:$C$100, ISNUMBER(FIND( SUBSTITUTE(BWT!$C$1:$C$100," ",""), SUBSTITUTE(SUBSTITUTE(SUBSTITUTE(F82," ",""),"-",""),CHAR(160),"") )) ), 1 ), "")} -> SEE0I38
A83: 41260425102812000179570030000008191156750105 | B83: BWT ARAUCARIA - ARAUCARIA | C83: 06/04/2026 | D83: 819 | E83: 2709 - 2710 | F83: JAO3A97 - SFC5F71 - JAO3A88 | G83: RENATO GASPARELLO | H83: PARANAGUA | I83: PR | J83: MUITOS CAPOES | K83: RS | L83: BOCCHI INDUSTRIA E COMERCIO DE CERE TDA | M83: BWI TRADING COMERCIAL IMPORTADORA E RTADORA LTDA | N83: CATTALINI TERMINAIS MARITIMOS S/A | O83: BOCCHI INDUSTRIA E COMERCIO DE CERE TDA | P83: BOCCHI INDUSTRIA E COMERCIO DE CERE TDA | Q83: METANOL - ONU 1230 | R83: 48220 | S83: 73820 | T83: 10367.3 | U83: 8588.62 | V83: 607.5 | W83: 1171.18 | X83: 0.12 | Y83: 9759.8 | Z83: =IF(H83&J83="","CT-e COMPLEMENTAR",H83&"/"&J83) -> PARANAGUA/MUITOS CAPOES | AA83: =IFERROR(_xlfn.XLOOKUP(Z83,Rotas!C:C,Rotas!D:D),"0") -> 581 | AB83: =IF(AC83=0,"SUBCONTRATADO","BWT") -> BWT | AC83: {=IFERROR( INDEX( _xlfn._xlws.FILTER( BWT!$C$1:$C$100, ISNUMBER(FIND( SUBSTITUTE(BWT!$C$1:$C$100," ",""), SUBSTITUTE(SUBSTITUTE(SUBSTITUTE(F83," ",""),"-",""),CHAR(160),"") )) ), 1 ), "")} -> SFC5F71
A84: 41260425102812000179570030000008211667124100 | B84: BWT ARAUCARIA - ARAUCARIA | C84: 06/04/2026 | D84: 821 | E84: 1096020 | F84: BDQ4E39 | G84: WERNER DUCK | H84: PARANAGUA | I84: PR | J84: LAPA | K84: PR | L84: POTENCIAL AGRO S/A - MATRIZ | M84: CATTALINI TERMINAIS MARITIMOS S/A | N84: CATTALINI TERMINAIS MARITIMOS S/A | O84: POTENCIAL AGRO S/A - MATRIZ | P84: POTENCIAL AGRO S/A - MATRIZ | Q84: METANOL - ONU 1230 | R84: 47772 | S84: 73792 | T84: 4378.3 | U84: 4378.3 | V84: 0 | W84: 0 | Z84: =IF(H84&J84="","CT-e COMPLEMENTAR",H84&"/"&J84) -> PARANAGUA/LAPA | AA84: =IFERROR(_xlfn.XLOOKUP(Z84,Rotas!C:C,Rotas!D:D),"0") -> 153 | AB84: =IF(AC84=0,"SUBCONTRATADO","BWT") -> BWT | AC84: {=IFERROR( INDEX( _xlfn._xlws.FILTER( BWT!$C$1:$C$100, ISNUMBER(FIND( SUBSTITUTE(BWT!$C$1:$C$100," ",""), SUBSTITUTE(SUBSTITUTE(SUBSTITUTE(F84," ",""),"-",""),CHAR(160),"") )) ), 1 ), "")} -> BDQ4E39
A85: 41260425102812000179570030000008231496480670 | B85: BWT ARAUCARIA - ARAUCARIA | C85: 06/04/2026 | D85: 823 | E85: 1096031 | F85: JCW7C11 - JCW7D87 - TAW2A61 | G85: ALCIONE DE CASTRO | H85: PARANAGUA | I85: PR | J85: IJUI | K85: RS | L85: CAMERA AGROALIMENTOS S A | M85: CATTALINI TERMINAIS MARITIMOS S/A | N85: CATTALINI TERMINAIS MARITIMOS S/A | O85: CAMERA AGROALIMENTOS S A | P85: CAMERA AGROALIMENTOS S A | Q85: METANOL - ONU 1230 | R85: 48409 | S85: 73889 | T85: 10843.62 | U85: 8969.77 | V85: 650.7 | W85: 1223.15 | X85: 0.12 | Y85: 10192.92 | Z85: =IF(H85&J85="","CT-e COMPLEMENTAR",H85&"/"&J85) -> PARANAGUA/IJUI | AA85: =IFERROR(_xlfn.XLOOKUP(Z85,Rotas!C:C,Rotas!D:D),"0") -> 800 | AB85: =IF(AC85=0,"SUBCONTRATADO","BWT") -> BWT | AC85: {=IFERROR( INDEX( _xlfn._xlws.FILTER( BWT!$C$1:$C$100, ISNUMBER(FIND( SUBSTITUTE(BWT!$C$1:$C$100," ",""), SUBSTITUTE(SUBSTITUTE(SUBSTITUTE(F85," ",""),"-",""),CHAR(160),"") )) ), 1 ), "")} -> TAW2A61
A86: 41260425102812000179570030000008241197313761 | B86: BWT ARAUCARIA - ARAUCARIA | C86: 06/04/2026 | D86: 824 | E86: 1096032 | F86: BDF9C15 - JCH2G41 | G86: GUSTAVO ANTONIO NOGUEIRA | H86: PARANAGUA | I86: PR | J86: LAPA | K86: PR | L86: POTENCIAL AGRO S/A - MATRIZ | M86: CATTALINI TERMINAIS MARITIMOS S/A | N86: CATTALINI TERMINAIS MARITIMOS S/A | O86: POTENCIAL AGRO S/A - MATRIZ | P86: POTENCIAL AGRO S/A - MATRIZ | Q86: METANOL - ONU 1230 | R86: 38384 | S86: 58344 | T86: 3942.04 | U86: 3942.04 | V86: 0 | W86: 0 | Z86: =IF(H86&J86="","CT-e COMPLEMENTAR",H86&"/"&J86) -> PARANAGUA/LAPA | AA86: =IFERROR(_xlfn.XLOOKUP(Z86,Rotas!C:C,Rotas!D:D),"0") -> 153 | AB86: =IF(AC86=0,"SUBCONTRATADO","BWT") -> BWT | AC86: {=IFERROR( INDEX( _xlfn._xlws.FILTER( BWT!$C$1:$C$100, ISNUMBER(FIND( SUBSTITUTE(BWT!$C$1:$C$100," ",""), SUBSTITUTE(SUBSTITUTE(SUBSTITUTE(F86," ",""),"-",""),CHAR(160),"") )) ), 1 ), "")} -> BDF9C15
A87: 41260425102812000179570030000008251720508604 | B87: BWT ARAUCARIA - ARAUCARIA | C87: 06/04/2026 | D87: 825 | E87: 1096037 | F87: JCI5E48 - AWZ2403 | G87: JOAO GABRIEL DA CRUZ | H87: PARANAGUA | I87: PR | J87: LAPA | K87: PR | L87: POTENCIAL AGRO S/A - MATRIZ | M87: CATTALINI TERMINAIS MARITIMOS S/A | N87: CATTALINI TERMINAIS MARITIMOS S/A | O87: POTENCIAL AGRO S/A - MATRIZ | P87: POTENCIAL AGRO S/A - MATRIZ | Q87: METANOL - ONU 1230 | R87: 39084 | S87: 58284 | T87: 4013.93 | U87: 4013.93 | V87: 0 | W87: 0 | Z87: =IF(H87&J87="","CT-e COMPLEMENTAR",H87&"/"&J87) -> PARANAGUA/LAPA | AA87: =IFERROR(_xlfn.XLOOKUP(Z87,Rotas!C:C,Rotas!D:D),"0") -> 153 | AB87: =IF(AC87=0,"SUBCONTRATADO","BWT") -> BWT | AC87: {=IFERROR( INDEX( _xlfn._xlws.FILTER( BWT!$C$1:$C$100, ISNUMBER(FIND( SUBSTITUTE(BWT!$C$1:$C$100," ",""), SUBSTITUTE(SUBSTITUTE(SUBSTITUTE(F87," ",""),"-",""),CHAR(160),"") )) ), 1 ), "")} -> AWZ2403
A88: 41260425102812000179570030000008261880798667 | B88: BWT ARAUCARIA - ARAUCARIA | C88: 06/04/2026 | D88: 826 | E88: 79450 | F88: JAS4J43 - JAS4J59 - RHI3D46 | G88: ELENILDO GOMES DA SILVA | H88: PARANAGUA | I88: PR | J88: PASSO FUNDO | K88: RS | L88: IPIRANGA PRODUTOS DE PETROLEO S.A | M88: IPIRANGA PRODUTOS DE PETROLEO S.A | N88: CATTALINI TERMINAIS MARITIMOS S/A | O88: IPIRANGA PRODUTOS DE PETROLEO S.A. | P88: IPIRANGA PRODUTOS DE PETROLEO S.A. | Q88: Diesel S10 A | R88: 58563 | S88: 48262 | T88: 12298.23 | U88: 12298.23 | V88: 0 | W88: 0 | Z88: =IF(H88&J88="","CT-e COMPLEMENTAR",H88&"/"&J88) -> PARANAGUA/PASSO FUNDO | AA88: =IFERROR(_xlfn.XLOOKUP(Z88,Rotas!C:C,Rotas!D:D),"0") -> 636 | AB88: =IF(AC88=0,"SUBCONTRATADO","BWT") -> BWT | AC88: {=IFERROR( INDEX( _xlfn._xlws.FILTER( BWT!$C$1:$C$100, ISNUMBER(FIND( SUBSTITUTE(BWT!$C$1:$C$100," ",""), SUBSTITUTE(SUBSTITUTE(SUBSTITUTE(F88," ",""),"-",""),CHAR(160),"") )) ), 1 ), "")} -> RHI3D46
A89: 35260325102812000500570030000001631023134220 | B89: BWT TRANSPORTE E LOGISTICA S. A - PAULINIA | C89: 07/04/2026 | D89: 259 | F89: SEE2J87 - RYD5E09 - RYD5D89 | G89: LUIZ CEZAR KELCZESKI | I89: SP | K89: RS | L89: IPIRANGA PRODUTOS DE PETROLEO S/A | M89: Cooperativa Prod de Cana-de-AA A ca A A car e | N89: Cooperativa Prod de Cana-de-AA A ca A A car e | O89: IPIRANGA PRODUTOS DE PETROLEO S/A | P89: IPIRANGA PRODUTOS DE PETROLEO S/A | T89: 163.87 | U89: 163.87 | V89: 0 | W89: 0 | X89: 0.12 | Y89: 163.87 | Z89: =IF(H89&J89="","CT-e COMPLEMENTAR",H89&"/"&J89) -> CT-e COMPLEMENTAR | AA89: =IFERROR(_xlfn.XLOOKUP(Z89,Rotas!C:C,Rotas!D:D),"0") -> 0 | AB89: =IF(AC89=0,"SUBCONTRATADO","BWT") -> BWT | AC89: {=IFERROR( INDEX( _xlfn._xlws.FILTER( BWT!$C$1:$C$100, ISNUMBER(FIND( SUBSTITUTE(BWT!$C$1:$C$100," ",""), SUBSTITUTE(SUBSTITUTE(SUBSTITUTE(F89," ",""),"-",""),CHAR(160),"") )) ), 1 ), "")} -> SEE2J87
A90: 35260325102812000500570030000001651564818518 | B90: BWT TRANSPORTE E LOGISTICA S. A - PAULINIA | C90: 07/04/2026 | D90: 261 | F90: BDU5F24 - BDU5F23 - SER6B09 | G90: RICARDO FERREIRA DOS SANTOS | I90: SP | K90: RS | L90: IPIRANGA PRODUTOS DE PETROLEO S/A | M90: Cooperativa Prod de Cana-de-AA A ca A A car e | N90: Cooperativa Prod de Cana-de-AA A ca A A car e | O90: IPIRANGA PRODUTOS DE PETROLEO S/A | P90: IPIRANGA PRODUTOS DE PETROLEO S/A | T90: 194.01 | U90: 194.01 | V90: 0 | W90: 0 | X90: 0.12 | Y90: 194.01 | Z90: =IF(H90&J90="","CT-e COMPLEMENTAR",H90&"/"&J90) -> CT-e COMPLEMENTAR | AA90: =IFERROR(_xlfn.XLOOKUP(Z90,Rotas!C:C,Rotas!D:D),"0") -> 0 | AB90: =IF(AC90=0,"SUBCONTRATADO","BWT") -> BWT | AC90: {=IFERROR( INDEX( _xlfn._xlws.FILTER( BWT!$C$1:$C$100, ISNUMBER(FIND( SUBSTITUTE(BWT!$C$1:$C$100," ",""), SUBSTITUTE(SUBSTITUTE(SUBSTITUTE(F90," ",""),"-",""),CHAR(160),"") )) ), 1 ), "")} -> SER6B09
A91: 35260325102812000500570030000001851149565162 | B91: BWT TRANSPORTE E LOGISTICA S. A - PAULINIA | C91: 07/04/2026 | D91: 263 | F91: BBD0E82 - BBD0E81 - RHH5C95 | G91: REINALDO FERNEDA | I91: SP | K91: RS | L91: IPIRANGA PRODUTOS DE PETROLEO S/A | M91: COOPERATIVA DE PRODUTORES DE CANA-D ACUCAR, ACUCAR E ALCOOL | N91: COOPERATIVA DE PRODUTORES DE CANA-D ACUCAR, ACUCAR E ALCOOL | O91: IPIRANGA PRODUTOS DE PETROLEO S/A | P91: IPIRANGA PRODUTOS DE PETROLEO S/A | T91: 172.54 | U91: 172.54 | V91: 0 | W91: 0 | X91: 0.12 | Y91: 172.54 | Z91: =IF(H91&J91="","CT-e COMPLEMENTAR",H91&"/"&J91) -> CT-e COMPLEMENTAR | AA91: =IFERROR(_xlfn.XLOOKUP(Z91,Rotas!C:C,Rotas!D:D),"0") -> 0 | AB91: =IF(AC91=0,"SUBCONTRATADO","BWT") -> BWT | AC91: {=IFERROR( INDEX( _xlfn._xlws.FILTER( BWT!$C$1:$C$100, ISNUMBER(FIND( SUBSTITUTE(BWT!$C$1:$C$100," ",""), SUBSTITUTE(SUBSTITUTE(SUBSTITUTE(F91," ",""),"-",""),CHAR(160),"") )) ), 1 ), "")} -> RHH5C95
A92: 35260325102812000500570030000001911495688835 | B92: BWT TRANSPORTE E LOGISTICA S. A - PAULINIA | C92: 07/04/2026 | D92: 262 | F92: AYP3139 - SEX2C73 - AYP3138 | G92: MARIOVANY QUIRINO GOMES | I92: SP | K92: RS | L92: IPIRANGA PRODUTOS DE PETROLEO S/A | M92: Cooperativa Prod de Cana-de-AA A ca A A car e | N92: Cooperativa Prod de Cana-de-AA A ca A A car e | O92: IPIRANGA PRODUTOS DE PETROLEO S/A | P92: IPIRANGA PRODUTOS DE PETROLEO S/A | T92: 226.03 | U92: 226.03 | V92: 0 | W92: 0 | X92: 0.12 | Y92: 226.03 | Z92: =IF(H92&J92="","CT-e COMPLEMENTAR",H92&"/"&J92) -> CT-e COMPLEMENTAR | AA92: =IFERROR(_xlfn.XLOOKUP(Z92,Rotas!C:C,Rotas!D:D),"0") -> 0 | AB92: =IF(AC92=0,"SUBCONTRATADO","BWT") -> BWT | AC92: {=IFERROR( INDEX( _xlfn._xlws.FILTER( BWT!$C$1:$C$100, ISNUMBER(FIND( SUBSTITUTE(BWT!$C$1:$C$100," ",""), SUBSTITUTE(SUBSTITUTE(SUBSTITUTE(F92," ",""),"-",""),CHAR(160),"") )) ), 1 ), "")} -> SEX2C73
A93: 35260425102812000500570030000002641315020603 | B93: BWT TRANSPORTE E LOGISTICA S. A - PAULINIA | C93: 07/04/2026 | D93: 264 | E93: 30683 | F93: BDQ4E29 - IZW8A03 - IZW8A02 | G93: LUIZ CARLOS COELHO | H93: SANTOS | I93: SP | J93: PAULINIA | K93: SP | L93: IPIRANGA PRODUTOS DE PETROLEO S.A. | M93: IPIRANGA PRODUTOS DE PETROLEO S.A. | N93: VOPAK BRASIL S.A. | O93: IPIRANGA PRODUTOS DE PETROLEO S/A | P93: IPIRANGA PRODUTOS DE PETROLEO S/A | Q93: Gasolina A | R93: 63212 | S93: 45500 | T93: 3149.83 | U93: 2771.85 | V93: 0 | W93: 377.98 | X93: 0.12 | Y93: 3149.83 | Z93: =IF(H93&J93="","CT-e COMPLEMENTAR",H93&"/"&J93) -> SANTOS/PAULINIA | AA93: =IFERROR(_xlfn.XLOOKUP(Z93,Rotas!C:C,Rotas!D:D),"0") -> 215 | AB93: =IF(AC93=0,"SUBCONTRATADO","BWT") -> BWT | AC93: {=IFERROR( INDEX( _xlfn._xlws.FILTER( BWT!$C$1:$C$100, ISNUMBER(FIND( SUBSTITUTE(BWT!$C$1:$C$100," ",""), SUBSTITUTE(SUBSTITUTE(SUBSTITUTE(F93," ",""),"-",""),CHAR(160),"") )) ), 1 ), "")} -> BDQ4E29
A94: 35260425102812000500570030000002651188808972 | B94: BWT TRANSPORTE E LOGISTICA S. A - PAULINIA | C94: 07/04/2026 | D94: 265 | E94: 774291 | F94: BBM8G18 - RHH5C92 - BBM8G17 | G94: CLAUDEMIR SOARES | H94: SANTOS | I94: SP | J94: CIANORTE | K94: PR | L94: CIAPETRO DISTRIBUIDORA DE COMBUSTIV TDA | M94: CIAPETRO DISTRIBUIDORA DE COMBUSTIV TDA | N94: Stolthaven Santos Ltda. | O94: CIAPETRO DISTRIBUIDORA DE COMBUSTIV TDA | P94: CIAPETRO DISTRIBUIDORA DE COMBUSTIV TDA | Q94: Gasolina A | R94: 60715 | S94: 42719.07 | T94: 8500.1 | U94: 7480.09 | V94: 0 | W94: 1020.01 | X94: 0.12 | Y94: 8500.1 | Z94: =IF(H94&J94="","CT-e COMPLEMENTAR",H94&"/"&J94) -> SANTOS/CIANORTE | AA94: =IFERROR(_xlfn.XLOOKUP(Z94,Rotas!C:C,Rotas!D:D),"0") -> 794 | AB94: =IF(AC94=0,"SUBCONTRATADO","BWT") -> BWT | AC94: {=IFERROR( INDEX( _xlfn._xlws.FILTER( BWT!$C$1:$C$100, ISNUMBER(FIND( SUBSTITUTE(BWT!$C$1:$C$100," ",""), SUBSTITUTE(SUBSTITUTE(SUBSTITUTE(F94," ",""),"-",""),CHAR(160),"") )) ), 1 ), "")} -> RHH5C92
A95: 35260425102812000500570030000002661046824649 | B95: BWT TRANSPORTE E LOGISTICA S. A - PAULINIA | C95: 07/04/2026 | D95: 266 | E95: 30697 | F95: JBU5G53 - SEE2J86 - JBU5H02 | G95: LUIZ CARLOS COELHO | H95: SANTOS | I95: SP | J95: PAULINIA | K95: SP | L95: IPIRANGA PRODUTOS DE PETROLEO S.A. | M95: IPIRANGA PRODUTOS DE PETROLEO S.A. | N95: VOPAK BRASIL S.A. | O95: IPIRANGA PRODUTOS DE PETROLEO S/A | P95: IPIRANGA PRODUTOS DE PETROLEO S/A | Q95: Gasolina A | R95: 61241 | S95: 44118 | T95: 3149.74 | U95: 2771.77 | V95: 0 | W95: 377.97 | X95: 0.12 | Y95: 3149.74 | Z95: =IF(H95&J95="","CT-e COMPLEMENTAR",H95&"/"&J95) -> SANTOS/PAULINIA | AA95: =IFERROR(_xlfn.XLOOKUP(Z95,Rotas!C:C,Rotas!D:D),"0") -> 215 | AB95: =IF(AC95=0,"SUBCONTRATADO","BWT") -> BWT | AC95: {=IFERROR( INDEX( _xlfn._xlws.FILTER( BWT!$C$1:$C$100, ISNUMBER(FIND( SUBSTITUTE(BWT!$C$1:$C$100," ",""), SUBSTITUTE(SUBSTITUTE(SUBSTITUTE(F95," ",""),"-",""),CHAR(160),"") )) ), 1 ), "")} -> SEE2J86
A96: 35260425102812000500570030000002671174983208 | B96: BWT TRANSPORTE E LOGISTICA S. A - PAULINIA | C96: 07/04/2026 | D96: 267 | E96: 30708 | F96: JAV7E00 - SEX2C75 - JAV7E07 | G96: FRANCISCO JOSE ESTEVES | H96: SANTOS | I96: SP | J96: PAULINIA | K96: SP | L96: IPIRANGA PRODUTOS DE PETROLEO S.A. | M96: IPIRANGA PRODUTOS DE PETROLEO S.A. | N96: VOPAK BRASIL S.A. | O96: IPIRANGA PRODUTOS DE PETROLEO S/A | P96: IPIRANGA PRODUTOS DE PETROLEO S/A | Q96: Gasolina A | R96: 63309 | S96: 45570 | T96: 3150.34 | U96: 2772.3 | V96: 0 | W96: 378.04 | X96: 0.12 | Y96: 3150.34 | Z96: =IF(H96&J96="","CT-e COMPLEMENTAR",H96&"/"&J96) -> SANTOS/PAULINIA | AA96: =IFERROR(_xlfn.XLOOKUP(Z96,Rotas!C:C,Rotas!D:D),"0") -> 215 | AB96: =IF(AC96=0,"SUBCONTRATADO","BWT") -> BWT | AC96: {=IFERROR( INDEX( _xlfn._xlws.FILTER( BWT!$C$1:$C$100, ISNUMBER(FIND( SUBSTITUTE(BWT!$C$1:$C$100," ",""), SUBSTITUTE(SUBSTITUTE(SUBSTITUTE(F96," ",""),"-",""),CHAR(160),"") )) ), 1 ), "")} -> SEX2C75
A97: 35260425102812000500570030000002681273526481 | B97: BWT TRANSPORTE E LOGISTICA S. A - PAULINIA | C97: 07/04/2026 | D97: 268 | E97: 30721 | F97: TAW8C01 - RYF3A30 - RYF2J90 | G97: ROBERTO RIVELINO CABRAL | H97: SANTOS | I97: SP | J97: PAULINIA | K97: SP | L97: IPIRANGA PRODUTOS DE PETROLEO S.A. | M97: IPIRANGA PRODUTOS DE PETROLEO S.A. | N97: VOPAK BRASIL S.A. | O97: IPIRANGA PRODUTOS DE PETROLEO S/A | P97: IPIRANGA PRODUTOS DE PETROLEO S/A | Q97: Gasolina A | R97: 61281 | S97: 44110 | T97: 3149.7 | U97: 2771.74 | V97: 0 | W97: 377.96 | X97: 0.12 | Y97: 3149.7 | Z97: =IF(H97&J97="","CT-e COMPLEMENTAR",H97&"/"&J97) -> SANTOS/PAULINIA | AA97: =IFERROR(_xlfn.XLOOKUP(Z97,Rotas!C:C,Rotas!D:D),"0") -> 215 | AB97: =IF(AC97=0,"SUBCONTRATADO","BWT") -> BWT | AC97: {=IFERROR( INDEX( _xlfn._xlws.FILTER( BWT!$C$1:$C$100, ISNUMBER(FIND( SUBSTITUTE(BWT!$C$1:$C$100," ",""), SUBSTITUTE(SUBSTITUTE(SUBSTITUTE(F97," ",""),"-",""),CHAR(160),"") )) ), 1 ), "")} -> TAW8C01
A98: 35260425102812000500570030000002691014474989 | B98: BWT TRANSPORTE E LOGISTICA S. A - PAULINIA | C98: 07/04/2026 | D98: 269 | E98: 30722 | F98: JBT6B33 - BDQ4E30 | G98: NEY CESAR WANDERLINDE LEINEKER | H98: SANTOS | I98: SP | J98: PAULINIA | K98: SP | L98: IPIRANGA PRODUTOS DE PETROLEO S.A. | M98: IPIRANGA PRODUTOS DE PETROLEO S.A. | N98: VOPAK BRASIL S.A. | O98: IPIRANGA PRODUTOS DE PETROLEO S/A | P98: IPIRANGA PRODUTOS DE PETROLEO S/A | Q98: Gasolina A | R98: 49350 | S98: 35552 | T98: 2359.83 | U98: 2076.65 | V98: 0 | W98: 283.18 | X98: 0.12 | Y98: 2359.83 | Z98: =IF(H98&J98="","CT-e COMPLEMENTAR",H98&"/"&J98) -> SANTOS/PAULINIA | AA98: =IFERROR(_xlfn.XLOOKUP(Z98,Rotas!C:C,Rotas!D:D),"0") -> 215 | AB98: =IF(AC98=0,"SUBCONTRATADO","BWT") -> BWT | AC98: {=IFERROR( INDEX( _xlfn._xlws.FILTER( BWT!$C$1:$C$100, ISNUMBER(FIND( SUBSTITUTE(BWT!$C$1:$C$100," ",""), SUBSTITUTE(SUBSTITUTE(SUBSTITUTE(F98," ",""),"-",""),CHAR(160),"") )) ), 1 ), "")} -> BDQ4E30
A99: 41260325102812000179570030000004651999730485 | B99: BWT ARAUCARIA - ARAUCARIA | C99: 07/04/2026 | D99: 828 | F99: JAS1A99 - JAS0J82 - SFA7G28 | G99: EDUARDO RAFAEL BORGES | I99: PR | K99: SC | L99: IPIRANGA PRODUTOS DE PETROLEO S.A | M99: USINA ALTO ALEGRE S.A - ACUCAR E AL | N99: USINA ALTO ALEGRE S.A - ACUCAR E AL | O99: IPIRANGA PRODUTOS DE PETROLEO S.A | P99: IPIRANGA PRODUTOS DE PETROLEO S.A | T99: 72.79 | U99: 72.79 | V99: 0 | W99: 0 | X99: 0.12 | Y99: 72.79 | Z99: =IF(H99&J99="","CT-e COMPLEMENTAR",H99&"/"&J99) -> CT-e COMPLEMENTAR | AA99: =IFERROR(_xlfn.XLOOKUP(Z99,Rotas!C:C,Rotas!D:D),"0") -> 0 | AB99: =IF(AC99=0,"SUBCONTRATADO","BWT") -> BWT | AC99: {=IFERROR( INDEX( _xlfn._xlws.FILTER( BWT!$C$1:$C$100, ISNUMBER(FIND( SUBSTITUTE(BWT!$C$1:$C$100," ",""), SUBSTITUTE(SUBSTITUTE(SUBSTITUTE(F99," ",""),"-",""),CHAR(160),"") )) ), 1 ), "")} -> SFA7G28
A100: 41260325102812000179570030000005691492954650 | B100: BWT ARAUCARIA - ARAUCARIA | C100: 07/04/2026 | D100: 829 | F100: BDQ4E39 | G100: LUIZ CARLOS COELHO | I100: PR | K100: PR | L100: IPIRANGA PRODUTOS DE PETROLEO S/A | M100: IPIRANGA PRODUTOS DE PETROLEO S/A | N100: IPIRANGA PRODUTOS DE PETROLEO S/A | O100: IPIRANGA PRODUTOS DE PETROLEO S.A | P100: IPIRANGA PRODUTOS DE PETROLEO S.A | T100: 215.98 | U100: 215.98 | V100: 0 | W100: 0 | Z100: =IF(H100&J100="","CT-e COMPLEMENTAR",H100&"/"&J100) -> CT-e COMPLEMENTAR | AA100: =IFERROR(_xlfn.XLOOKUP(Z100,Rotas!C:C,Rotas!D:D),"0") -> 0 | AB100: =IF(AC100=0,"SUBCONTRATADO","BWT") -> BWT | AC100: {=IFERROR( INDEX( _xlfn._xlws.FILTER( BWT!$C$1:$C$100, ISNUMBER(FIND( SUBSTITUTE(BWT!$C$1:$C$100," ",""), SUBSTITUTE(SUBSTITUTE(SUBSTITUTE(F100," ",""),"-",""),CHAR(160),"") )) ), 1 ), "")} -> BDQ4E39
A101: 41260425102812000179570030000008271018522559 | B101: BWT ARAUCARIA - ARAUCARIA | C101: 07/04/2026 | D101: 827 | E101: 79457 | F101: TAW8B90 - JDJ6D53 - JDJ6D33 | G101: DEIZE CRISTINA WEILER | H101: PARANAGUA | I101: PR | J101: PASSO FUNDO | K101: RS | L101: IPIRANGA PRODUTOS DE PETROLEO S.A | M101: IPIRANGA PRODUTOS DE PETROLEO S.A | N101: CATTALINI TERMINAIS MARITIMOS S/A | O101: IPIRANGA PRODUTOS DE PETROLEO S.A. | P101: IPIRANGA PRODUTOS DE PETROLEO S.A. | Q101: Diesel S10 A | R101: 59421 | S101: 48999 | T101: 12478.41 | U101: 12478.41 | V101: 0 | W101: 0 | X101: 0.12 | Y101: 12478.41 | Z101: =IF(H101&J101="","CT-e COMPLEMENTAR",H101&"/"&J101) -> PARANAGUA/PASSO FUNDO | AA101: =IFERROR(_xlfn.XLOOKUP(Z101,Rotas!C:C,Rotas!D:D),"0") -> 636 | AB101: =IF(AC101=0,"SUBCONTRATADO","BWT") -> BWT | AC101: {=IFERROR( INDEX( _xlfn._xlws.FILTER( BWT!$C$1:$C$100, ISNUMBER(FIND( SUBSTITUTE(BWT!$C$1:$C$100," ",""), SUBSTITUTE(SUBSTITUTE(SUBSTITUTE(F101," ",""),"-",""),CHAR(160),"") )) ), 1 ), "")} -> TAW8B90
...

Sheet Telemetria Sighra
A1: TRANSPORTADORA | B1: MOTORISTA | C1: DATA_INICIAL | D1: DATA_FINAL | E1: VEICULO | F1: PLACA | G1: MODELO | H1: KM RODADO | I1: CONSUMO EM LITROS | J1: CONSUMO MEDIO | K1: HODOMETRO INICIAL | L1: HODOMETRO FINAL | M1: MOTOR LIGADO PARADO | N1: TEMPO FAIXA VERDE | O1: TEMPO FAIXA AZUL | P1: TEMPO FAIXA AMARELA | Q1: TEMPO FAIXA VERMELHA | R1: Hodometro | S1: media | T1: MOTORISTA
A2: BWT TRANSPORTE E LOGISTICA S.A - GRUPO POTENCIAL | B2: DANIEL EUFRAZIO - 245 | C2: 46113.298 | D2: 46124.827 | E2: 206337 | F2: BDQ4E18 | G2: FH 540 | H2: 1671.19 | I2: 1292.22 | J2: 1.29327 | K2: 542897.13 | L2: 544568.13 | M2: 11.86 | N2: 13.56 | O2: 1.63 | P2: 8.32 | Q2: 0 | R2: =L2-K2 -> 1671 | S2: =H2/I2 -> 1.2932705 | T2: =TRIM(B2) -> DANIEL EUFRAZIO - 245
A3: BWT TRANSPORTE E LOGISTICA S.A - GRUPO POTENCIAL | B3: ADRIANO DAGNON - 247 | C3: 46113.338 | D3: 46125.323 | E3: 205347 | F3: BDQ4E19 | G3: FH 540 | H3: 3022.03 | I3: 1914.53 | J3: 1.578471 | K3: 532718.85 | L3: 535740.71 | M3: 12.15 | N3: 29.59 | O3: 3.66 | P3: 10.09 | Q3: 0 | R3: =L3-K3 -> 3021.86 | S3: =H3/I3 -> 1.578471 | T3: =TRIM(B3) -> ADRIANO DAGNON - 247
A4: BWT TRANSPORTE E LOGISTICA S.A - GRUPO POTENCIAL | B4: ALCIONE DE CASTRO - 180 | C4: 46113.269 | D4: 46123.54 | E4: 229986 | F4: TAW2A61 | G4: FH 500 | H4: 3325.54 | I4: 2053.83 | J4: 1.61919 | K4: 90628.8 | L4: 93957.88 | M4: 4.58 | N4: 35.97 | O4: 1.31 | P4: 5.97 | Q4: 0 | R4: =L4-K4 -> 3329.08 | S4: =H4/I4 -> 1.6191895 | T4: =TRIM(B4) -> ALCIONE DE CASTRO - 180
A5: BWT TRANSPORTE E LOGISTICA S.A - GRUPO POTENCIAL | B5: ALEX DE OLIVEIRA RODRIGUES - 50100 | C5: 46113.325 | D5: 46124.574 | E5: 192839 | F5: SEY8B40 | G5: XF FTT 530 | H5: 3763.74 | I5: 2327.86 | J5: 1.616824 | K5: 185122 | L5: 188885.48 | M5: 4.79 | N5: 35.31 | O5: 2.54 | P5: 9.54 | Q5: 0 | R5: =L5-K5 -> 3763.48 | S5: =H5/I5 -> 1.616824 | T5: =TRIM(B5) -> ALEX DE OLIVEIRA RODRIGUES - 50100
A6: BWT TRANSPORTE E LOGISTICA S.A - GRUPO POTENCIAL | B6: AMAURI DOS SANTOS PEREIRA - 240 | C6: 46113.319 | D6: 46122.428 | E6: 229501 | F6: TAW8B89 | G6: FH 500 | H6: 2396.15 | I6: 1361.57 | J6: 1.759843 | K6: 107526.61 | L6: 109922.57 | M6: 2.46 | N6: 28.89 | O6: 0.43 | P6: 0.34 | Q6: 0 | R6: =L6-K6 -> 2395.96 | S6: =H6/I6 -> 1.7598434 | T6: =TRIM(B6) -> AMAURI DOS SANTOS PEREIRA - 240
A7: BWT TRANSPORTE E LOGISTICA S.A - GRUPO POTENCIAL | B7: ANDRIELIA APARECIDA GOMES - 238 | C7: 46113.25 | D7: 46120.677 | E7: 200789 | F7: SFF3I82 | G7: XF530 | H7: 1783.25 | I7: 1373.76 | J7: 1.29808 | K7: 145832.57 | L7: 147615.66 | M7: 6.74 | N7: 16.1 | O7: 1.81 | P7: 7.73 | Q7: 0 | R7: =L7-K7 -> 1783.09 | S7: =H7/I7 -> 1.2980797 | T7: =TRIM(B7) -> ANDRIELIA APARECIDA GOMES - 238
A8: BWT TRANSPORTE E LOGISTICA S.A - GRUPO POTENCIAL | B8: ANDRIELIA APARECIDA GOMES - 238 | C8: 46113.448 | D8: 46124.723 | E8: 199555 | F8: SEE2J90 | G8: XF530 | H8: 2482.83 | I8: 1406.75 | J8: 1.76494 | K8: 232246.73 | L8: 234729.35 | M8: 15.73 | N8: 26.36 | O8: 4.48 | P8: 4.44 | Q8: 0 | R8: =L8-K8 -> 2482.62 | S8: =H8/I8 -> 1.7649405 | T8: =TRIM(B8) -> ANDRIELIA APARECIDA GOMES - 238
